Workbook

Sheet Sessions
A1: MTC session catalog
A2: 134 session records . Filter by focus area, tags, or review status . Repeated offerings are grouped
A4: Session ID | B4: Session title | C4: Short description | D4: Primary focus | E4: Additional focus areas | F4: Topic tags | G4: Documented date(s) | H4: Program(s) | I4: Offerings | J4: Review needed | K4: Source URL | L4: Session folder URL (latest offering)
A5: MTC-001 | B5: 3-Act Math Tasks | C5: Experience a three-act task about draining a pool and examine how a visual question, needed information, and a reveal support mathematical modeling. | D5: Teaching & Learning | E5: Mathematical Modeling | F5: 3-Act tasks; Desmos; questioning; modeling | G5: 2021-06-17 | H5: Summer Institute | I5: =COUNTIF(Offerings!$B$5:$B$145,A5) -> 1 | J5: =IF(COUNTIFS(Offerings!$B$5:$B$145,A5,Offerings!$K$5:$K$145,"Yes")>0,"Yes","No") -> No | K5: https://docs.google.com/presentation/d/1n_7f4sxYuztvXVN8gZ-NnK-xv4gQRV5r_x4P9LyLR2A/edit?usp=drivesdk | L5: https://drive.google.com/drive/folders/1e2q-g-xXdeIYu1vMIBuR4E2F1yCZiMxQ
A6: MTC-002 | B6: 4-Game Night | C6: Compare strategies and possible generalizations across four games: The Child and the Witch, Nim, The Fox and the Rabbit, and The Rook Game. | D6: Game Theory | E6: Logic & Proof | F6: Nim; rook game; fox and rabbit; child and witch | G6: 2024-02-06 | H6: MTC academic-year session | I6: =COUNTIF(Offerings!$B$5:$B$145,A6) -> 1 | J6: =IF(COUNTIFS(Offerings!$B$5:$B$145,A6,Offerings!$K$5:$K$145,"Yes")>0,"Yes","No") -> No | K6: https://drive.google.com/file/d/1zL70vEoZ6Aae0qdb6JW5lnACC4mTBQaa/view?usp=drivesdk | L6: https://drive.google.com/drive/folders/1gUdo__wtMXb0xibi5HdtlAkjX3OzRTI1
A7: MTC-003 | B7: Addressing Unfinished Learning | C7: Explore ways to address unfinished learning with an equity mindset and collaborate on instructional plans. | D7: Teaching & Learning | F7: equity; unfinished learning; instructional planning | G7: 2022-01-22 | H7: PLUS Math | I7: =COUNTIF(Offerings!$B$5:$B$145,A7) -> 1 | J7: =IF(COUNTIFS(Offerings!$B$5:$B$145,A7,Offerings!$K$5:$K$145,"Yes")>0,"Yes","No") -> No | K7: https://drive.google.com/file/d/1bASee8-xo4xHQZQi3HM7F3FOFzsfH4TX/view?usp=drivesdk | L7: https://drive.google.com/drive/folders/1iaJ8EXGtfXLv8gjdcBmZKyAShomA-9JP
A8: MTC-004 | B8: Alternate Algorithms | C8: Compare alternative addition and multiplication methods, including lattice algorithms, partial products, and stick multiplication. | D8: Number Sense & Arithmetic | E8: Teaching & Learning | F8: lattice arithmetic; partial products; multiple methods | G8: 2018-06-18 to 2018-06-21 (institute window) | H8: Summer Institute | I8: =COUNTIF(Offerings!$B$5:$B$145,A8) -> 1 | J8: =IF(COUNTIFS(Offerings!$B$5:$B$145,A8,Offerings!$K$5:$K$145,"Yes")>0,"Yes","No") -> Yes | K8: https://docs.google.com/presentation/d/1u6vBmLM7voR7AKzROirAZsQji_7M82HC/edit?usp=drivesdk&ouid=109901495158487957834&rtpof=true&sd=true | L8: https://drive.google.com/drive/folders/1SdYWc2admzVtcf9FW5D6I12sTV-2Ivi4
A9: MTC-006 | B9: Assess, Activate, and Build on Prior Knowledge | C9: Use math-vocabulary activities and structured reading discussion to consider how instruction can assess, activate, and build on students’ prior knowledge. | D9: Teaching & Learning | F9: ICUCARE; prior knowledge; math vocabulary; Catch Phrase | G9: 2025-06-13 | H9: Summer Institute | I9: =COUNTIF(Offerings!$B$5:$B$145,A9) -> 1 | J9: =IF(COUNTIFS(Offerings!$B$5:$B$145,A9,Offerings!$K$5:$K$145,"Yes")>0,"Yes","No") -> No | K9: https://docs.google.com/presentation/d/1ScAfRKcWWTDrnk6C2kW1XyS0nk0lEoGq/edit?usp=drivesdk&ouid=109901495158487957834&rtpof=true&sd=true | L9: https://drive.google.com/drive/folders/1jiWrWvgndwUoN-3kKi7cHTNb1bV9KyRS
A10: MTC-007 | B10: Assessing Mathematical Modeling | C10: Discuss assessment of mathematical modeling using the assigned GAIMME reading and a collaborative response activity. | D10: Teaching & Learning | E10: Mathematical Modeling | F10: assessment; GAIMME; modeling | G10: 2021-06-18 | H10: Summer Institute | I10: =COUNTIF(Offerings!$B$5:$B$145,A10) -> 1 | J10: =IF(COUNTIFS(Offerings!$B$5:$B$145,A10,Offerings!$K$5:$K$145,"Yes")>0,"Yes","No") -> No | K10: https://docs.google.com/document/d/1XgBPtwa7dVUiBdYAa1nvv7DqLhWe7ho8BS23HndmozU/edit?usp=drivesdk | L10: https://drive.google.com/drive/folders/1jMaUXv_moFqp4vPk7rMqgcL-NFSsSY0E
A11: MTC-008 | B11: Big Numbers | C11: Build and compare very large numbers using exponentiation and factorials, and examine ways to represent quantities too large to write digit by digit. | D11: Number Sense & Arithmetic | E11: Algebra | F11: exponents; factorials; growth rates; large numbers | G11: 2026-03-03 | H11: MTC academic-year session | I11: =COUNTIF(Offerings!$B$5:$B$145,A11) -> 1 | J11: =IF(COUNTIFS(Offerings!$B$5:$B$145,A11,Offerings!$K$5:$K$145,"Yes")>0,"Yes","No") -> No | K11: https://drive.google.com/file/d/14zGzB4zObSrzZB6b3P96l2fWO2xcnhwA/view?usp=drivesdk | L11: https://drive.google.com/drive/folders/1Lh8pWV2kc1VTG6jOyfqx_ZarEunyXWkU
A12: MTC-009 | B12: Blind Stork: Collecting and Modeling Data | C12: Collect balance-test data, choose appropriate visualizations, and use Desmos to explore statistical summaries and relationships. | D12: Probability & Statistics | E12: Mathematical Modeling | F12: Desmos; data collection; graph selection; regression | G12: 2023-06-20 | H12: Summer Institute | I12: =COUNTIF(Offerings!$B$5:$B$145,A12) -> 1 | J12: =IF(COUNTIFS(Offerings!$B$5:$B$145,A12,Offerings!$K$5:$K$145,"Yes")>0,"Yes","No") -> No | K12: https://docs.google.com/presentation/d/1eBBhuPUH1Sk8yqbKnEZNtrYFpvk6s9e8/edit?usp=drivesdk&ouid=109901495158487957834&rtpof=true&sd=true | L12: https://drive.google.com/drive/folders/1NVpERNtguPK1wdF3QHYUFpueMv7iabZH
A13: MTC-010 | B13: Blokus and Polyominoes | C13: Play Blokus and investigate the geometry and tiling properties of polyominoes. | D13: Geometry | E13: Combinatorics | F13: polyominoes; tiling; Blokus | G13: 2018-11-06 | H13: MTC academic-year session | I13: =COUNTIF(Offerings!$B$5:$B$145,A13) -> 1 | J13: =IF(COUNTIFS(Offerings!$B$5:$B$145,A13,Offerings!$K$5:$K$145,"Yes")>0,"Yes","No") -> No | K13: https://drive.google.com/file/d/11LMWsczRyxmNkLaP_2Zb_5QISDRARhAM/view?usp=drivesdk | L13: https://drive.google.com/drive/folders/1i6fFH73dedn7uE3D5CrxC0mC5dTf-zL8
A14: MTC-011 | B14: Bringing Data into Classrooms | C14: Investigate participant car-survey data using one-variable and multivariable questions, then discuss how to bring data investigations into classrooms. | D14: Probability & Statistics | E14: Teaching & Learning | F14: GAISE II; survey data; Google Sheets; statistical questions | G14: 2023-06-22 | H14: Summer Institute | I14: =COUNTIF(Offerings!$B$5:$B$145,A14) -> 1 | J14: =IF(COUNTIFS(Offerings!$B$5:$B$145,A14,Offerings!$K$5:$K$145,"Yes")>0,"Yes","No") -> No | K14: https://docs.google.com/presentation/d/1K2tmaLErEVOhhciOyIDLkyqm0f5y_t4qHGoiHP-xoK8/edit?usp=drivesdk | L14: https://drive.google.com/drive/folders/1fbqt59z4P4_XYyOWhZAfhpE3u8oeSetz
A15: MTC-012 | B15: Bubbling Cauldrons | C15: Place successive integers into cauldrons so that no two numbers in a cauldron add to a third number there, then vary the number of cauldrons and starting value. | D15: Combinatorics | E15: Number Theory | F15: sum-free sets; constraints; generalization | G15: 2022-03-01 | H15: MTC academic-year session | I15: =COUNTIF(Offerings!$B$5:$B$145,A15) -> 1 | J15: =IF(COUNTIFS(Offerings!$B$5:$B$145,A15,Offerings!$K$5:$K$145,"Yes")>0,"Yes","No") -> No | K15: https://drive.google.com/file/d/14bi8fihcIm4Args2WhVR4CV7iAsAnimL/view?usp=drivesdk | L15: https://drive.google.com/drive/folders/1S5El3eNXpjIllIZfOLvcKPqZt-7IHb44
A16: MTC-013 | B16: Bulgarian Solitaire | C16: Rearrange piles of counters according to Bulgarian Solitaire rules and investigate stable configurations, cycles, and ways to classify arrangements. | D16: Algebra | E16: Combinatorics | F16: dynamical systems; partitions; cycles | G16: 2019-09-03 | H16: MTC academic-year session | I16: =COUNTIF(Offerings!$B$5:$B$145,A16) -> 1 | J16: =IF(COUNTIFS(Offerings!$B$5:$B$145,A16,Offerings!$K$5:$K$145,"Yes")>0,"Yes","No") -> No | K16: https://drive.google.com/file/d/1gfAyb62Hqiwmjzht8VDSoYEYMegTx87L/view?usp=drivesdk | L16: https://drive.google.com/drive/folders/11SA0qc1_8-DXGqh_XV_yRZnR-bkzOPXu
A17: MTC-014 | B17: Candy Sharing | C17: Play a repeated candy-sharing game and investigate when the process stabilizes, repeats, or continues indefinitely. | D17: Algebra | E17: Algorithms & Computing | F17: dynamical systems; iteration; cycles | G17: 2017-11-07 | H17: MTC academic-year session | I17: =COUNTIF(Offerings!$B$5:$B$145,A17) -> 1 | J17: =IF(COUNTIFS(Offerings!$B$5:$B$145,A17,Offerings!$K$5:$K$145,"Yes")>0,"Yes","No") -> No | K17: https://drive.google.com/file/d/0B4cCTfJeL7_dNG1SRGJIUWh4R2c/view?usp=drivesdk&resourcekey=0-jEyNsfAltNj9lA6QZChKPQ | L17: https://drive.google.com/drive/folders/0B4cCTfJeL7_demd3d3RFTkZKWnM?resourcekey=0-MzT-jVW9rtLCFP_7rXBvcw
A18: MTC-016 | B18: Connecting Math, Community, and Equity Through Tax Rates | C18: Investigate tax brackets and rates through a relevant modeling task, then connect the activity with peer expertise and knowledge of students. | D18: Algebra | E18: Mathematical Modeling; Teaching & Learning | F18: tax rates; financial literacy; ICUCARE; equity | G18: 2025-06-17 | H18: Summer Institute | I18: =COUNTIF(Offerings!$B$5:$B$145,A18) -> 1 | J18: =IF(COUNTIFS(Offerings!$B$5:$B$145,A18,Offerings!$K$5:$K$145,"Yes")>0,"Yes","No") -> No | K18: https://docs.google.com/presentation/d/14r7xF06YREoURZK8WDV20sgtxwqRhS9q/edit?usp=drivesdk&ouid=109901495158487957834&rtpof=true&sd=true | L18: https://drive.google.com/drive/folders/11vxjmRb0TS8JFvDvhD_iZ-EzytMid970
A19: MTC-017 | B19: Create Your Own Graph Talk | C19: Select or create a graph, anticipate questions, and plan how to facilitate a graph talk with students. | D19: Teaching & Learning | E19: Probability & Statistics | F19: graph talks; CODAP; task design | G19: 2023-06-21 | H19: Summer Institute | I19: =COUNTIF(Offerings!$B$5:$B$145,A19) -> 1 | J19: =IF(COUNTIFS(Offerings!$B$5:$B$145,A19,Offerings!$K$5:$K$145,"Yes")>0,"Yes","No") -> No | K19: https://docs.google.com/presentation/d/1LWIWmJ3EBrNjSHOYKbrKgh5hV4SagZqu/edit?usp=drivesdk&ouid=109901495158487957834&rtpof=true&sd=true | L19: https://drive.google.com/drive/folders/1PT_C7BaoICdlpDmqhk9gb7LKcbGW-VWR
A20: MTC-018 | B20: Criss Cross | C20: Play a line-drawing game on a triangular board and use relationships among vertices, edges, and faces to predict the winner. | D20: Graph Theory | E20: Game Theory; Logic & Proof | F20: planar graphs; Euler’s formula; parity | G20: 2019-06-20 to 2019-06-21 (review) | H20: Summer Institute | I20: =COUNTIF(Offerings!$B$5:$B$145,A20) -> 1 | J20: =IF(COUNTIFS(Offerings!$B$5:$B$145,A20,Offerings!$K$5:$K$145,"Yes")>0,"Yes","No") -> Yes | K20: https://drive.google.com/file/d/1wZBu9JjpnZc-_lNGFN8W4n1F9bUGb0un/view?usp=drivesdk | L20: https://drive.google.com/drive/folders/1NsrdraSpycoqCkhd5WqHbz2EyQAug4eW
A21: MTC-020 | B21: Designing Leadership, Coaching, and Learning Activities | C21: Plan a learning activity by identifying participants, goals, prior knowledge, and evidence of learning, then develop opportunities for active participation. | D21: Teaching & Learning | F21: backward design; coaching; professional learning | G21: 2026-06-15 to 2026-06-18 | H21: Summer Institute | I21: =COUNTIF(Offerings!$B$5:$B$145,A21) -> 1 | J21: =IF(COUNTIFS(Offerings!$B$5:$B$145,A21,Offerings!$K$5:$K$145,"Yes")>0,"Yes","No") -> No | K21: https://docs.google.com/document/d/1thTVuqYvy2QVlGlKgaeSSTik83Pc0ks0/edit?usp=drivesdk&ouid=109901495158487957834&rtpof=true&sd=true | L21: https://drive.google.com/drive/folders/1p_V_zMd7U5Usmmm_pc1ghlzTvB84LP-G
A22: MTC-021 | B22: Desmos: More than Graphing Curves | C22: Connect graphs, equations, and everyday situations, then use Desmos to represent personal experiences with functions and inequalities. | D22: Algebra | E22: Teaching & Learning | F22: Desmos; functions; representations; social justice | G22: 2020-06-26 | H22: Summer Institute | I22: =COUNTIF(Offerings!$B$5:$B$145,A22) -> 1 | J22: =IF(COUNTIFS(Offerings!$B$5:$B$145,A22,Offerings!$K$5:$K$145,"Yes")>0,"Yes","No") -> No | K22: https://drive.google.com/file/d/1Sh_xE5MoDkGr3KBG0lJk_wxq0kbGjDNI/view?usp=drivesdk | L22: https://drive.google.com/drive/folders/1M9dECAjNKbC9FGv_ypUoRPws0u6-LvNK
A23: MTC-022 | B23: Duck Duck Deduce! | C23: Use a circle-elimination game and Eleusis to develop conjectures, infer hidden rules, and practice constructing and critiquing mathematical arguments. | D23: Logic & Proof | E23: Teaching & Learning | F23: Eleusis; Josephus problem; SMP 3; mathematical argument | G23: 2024-12-03 | H23: MTC academic-year session | I23: =COUNTIF(Offerings!$B$5:$B$145,A23) -> 1 | J23: =IF(COUNTIFS(Offerings!$B$5:$B$145,A23,Offerings!$K$5:$K$145,"Yes")>0,"Yes","No") -> No | K23: https://drive.google.com/file/d/1nlSqHlNUYJxRIN2NhdNYJvhPmxM9ZQVc/view?usp=drivesdk | L23: https://drive.google.com/drive/folders/1qQpotvZVNfbISnL2MH9cFcBqC7ggXoq7
A24: MTC-023 | B24: Día de los Muertos and the Mathematics of Musical Groups | C24: Connect Día de los Muertos traditions with mathematical activities, including counting and representing different ways to form musical groups. | D24: Combinatorics | E24: Teaching & Learning | F24: cultural connections; counting; music | G24: 2025-11-04 | H24: MTC academic-year session | I24: =COUNTIF(Offerings!$B$5:$B$145,A24) -> 1 | J24: =IF(COUNTIFS(Offerings!$B$5:$B$145,A24,Offerings!$K$5:$K$145,"Yes")>0,"Yes","No") -> No | K24: https://drive.google.com/file/d/1ccSH5xy64xUybrrpRCfaii4DTrYg7Jkm/view?usp=drivesdk | L24: https://drive.google.com/drive/folders/1MgvnN2dqgEB6Lxpe372rpWqGBQlOUy5g
A25: MTC-025 | B25: Eleusis | C25: Infer a secret rule from legal and illegal card plays, testing and refining conjectures as new evidence becomes available. | D25: Logic & Proof | E25: Number Theory | F25: inductive reasoning; hidden rules; card games | G25: 2019-06-20 to 2019-06-21 (institute window) | H25: Summer Institute | I25: =COUNTIF(Offerings!$B$5:$B$145,A25) -> 1 | J25: =IF(COUNTIFS(Offerings!$B$5:$B$145,A25,Offerings!$K$5:$K$145,"Yes")>0,"Yes","No") -> Yes | K25: https://docs.google.com/presentation/d/1eWTlS74T3knkqT6S_U0QG41FVvl8RVxy/edit?usp=drivesdk&ouid=109901495158487957834&rtpof=true&sd=true | L25: https://drive.google.com/drive/folders/1nc7RfHAErgH-D9djo1jgGfxKw29-k9zM
A26: MTC-026 | B26: Empowering Students Through WODB | C26: Explore and design Which One Doesn’t Belong tasks that support multiple justifications, student ownership, and high expectations. | D26: Teaching & Learning | E26: Logic & Proof | F26: Which One Doesn’t Belong; ICUCARE; student agency; discourse | G26: 2025-06-16 | H26: Summer Institute | I26: =COUNTIF(Offerings!$B$5:$B$145,A26) -> 1 | J26: =IF(COUNTIFS(Offerings!$B$5:$B$145,A26,Offerings!$K$5:$K$145,"Yes")>0,"Yes","No") -> No | K26: https://drive.google.com/file/d/1eqejz5FAttFI-D-_rCoygjtJkY4gr_6E/view?usp=drivesdk | L26: https://drive.google.com/drive/folders/15qE3uYckxLBJmV2cdP55IN15uY3jW_CB
A27: MTC-027 | B27: Estimathon | C27: Work in teams to estimate ranges for real-world quantities and use related estimates to improve accuracy and game strategy. | D27: Number Sense & Arithmetic | E27: Mathematical Modeling | F27: estimation; intervals; collaboration | G27: 2017-10-03 | H27: MTC academic-year session | I27: =COUNTIF(Offerings!$B$5:$B$145,A27) -> 1 | J27: =IF(COUNTIFS(Offerings!$B$5:$B$145,A27,Offerings!$K$5:$K$145,"Yes")>0,"Yes","No") -> No | K27: https://drive.google.com/file/d/0B4cCTfJeL7_dV0lNaHRySThBV1k/view?usp=drivesdk&resourcekey=0-4tLGwO-rngRT5TqyiZh4jw | L27: https://drive.google.com/drive/folders/0B4cCTfJeL7_dYkh0eHhlc1o5dVE?resourcekey=0-mQ9ZVlb8YaF0fKERKMu7-w
A28: MTC-028 | B28: Euler and Hamilton: Two Travelers | C28: Investigate routes that use every road or visit every destination and connect travel problems with graph theory. | D28: Graph Theory | E28: Algorithms & Computing | F28: Euler paths; Hamilton paths; networks | G28: 2020-02-04 (review) | H28: MTC academic-year session | I28: =COUNTIF(Offerings!$B$5:$B$145,A28) -> 1 | J28: =IF(COUNTIFS(Offerings!$B$5:$B$145,A28,Offerings!$K$5:$K$145,"Yes")>0,"Yes","No") -> Yes | K28: https://drive.google.com/file/d/1NUoohDIE7En8mNXJFO17YY8SFLMBh-Aw/view?usp=drivesdk | L28: https://drive.google.com/drive/folders/14m4-qQdf7br8-tagTwB4Q7nAJD-OTZnQ
A29: MTC-029 | B29: Exploding Dots | C29: Use dots-and-boxes machines to model number bases and arithmetic, then extend the representation to polynomial operations and infinite expansions. | D29: Number Sense & Arithmetic | E29: Algebra | F29: place value; number bases; arithmetic; polynomials | G29: 2018-06-18 to 2018-06-19 | H29: Summer Institute | I29: =COUNTIF(Offerings!$B$5:$B$145,A29) -> 1 | J29: =IF(COUNTIFS(Offerings!$B$5:$B$145,A29,Offerings!$K$5:$K$145,"Yes")>0,"Yes","No") -> No | K29: https://docs.google.com/presentation/d/1Xt1UGnUBeJ4dzoaQai64-gyIFavAC_P4/edit?usp=drivesdk&ouid=109901495158487957834&rtpof=true&sd=true | L29: https://drive.google.com/drive/folders/1fTD9nzVBBx-KwkD0_11w5IIrpzxiWWck
A30: MTC-030 | B30: Exploring Traffic Stop Data | C30: Investigate Los Angeles traffic-stop data, compare counts and rates across groups, and consider what additional evidence is needed to interpret disparities. | D30: Probability & Statistics | E30: Mathematical Modeling | F30: CODAP; traffic stops; conditional rates; social justice | G30: 2023-06-22 | H30: Summer Institute | I30: =COUNTIF(Offerings!$B$5:$B$145,A30) -> 1 | J30: =IF(COUNTIFS(Offerings!$B$5:$B$145,A30,Offerings!$K$5:$K$145,"Yes")>0,"Yes","No") -> No | K30: https://docs.google.com/presentation/d/1l0tgXLu1QdG2sz09KWIyXSdB9CKesD0v/edit?usp=drivesdk&ouid=109901495158487957834&rtpof=true&sd=true | L30: https://drive.google.com/drive/folders/1cfYEH3N18lQ0KgAeKUe3Yn0eQ2_KTM96
A31: MTC-031 | B31: Facets of Proof | C31: Compare forms of mathematical reasoning and proof, using tasks to move from observations and conjectures toward convincing general arguments. | D31: Logic & Proof | E31: Teaching & Learning | F31: proof; conjectures; reasoning; mathematical practices | G31: 2019-06-20 to 2019-06-21 (institute window) | H31: Summer Institute | I31: =COUNTIF(Offerings!$B$5:$B$145,A31) -> 1 | J31: =IF(COUNTIFS(Offerings!$B$5:$B$145,A31,Offerings!$K$5:$K$145,"Yes")>0,"Yes","No") -> Yes | K31: https://docs.google.com/presentation/d/1pKYAhcrbgatmOoLS58fDMZghafRnEF7_/edit?usp=drivesdk&ouid=109901495158487957834&rtpof=true&sd=true | L31: https://drive.google.com/drive/folders/1fjql2fMUsHiBMi1aVeM4pZcYt0NRT0OL
A32: MTC-032 | B32: Factoring in Time for Numeracy: Prime Climb | C32: Explore Prime Climb as a game that combines arithmetic, factoring, chance, and strategy to support number fluency. | D32: Number Sense & Arithmetic | E32: Teaching & Learning | F32: number fluency; factoring; Prime Climb | G32: 2018-12-04 | H32: MTC academic-year session | I32: =COUNTIF(Offerings!$B$5:$B$145,A32) -> 1 | J32: =IF(COUNTIFS(Offerings!$B$5:$B$145,A32,Offerings!$K$5:$K$145,"Yes")>0,"Yes","No") -> No | K32: https://drive.google.com/file/d/16ak6R_4SaZE99Gsze3dcCRqK4fT_51pN/view?usp=drivesdk | L32: https://drive.google.com/drive/folders/1ffcjcyAm95Yy8nXxrdPMgVGMrNNJloao
A33: MTC-033 | B33: Fair Voting and Group-Ranking Methods | C33: Compare plurality voting with alternative group-ranking methods and investigate how different definitions of fairness affect election outcomes. | D33: Mathematical Modeling | E33: Logic & Proof | F33: voting theory; rankings; fairness; social choice | G33: 2020-06-25 2024-10-01 | H33: MTC academic-year session; Summer Institute | I33: =COUNTIF(Offerings!$B$5:$B$145,A33) -> 2 | J33: =IF(COUNTIFS(Offerings!$B$5:$B$145,A33,Offerings!$K$5:$K$145,"Yes")>0,"Yes","No") -> No | K33: https://drive.google.com/file/d/1_G-doR9-mrjYP-6QWYDMwIEsKJ-EM9Bu/view?usp=drivesdk | L33: https://drive.google.com/drive/folders/1jr59l3Nt-latBDxjDcg6UgkIzhqG8Jv9
A34: MTC-034 | B34: Flipping the Script: Reclaiming Mathematics for Our Students and Ourselves | C34: Explore an equity-focused approach to reclaiming mathematics for students and teachers, with discussion and lesson-planning connections. | D34: Teaching & Learning | F34: equity; student agency; social justice | G34: 2020-06-22 | H34: Summer Institute | I34: =COUNTIF(Offerings!$B$5:$B$145,A34) -> 1 | J34: =IF(COUNTIFS(Offerings!$B$5:$B$145,A34,Offerings!$K$5:$K$145,"Yes")>0,"Yes","No") -> Yes | K34: https://docs.google.com/document/d/1MU72dj7yVBt8j7hlae9ghGnPc6Dz3vmIQFpOM_nm71k/edit?usp=drivesdk | L34: https://drive.google.com/drive/folders/1TR-rQ5baZ9czW3kQE8Y527uOZJ4PG-0s
A35: MTC-035 | B35: Framework for All: A Vision for Teaching and Learning | C35: Examine the framework’s three dimensions of systemic change and five components of equitable teaching, with applications to classrooms and coaching. | D35: Teaching & Learning | F35: California Mathematics Framework; equity; coaching | G35: 2026-06-16 | H35: Summer Institute | I35: =COUNTIF(Offerings!$B$5:$B$145,A35) -> 1 | J35: =IF(COUNTIFS(Offerings!$B$5:$B$145,A35,Offerings!$K$5:$K$145,"Yes")>0,"Yes","No") -> No | K35: https://docs.google.com/presentation/d/1LaKKeZC-iN40iNDtyXvu56n75MUrDwQI/edit?usp=drivesdk&ouid=109901495158487957834&rtpof=true&sd=true | L35: https://drive.google.com/drive/folders/1M33DXkdcTbmOGg8w4ljAmGfdoj7i8RRQ
A36: MTC-037 | B36: Getting Nim-ble with Binary | C36: Investigate winning strategies in Nim and how starting configurations and rule changes connect the game with binary arithmetic. | D36: Game Theory | E36: Number Theory | F36: Nim; binary; winning positions | G36: 2019-05-07 | H36: MTC academic-year session | I36: =COUNTIF(Offerings!$B$5:$B$145,A36) -> 1 | J36: =IF(COUNTIFS(Offerings!$B$5:$B$145,A36,Offerings!$K$5:$K$145,"Yes")>0,"Yes","No") -> No | K36: https://drive.google.com/file/d/1LmYLoppKA9ocXHlpg0I5khoTcvwL6DyI/view?usp=drivesdk | L36: https://drive.google.com/drive/folders/1oGJIHA5ZxR875CYuluh6RfpoRAxKMTrl
A37: MTC-038 | B37: Graph Talks | C37: Use meaningful graphs to elicit student observations, questions, and mathematical reasoning while discussing the social contexts represented by data. | D37: Teaching & Learning | E37: Probability & Statistics | F37: graph talks; data visualization; social justice; discussion | G37: 2022-06-21 2023-06-20 2023-06-21 | H37: Summer Institute | I37: =COUNTIF(Offerings!$B$5:$B$145,A37) -> 3 | J37: =IF(COUNTIFS(Offerings!$B$5:$B$145,A37,Offerings!$K$5:$K$145,"Yes")>0,"Yes","No") -> No | K37: https://docs.google.com/presentation/d/1T1zOtCkQU_-Zb9bVvNtdICIVOv_v73ZS/edit?usp=drivesdk&ouid=109901495158487957834&rtpof=true&sd=true | L37: https://drive.google.com/drive/folders/1hDwdu80o8G_uXserSpBBqKXl4dJBQL1_
A38: MTC-039 | B38: Guppies, Goldfish and the Golden Ratio | C38: Play a two-pile take-away game and investigate how safe positions, number patterns, and the golden ratio reveal winning strategies. | D38: Game Theory | E38: Number Theory | F38: Wythoff’s game; golden ratio; winning positions | G38: 2025-09-02 | H38: MTC academic-year session | I38: =COUNTIF(Offerings!$B$5:$B$145,A38) -> 1 | J38: =IF(COUNTIFS(Offerings!$B$5:$B$145,A38,Offerings!$K$5:$K$145,"Yes")>0,"Yes","No") -> No | K38: https://drive.google.com/file/d/1ZrqtsJmZ_sj1Xm1RNL6B6KnIKHsJtzOD/view?usp=drivesdk | L38: https://drive.google.com/drive/folders/1khQvS5_iRyU4DulxZAVqDj2DPrWzc_GA
A39: MTC-040 | B39: Harmonic Numbers | C39: Explore numbers of the form 2^a × 3^b, investigate their possible differences, and connect the questions with musical ratios and the abc conjecture. | D39: Number Theory | F39: harmonic numbers; differences; abc conjecture | G39: 2019-12-03 | H39: MTC academic-year session | I39: =COUNTIF(Offerings!$B$5:$B$145,A39) -> 1 | J39: =IF(COUNTIFS(Offerings!$B$5:$B$145,A39,Offerings!$K$5:$K$145,"Yes")>0,"Yes","No") -> No | K39: https://drive.google.com/file/d/14NMNxZXO05cJLv0l_H-OyJCi0VUlGaVL/view?usp=drivesdk | L39: https://drive.google.com/drive/folders/1QngmjBRVRDmBrUxQpDi4INur_f1rfZUq
A40: MTC-041 | B40: How Generative AI Works and How It Can Work for You | C40: Explore the mathematics behind generative AI, practice prompt design, and examine classroom uses and limitations of AI tools. | D40: Teaching & Learning | E40: Algorithms & Computing | F40: generative AI; large language models; prompt design | G40: 2025-09-16 | H40: LIFT | I40: =COUNTIF(Offerings!$B$5:$B$145,A40) -> 1 | J40: =IF(COUNTIFS(Offerings!$B$5:$B$145,A40,Offerings!$K$5:$K$145,"Yes")>0,"Yes","No") -> No | K40: https://drive.google.com/file/d/1HYmRyKHHLjUH1plonTNwwYzKKR3XnQ0w/view?usp=drivesdk | L40: https://drive.google.com/drive/folders/1CceKEqM8hNhsHav8l4tEptIcttER7HG9
A41: MTC-042 | B41: I Walk the Line(s) | C41: Count routes through a city laid out on a square grid, then investigate how restrictions and obstacles change the possible paths. | D41: Combinatorics | F41: grid paths; counting; obstacles; Catalan numbers | G41: 2022-02-01 2026-05-05 | H41: MTC academic-year session | I41: =COUNTIF(Offerings!$B$5:$B$145,A41) -> 2 | J41: =IF(COUNTIFS(Offerings!$B$5:$B$145,A41,Offerings!$K$5:$K$145,"Yes")>0,"Yes","No") -> No | K41: https://drive.google.com/file/d/1bUV6IoSvVROkVKEdK5lKC5biTV5Q8TTe/view?usp=drivesdk | L41: https://drive.google.com/drive/folders/1JL7xZB4YFofEOWhY-ZSCobR_vBFLc-gZ
A42: MTC-043 | B42: Include Others as Experts and Understand Your Students Well | C42: Use team-building activities and reflection to explore how students can serve as experts and how teachers can learn about their experiences and identities. | D42: Teaching & Learning | F42: ICUCARE; collaboration; student identity; math autobiography | G42: 2025-06-17 | H42: Summer Institute | I42: =COUNTIF(Offerings!$B$5:$B$145,A42) -> 1 | J42: =IF(COUNTIFS(Offerings!$B$5:$B$145,A42,Offerings!$K$5:$K$145,"Yes")>0,"Yes","No") -> No | K42: https://docs.google.com/presentation/d/1OH3vJj5NCGamQgjjzRzlK5LkNo2eCXkD/edit?usp=drivesdk&ouid=109901495158487957834&rtpof=true&sd=true | L42: https://drive.google.com/drive/folders/11vxjmRb0TS8JFvDvhD_iZ-EzytMid970
A43: MTC-044 | B43: Inductive Reasoning with Geoboards | C43: Count segments on geoboards, build and test conjectures, and consider how inquiry tasks support conceptual and procedural understanding. | D43: Geometry | E43: Logic & Proof; Teaching & Learning | F43: geoboards; patterns; inductive reasoning | G43: 2019-06-20 to 2019-06-21 (institute window) | H43: Summer Institute | I43: =COUNTIF(Offerings!$B$5:$B$145,A43) -> 1 | J43: =IF(COUNTIFS(Offerings!$B$5:$B$145,A43,Offerings!$K$5:$K$145,"Yes")>0,"Yes","No") -> Yes | K43: https://docs.google.com/presentation/d/1TMow9UBVdxIhyPxYmk4QKFf2aPfA39kd45XcXvdJ71w/edit?usp=drivesdk | L43: https://drive.google.com/drive/folders/1rCzj4dRC4_nPVNUpFQC8srEsaJOrEUFN
A44: MTC-045 | B44: Instant Insanity | C44: Arrange colored cubes so each side of a tower displays every color, then explore numerical and graph-based representations of the puzzle. | D44: Combinatorics | E44: Number Theory; Graph Theory | F44: colored cubes; factoring; constraint puzzles | G44: 2017-06-15 to 2017-06-16 (institute window) | H44: Summer Institute | I44: =COUNTIF(Offerings!$B$5:$B$145,A44) -> 1 | J44: =IF(COUNTIFS(Offerings!$B$5:$B$145,A44,Offerings!$K$5:$K$145,"Yes")>0,"Yes","No") -> Yes | K44: https://docs.google.com/presentation/d/0B4cCTfJeL7_dZ084MGZNUjVBU1E/edit?usp=drivesdk&ouid=109901495158487957834&resourcekey=0-xqQaukkaqbnIwZhtqkr3HQ&rtpof=true&sd=true | L44: https://drive.google.com/drive/folders/0B4cCTfJeL7_dQTJaNFc5empWbUE?resourcekey=0-8hWfh9_udgJ8jFMROirwEg
A45: MTC-046 | B45: Introduction to Fractals | C45: Construct and analyze fractals to explore self-similarity, repeated rules, and connections among nature, geometry, and algebra. | D45: Geometry | E45: Algebra | F45: fractals; self-similarity; iteration; patterns | G45: 2022-06-23 (review) | H45: Summer Institute | I45: =COUNTIF(Offerings!$B$5:$B$145,A45) -> 1 | J45: =IF(COUNTIFS(Offerings!$B$5:$B$145,A45,Offerings!$K$5:$K$145,"Yes")>0,"Yes","No") -> Yes | K45: https://docs.google.com/presentation/d/1bDNjxI9WN_Ivms1TvOklkV9Poh1zcHzR/edit?usp=drivesdk&ouid=109901495158487957834&rtpof=true&sd=true | L45: https://drive.google.com/drive/folders/16M3IuXYUFOAt1KMkN3Cm6F4lnMv7WKSX
A46: MTC-047 | B46: Is Base 10 Best? | C46: Use Exploding Dots to compare fractional representations in different bases and investigate why some expansions terminate while others repeat. | D46: Number Sense & Arithmetic | E46: Number Theory | F46: number bases; fractions; repeating decimals; Exploding Dots | G46: 2025-05-06 | H46: MTC academic-year session | I46: =COUNTIF(Offerings!$B$5:$B$145,A46) -> 1 | J46: =IF(COUNTIFS(Offerings!$B$5:$B$145,A46,Offerings!$K$5:$K$145,"Yes")>0,"Yes","No") -> No | K46: https://drive.google.com/file/d/1muk5fEb0Tbn7io-1MXTEBd2WSOpAUxzB/view?usp=drivesdk | L46: https://drive.google.com/drive/folders/1idtcMuTrh4oREgooxv-ewPWTq0hGKih8
A47: MTC-048 | B47: Is Santa Secretly Deranged? | C47: Investigate Secret Santa assignments in which nobody draws their own name, and study how the counting and probabilities change as the group grows. | D47: Combinatorics | E47: Probability & Statistics | F47: derangements; permutations; Secret Santa | G47: 2017-12-05 2023-12-05 | H47: MTC academic-year session | I47: =COUNTIF(Offerings!$B$5:$B$145,A47) -> 2 | J47: =IF(COUNTIFS(Offerings!$B$5:$B$145,A47,Offerings!$K$5:$K$145,"Yes")>0,"Yes","No") -> No | K47: https://drive.google.com/file/d/1aFBtamtxp4JPdsOH_Yf003sqXUDzRTHT/view?usp=drivesdk | L47: https://drive.google.com/drive/folders/13-deZNzxTBUcDkHUwrj9rI4oee5VNdQn
A48: MTC-049 | B48: KenKen | C48: Solve KenKen puzzles at different levels, explore their mathematical structure, and create new puzzles. | D48: Logic & Proof | E48: Number Sense & Arithmetic | F48: arithmetic; puzzle design; constraints | G48: 2017-03-07 (review) | H48: MTC academic-year session | I48: =COUNTIF(Offerings!$B$5:$B$145,A48) -> 1 | J48: =IF(COUNTIFS(Offerings!$B$5:$B$145,A48,Offerings!$K$5:$K$145,"Yes")>0,"Yes","No") -> Yes | K48: https://drive.google.com/file/d/0B4cCTfJeL7_dUlREbmJoWGpoRlU/view?usp=drivesdk&resourcekey=0-2KQz8LJ2bXF_iO3B4_-4tg | L48: https://drive.google.com/drive/folders/0B4cCTfJeL7_dNzh2OXc3WDN5Tjg?resourcekey=0-6YR3U00KQXCHW6GbAQ7Q7w
A49: MTC-050 | B49: Knot Mosaics | C49: Represent knots with tiles and investigate which tiles are needed, how knot mosaics can be classified, and when representations describe the same knot. | D49: Topology | E49: Geometry | F49: knots; tiles; classification | G49: 2018-05-01 | H49: MTC academic-year session | I49: =COUNTIF(Offerings!$B$5:$B$145,A49) -> 1 | J49: =IF(COUNTIFS(Offerings!$B$5:$B$145,A49,Offerings!$K$5:$K$145,"Yes")>0,"Yes","No") -> No | K49: https://drive.google.com/file/d/11ZpvXPWejLT5th3HJ3hSWalPALNrBgMz/view?usp=drivesdk | L49: https://drive.google.com/drive/folders/1jnKOroAXawrv7jPNAbeqiP_dv2ScX-o2
A50: MTC-051 | B50: Leadership Activity (2026 Closing Session) | C50: A leadership activity is listed in the final-day agenda; the specific activity content is not identified clearly in the available materials. | D50: Teaching & Learning | F50: teacher leadership | G50: 2026-06-18 | H50: Summer Institute | I50: =COUNTIF(Offerings!$B$5:$B$145,A50) -> 1 | J50: =IF(COUNTIFS(Offerings!$B$5:$B$145,A50,Offerings!$K$5:$K$145,"Yes")>0,"Yes","No") -> Yes | K50: https://docs.google.com/document/d/1c1jxXWI9e_vogPRk7ZQRZyYas_4c9tPx/edit?usp=drivesdk&ouid=109901495158487957834&rtpof=true&sd=true | L50: https://drive.google.com/drive/folders/1tg2SfN_CqRxyGs_dKhXQeS3ejfGuK48V
A51: MTC-052 | B51: Leadership Role Play and Image Theatre | C51: Use nonverbal role play to examine difficult teaching and coaching situations and consider facilitation moves that support equitable participation. | D51: Teaching & Learning | F51: teacher leadership; coaching; role play; equity | G51: 2026-06-17 | H51: Summer Institute | I51: =COUNTIF(Offerings!$B$5:$B$145,A51) -> 1 | J51: =IF(COUNTIFS(Offerings!$B$5:$B$145,A51,Offerings!$K$5:$K$145,"Yes")>0,"Yes","No") -> No | K51: https://docs.google.com/document/d/1Q0Xl_OmZSXBnGjhtZQVhh0XxmcFg37V5/edit?usp=drivesdk&ouid=109901495158487957834&rtpof=true&sd=true | L51: https://drive.google.com/drive/folders/1RRidzQMCwBO2FgTiCAjoCMGC2Lany0YY
A52: MTC-053 | B52: Learning Mathematics and Social Justice | C52: Discuss connections between learning mathematics and social justice and consider their implications for teaching. | D52: Teaching & Learning | F52: social justice; mathematics learning; discussion | G52: 2021-06-19 | H52: Summer Institute | I52: =COUNTIF(Offerings!$B$5:$B$145,A52) -> 1 | J52: =IF(COUNTIFS(Offerings!$B$5:$B$145,A52,Offerings!$K$5:$K$145,"Yes")>0,"Yes","No") -> No | K52: https://docs.google.com/document/d/1XgBPtwa7dVUiBdYAa1nvv7DqLhWe7ho8BS23HndmozU/edit?usp=drivesdk | L52: https://drive.google.com/drive/folders/1jMaUXv_moFqp4vPk7rMqgcL-NFSsSY0E
A53: MTC-055 | B53: Liar’s Bingo | C53: Investigate patterns in bingo cards and use mathematical reasoning to detect false information in a game about truth and information transmission. | D53: Algorithms & Computing | E53: Logic & Proof | F53: information transmission; error detection; bingo | G53: 2017-04-04 (review) 2026-02-03 | H53: MTC academic-year session | I53: =COUNTIF(Offerings!$B$5:$B$145,A53) -> 2 | J53: =IF(COUNTIFS(Offerings!$B$5:$B$145,A53,Offerings!$K$5:$K$145,"Yes")>0,"Yes","No") -> Yes | K53: https://drive.google.com/file/d/1HnKdwue9H7Mi9IopcQbTDNGHz-x1EdKm/view?usp=drivesdk | L53: https://drive.google.com/drive/folders/1e4pleLHs5FJa40YpKOvwIX8rfIVoWw5-
A54: MTC-056 | B54: Linear Programming: Cookies and Inequalities | C54: Explore linear-programming situations through cookie and inequality scenarios, comparing constraints and possible solutions. | D54: Algebra | E54: Mathematical Modeling | F54: linear programming; inequalities; optimization | G54: 2021-06-19 | H54: Summer Institute | I54: =COUNTIF(Offerings!$B$5:$B$145,A54) -> 1 | J54: =IF(COUNTIFS(Offerings!$B$5:$B$145,A54,Offerings!$K$5:$K$145,"Yes")>0,"Yes","No") -> No | K54: https://docs.google.com/document/d/1XgBPtwa7dVUiBdYAa1nvv7DqLhWe7ho8BS23HndmozU/edit?usp=drivesdk | L54: https://drive.google.com/drive/folders/1jMaUXv_moFqp4vPk7rMqgcL-NFSsSY0E
A55: MTC-057 | B55: Logic: Knights and Knaves | C55: Solve symbolic, seating, and knights-and-knaves puzzles, comparing deduction strategies and using basic truth tables. | D55: Logic & Proof | F55: truth tables; logic puzzles; deduction | G55: 2017-06-15 to 2017-06-16 (institute window) | H55: Summer Institute | I55: =COUNTIF(Offerings!$B$5:$B$145,A55) -> 1 | J55: =IF(COUNTIFS(Offerings!$B$5:$B$145,A55,Offerings!$K$5:$K$145,"Yes")>0,"Yes","No") -> Yes | K55: https://docs.google.com/presentation/d/0B2XvpmARE9ZbMnZCM0ZOaHZXSVk/edit?usp=drivesdk&ouid=109901495158487957834&resourcekey=0-V7nKYNXuHYTwHhbaPrZV6w&rtpof=true&sd=true | L55: https://drive.google.com/drive/folders/0B4cCTfJeL7_dWWlYb3JRTVljWlU?resourcekey=0-NwX1MEHlBgX_Rxr44Y1iBQ
A56: MTC-058 | B56: M&M Color Distribution | C56: Collect and graph M&M color data, compare observed and expected distributions, and investigate what samples can tell us about a larger population. | D56: Probability & Statistics | F56: data collection; relative frequency; distributions; statistical inference | G56: 2026-06-16 | H56: Summer Institute | I56: =COUNTIF(Offerings!$B$5:$B$145,A56) -> 1 | J56: =IF(COUNTIFS(Offerings!$B$5:$B$145,A56,Offerings!$K$5:$K$145,"Yes")>0,"Yes","No") -> No | K56: https://docs.google.com/presentation/d/111Mm5rdSCYUzPxumGyXGdFcgspR82NM5N0OEi7wjdJ8/edit?usp=drivesdk | L56: https://drive.google.com/drive/folders/1M33DXkdcTbmOGg8w4ljAmGfdoj7i8RRQ
A57: MTC-059 | B57: M&M Estimation and Packing Density | C57: Estimate the number of M&Ms in a container by investigating their shape, volume, and packing density while making prior knowledge and reasoning visible. | D57: Geometry | E57: Mathematical Modeling; Teaching & Learning | F57: estimation; volume; packing density; Desmos | G57: 2024-06-20 | H57: Summer Institute | I57: =COUNTIF(Offerings!$B$5:$B$145,A57) -> 1 | J57: =IF(COUNTIFS(Offerings!$B$5:$B$145,A57,Offerings!$K$5:$K$145,"Yes")>0,"Yes","No") -> No | K57: https://docs.google.com/presentation/d/1NEhP_WJTq5C89f-nOPrqvzb3Pgn2wzNf/edit?usp=drivesdk&ouid=109901495158487957834&rtpof=true&sd=true | L57: https://drive.google.com/drive/folders/1yFqMd8ssJpVqMg2bbU912bXb6yPDduyD
A58: MTC-060 | B58: Make Your Own 3-Act Math Task | C58: Design and evaluate a three-act math task, using a planning template and peer collaboration to refine the mathematical question and learning sequence. | D58: Teaching & Learning | E58: Mathematical Modeling | F58: 3-Act tasks; task design; lesson planning | G58: 2021-06-17 | H58: Summer Institute | I58: =COUNTIF(Offerings!$B$5:$B$145,A58) -> 1 | J58: =IF(COUNTIFS(Offerings!$B$5:$B$145,A58,Offerings!$K$5:$K$145,"Yes")>0,"Yes","No") -> No | K58: https://docs.google.com/document/d/1XgBPtwa7dVUiBdYAa1nvv7DqLhWe7ho8BS23HndmozU/edit?usp=drivesdk | L58: https://drive.google.com/drive/folders/1jMaUXv_moFqp4vPk7rMqgcL-NFSsSY0E
A59: MTC-061 | B59: Making the Most of Things | C59: Solve maximum-and-minimum problems using arithmetic, algebra, and geometry, and turn everyday questions into open-ended mathematical investigations. | D59: Algebra | E59: Geometry | F59: optimization; extreme cases; arithmetic | G59: 2024-09-03 | H59: MTC academic-year session | I59: =COUNTIF(Offerings!$B$5:$B$145,A59) -> 1 | J59: =IF(COUNTIFS(Offerings!$B$5:$B$145,A59,Offerings!$K$5:$K$145,"Yes")>0,"Yes","No") -> No | K59: https://drive.google.com/file/d/1h6nGqXNest6UzmD5tGwvebeq9ySDt6Ff/view?usp=drivesdk | L59: https://drive.google.com/drive/folders/1yCkqvQozKRYzACo-UCVxFT39mdXn6jzy
A60: MTC-062 | B60: Mastermind | C60: Use feedback from Mastermind guesses to count remaining possibilities and compare efficient code-breaking strategies. | D60: Logic & Proof | E60: Combinatorics; Algorithms & Computing | F60: code breaking; information; strategy | G60: 2017-06-15 to 2017-06-16 (institute window) | H60: Summer Institute | I60: =COUNTIF(Offerings!$B$5:$B$145,A60) -> 1 | J60: =IF(COUNTIFS(Offerings!$B$5:$B$145,A60,Offerings!$K$5:$K$145,"Yes")>0,"Yes","No") -> Yes | K60: https://docs.google.com/presentation/d/0B4cCTfJeL7_dbkR1d0RQeHRMclU/edit?usp=drivesdk&ouid=109901495158487957834&resourcekey=0-qaLSVqn8XKSsNH4sKGV55g&rtpof=true&sd=true | L60: https://drive.google.com/drive/folders/0B4cCTfJeL7_dTHBkS1RrSkdGa1E?resourcekey=0-t_6NCUKHfrRprA1_i9yyhw
A61: MTC-063 | B61: Match or No Match | C61: Draw colored chips from a bag to test whether a matching game is fair, then vary the rules and configurations to build fair games. | D61: Probability & Statistics | E61: Combinatorics | F61: fair games; sampling; triangular numbers | G61: 2019-02-05 | H61: MTC academic-year session | I61: =COUNTIF(Offerings!$B$5:$B$145,A61) -> 1 | J61: =IF(COUNTIFS(Offerings!$B$5:$B$145,A61,Offerings!$K$5:$K$145,"Yes")>0,"Yes","No") -> No | K61: https://drive.google.com/file/d/1uC4fIii10Gq-tSJ5Dwhw5_m51EwmJBEC/view?usp=drivesdk | L61: https://drive.google.com/drive/folders/1hAGkv8rqxLUASObqaWlFU_gVs-0zwUHv
A62: MTC-064 | B62: Math and Environmental Justice | C62: Interpret environmental-exposure data and investigate how rates, averages, and graphs can reveal unequal impacts across communities. | D62: Probability & Statistics | E62: Mathematical Modeling | F62: data analysis; environmental justice; ratios; graphs | G62: 2022-06-21 | H62: Summer Institute | I62: =COUNTIF(Offerings!$B$5:$B$145,A62) -> 1 | J62: =IF(COUNTIFS(Offerings!$B$5:$B$145,A62,Offerings!$K$5:$K$145,"Yes")>0,"Yes","No") -> No | K62: https://docs.google.com/presentation/d/1RTj1fMGz0wEOL9Ve-0AWctdb8txMNY_S/edit?usp=drivesdk&ouid=109901495158487957834&rtpof=true&sd=true | L62: https://drive.google.com/drive/folders/12KdwrIwdgiabfHJPsYNGx-iNT777x6Yq
A63: MTC-065 | B63: Math and Photography: Classroom Applications | C63: Discuss examples of student photography and consider how photographs and mathematical apps can support classroom learning. | D63: Teaching & Learning | F63: photography; classroom technology; lesson design | G63: 2022-06-22 | H63: Summer Institute | I63: =COUNTIF(Offerings!$B$5:$B$145,A63) -> 1 | J63: =IF(COUNTIFS(Offerings!$B$5:$B$145,A63,Offerings!$K$5:$K$145,"Yes")>0,"Yes","No") -> No | K63: https://docs.google.com/presentation/d/1tJ6ON4M2cMa8SB_FiNd8-PawVANjjAaUuDpJ8OUMimQ/edit?usp=drivesdk | L63: https://drive.google.com/drive/folders/1S4RXsHe-nlbaLXgBSSgAnb8zt7jYvF1e
A64: MTC-066 | B64: Math in Toys and Games | C64: Play and vary mathematical games, investigate winning strategies, and consider classroom structures that support strategic reasoning. | D64: Game Theory | E64: Teaching & Learning | F64: Nim; anti tic-tac-toe; strategy; mathematical practices | G64: 2022-06-24 (review) | H64: Summer Institute | I64: =COUNTIF(Offerings!$B$5:$B$145,A64) -> 1 | J64: =IF(COUNTIFS(Offerings!$B$5:$B$145,A64,Offerings!$K$5:$K$145,"Yes")>0,"Yes","No") -> Yes | K64: https://docs.google.com/presentation/d/1RWRtteAz3hCalu4sddo6U3kiJ-GO7XaN/edit?usp=drivesdk&ouid=109901495158487957834&rtpof=true&sd=true | L64: https://drive.google.com/drive/folders/1eGpbdA4Hp8lOeRdRuohJia-TGwjesrAN
A65: MTC-067 | B65: Mathematical Connections: Gaussian Guesswork | C65: Investigate the arithmetic-geometric mean through mathematical reading and connections among sequences, computations, and historical sources. | D65: Algebra | E65: Teaching & Learning | F65: sequences; arithmetic-geometric mean; primary sources; Reading Apprenticeship | G65: 2024-06-21 | H65: Summer Institute | I65: =COUNTIF(Offerings!$B$5:$B$145,A65) -> 1 | J65: =IF(COUNTIFS(Offerings!$B$5:$B$145,A65,Offerings!$K$5:$K$145,"Yes")>0,"Yes","No") -> Yes | K65: https://drive.google.com/file/d/1HToAcoPW1SvF8XTJGolLFWbwlz79zSBh/view?usp=drivesdk | L65: https://drive.google.com/drive/folders/1snYWtnWJn7o1t_f6MUW9IZgU42PPlM5Z
A66: MTC-068 | B66: Mathematical Interactions for English Learners | C66: Discuss task structures that require mathematical communication, including information-gap, linking, building, and jigsaw activities. | D66: Teaching & Learning | F66: multilingual learners; mathematical language; information gaps; collaboration | G66: 2022-06-23 (review) | H66: Summer Institute | I66: =COUNTIF(Offerings!$B$5:$B$145,A66) -> 1 | J66: =IF(COUNTIFS(Offerings!$B$5:$B$145,A66,Offerings!$K$5:$K$145,"Yes")>0,"Yes","No") -> Yes | K66: https://docs.google.com/presentation/d/1O2bEMT3iJ5PP8TmY8gR_Ja4-J-lzoZOwtzg_qizB_to/edit?usp=drivesdk | L66: https://drive.google.com/drive/folders/16M3IuXYUFOAt1KMkN3Cm6F4lnMv7WKSX
A67: MTC-069 | B67: Mathematical Magic for Muggles | C67: Use simple ideas about parity and arithmetic to create and explain mathematical magic tricks. | D67: Number Theory | E67: Algebra | F67: parity; magic tricks; invariants | G67: 2023-10-03 | H67: MTC academic-year session | I67: =COUNTIF(Offerings!$B$5:$B$145,A67) -> 1 | J67: =IF(COUNTIFS(Offerings!$B$5:$B$145,A67,Offerings!$K$5:$K$145,"Yes")>0,"Yes","No") -> No | K67: https://drive.google.com/file/d/1SC9cPIcEpCmbNPY2J1-ZyJ_wd-qsPtth/view?usp=drivesdk | L67: https://drive.google.com/drive/folders/17EyNurQXIQaadG6i9wXQsbpBWw_Ok9h8
A68: MTC-070 | B68: Mathematics Education Through the Lens of Social Justice | C68: Discuss the assigned reading on acknowledgment, action, and accountability in mathematics education through a social-justice lens. | D68: Teaching & Learning | F68: social justice; equity; accountability | G68: 2020-06-23 | H68: Summer Institute | I68: =COUNTIF(Offerings!$B$5:$B$145,A68) -> 1 | J68: =IF(COUNTIFS(Offerings!$B$5:$B$145,A68,Offerings!$K$5:$K$145,"Yes")>0,"Yes","No") -> No | K68: https://docs.google.com/document/d/1MU72dj7yVBt8j7hlae9ghGnPc6Dz3vmIQFpOM_nm71k/edit?usp=drivesdk | L68: https://drive.google.com/drive/folders/1TR-rQ5baZ9czW3kQE8Y527uOZJ4PG-0s
A69: MTC-071 | B69: Mathematics Leadership: Strengths and Challenges | C69: Reflect on teaching strengths, areas for support, and leadership roles using the framework’s dimensions of systemic change and components of equitable teaching. | D69: Teaching & Learning | F69: math autobiography; teacher leadership; reflection | G69: 2026-06-15 | H69: Summer Institute | I69: =COUNTIF(Offerings!$B$5:$B$145,A69) -> 1 | J69: =IF(COUNTIFS(Offerings!$B$5:$B$145,A69,Offerings!$K$5:$K$145,"Yes")>0,"Yes","No") -> No | K69: https://docs.google.com/document/d/1ENOuRovlH7MmNHyU0oiZI95IukO8p2zW/edit?usp=drivesdk&ouid=109901495158487957834&rtpof=true&sd=true | L69: https://drive.google.com/drive/folders/1p_V_zMd7U5Usmmm_pc1ghlzTvB84LP-G
A70: MTC-072 | B70: Mathematics and Social Justice: Examining Stop and Frisk | C70: Analyze New York City stop-and-frisk data to investigate differences across communities and discuss how mathematics can inform understanding and action. | D70: Probability & Statistics | E70: Mathematical Modeling | F70: data analysis; social justice; stop and frisk | G70: 2020-09-01 | H70: MTC academic-year session | I70: =COUNTIF(Offerings!$B$5:$B$145,A70) -> 1 | J70: =IF(COUNTIFS(Offerings!$B$5:$B$145,A70,Offerings!$K$5:$K$145,"Yes")>0,"Yes","No") -> No | K70: https://drive.google.com/file/d/1FFLwOX1vcCpoJlVxhFeNMYQNg7-0nvL8/view?usp=drivesdk | L70: https://drive.google.com/drive/folders/1BgJfrLsCwVUImbaAqDDV_jJK8b4tjbZa
A71: MTC-073 | B71: Mathematics of Lotería | C71: Play Lotería and investigate the number of possible boards, winning patterns, and probabilities while connecting mathematics with students’ cultural experiences. | D71: Combinatorics | E71: Probability & Statistics; Teaching & Learning | F71: Lotería; cultural connections; counting; probability | G71: 2025-06-12 | H71: Summer Institute | I71: =COUNTIF(Offerings!$B$5:$B$145,A71) -> 1 | J71: =IF(COUNTIFS(Offerings!$B$5:$B$145,A71,Offerings!$K$5:$K$145,"Yes")>0,"Yes","No") -> No | K71: https://docs.google.com/presentation/d/1yS8CbjLk0VNOkSKteR-bD2m-Zdyhe7ol/edit?usp=drivesdk&ouid=109901495158487957834&rtpof=true&sd=true | L71: https://drive.google.com/drive/folders/1bjeqM6wGIQOCOVl20bZZJ-r8Tb23TmsO
A72: MTC-074 | B72: Measuring Up: A Perfect Ruler | C72: Investigate how to measure every integer length on a ruler while using fewer marked positions, and search for efficient or perfect ruler designs. | D72: Combinatorics | E72: Number Theory | F72: measurement; differences; optimization | G72: 2023-02-07 | H72: MTC academic-year session | I72: =COUNTIF(Offerings!$B$5:$B$145,A72) -> 1 | J72: =IF(COUNTIFS(Offerings!$B$5:$B$145,A72,Offerings!$K$5:$K$145,"Yes")>0,"Yes","No") -> No | K72: https://drive.google.com/file/d/1G4zatwIw7aUlvSjwHvFqFcfNrTb5m_FU/view?usp=drivesdk | L72: https://drive.google.com/drive/folders/1mm9TLbXkEuHd67SSyDodgZgcaxF1JPF0
A73: MTC-075 | B73: Monte Carlo Simulations | C73: Compare deterministic and stochastic models, using repeated simulations to explore uncertain outcomes such as the time needed to drain a pool. | D73: Probability & Statistics | E73: Mathematical Modeling | F73: Monte Carlo; simulation; randomness; stochastic models | G73: 2021-06-21 | H73: Summer Institute | I73: =COUNTIF(Offerings!$B$5:$B$145,A73) -> 1 | J73: =IF(COUNTIFS(Offerings!$B$5:$B$145,A73,Offerings!$K$5:$K$145,"Yes")>0,"Yes","No") -> No | K73: https://docs.google.com/presentation/d/19cXuJB9iIDB86Fdlc5V7KbOxKqFGx-ij/edit?usp=drivesdk&ouid=109901495158487957834&rtpof=true&sd=true | L73: https://drive.google.com/drive/folders/1E7fYcRB-72i5hOTtaIDTIY5i8Ft41yv2
A74: MTC-076 | B74: More Sprinkles | C74: Count ice-cream topping selections, vary the number of available or permitted toppings, and connect the resulting patterns with other counting problems. | D74: Combinatorics | F74: combinations; counting; toppings | G74: 2022-11-01 | H74: MTC academic-year session | I74: =COUNTIF(Offerings!$B$5:$B$145,A74) -> 1 | J74: =IF(COUNTIFS(Offerings!$B$5:$B$145,A74,Offerings!$K$5:$K$145,"Yes")>0,"Yes","No") -> No | K74: https://drive.google.com/file/d/12tNUhCtvt8zln3LLOfIrqhu9fWiW-jgm/view?usp=drivesdk | L74: https://drive.google.com/drive/folders/17bNwEyyRjVcV1QoiEpohKhoXhgPMyynq
A75: MTC-077 | B75: Multiplication Madness | C75: Create alternative multiplication operations from line intersections, rectangle counting, and dinner-party arrangements, then compare their structures. | D75: Algebra | E75: Combinatorics | F75: operations; multiplication tables; patterns | G75: 2019-11-05 | H75: MTC academic-year session | I75: =COUNTIF(Offerings!$B$5:$B$145,A75) -> 1 | J75: =IF(COUNTIFS(Offerings!$B$5:$B$145,A75,Offerings!$K$5:$K$145,"Yes")>0,"Yes","No") -> No | K75: https://drive.google.com/file/d/1nTZAzrX50ic8-p_UeQd6j7uylgKOVBum/view?usp=drivesdk | L75: https://drive.google.com/drive/folders/1cMnUxgRQXWjD1UgjsQfvtw0kcOtXPWZ4
A76: MTC-078 | B76: Nearest Neighbor: Voronoi Diagrams | C76: Explore Voronoi diagrams and how nearest-neighbor regions can help answer questions about locations, patterns, and real-world applications. | D76: Geometry | E76: Mathematical Modeling | F76: Voronoi diagrams; nearest neighbors; spatial partitions | G76: 2020-03-03 | H76: MTC academic-year session | I76: =COUNTIF(Offerings!$B$5:$B$145,A76) -> 1 | J76: =IF(COUNTIFS(Offerings!$B$5:$B$145,A76,Offerings!$K$5:$K$145,"Yes")>0,"Yes","No") -> No | K76: https://drive.google.com/file/d/1iYATNDZoGU69G_AkxC5O9cU4eo59Uq59/view?usp=drivesdk | L76: https://drive.google.com/drive/folders/1GYFrk5PJ894tCvq0mcp9561W-UjxSmZK
A77: MTC-079 | B77: Notable Numbers | C77: Explore perfect-square arrangements, expressions built from small numbers, and Friedman numbers formed using their own digits. | D77: Number Sense & Arithmetic | E77: Number Theory | F77: Friedman numbers; operations; perfect squares; puzzles | G77: 2026-06-18 | H77: Summer Institute | I77: =COUNTIF(Offerings!$B$5:$B$145,A77) -> 1 | J77: =IF(COUNTIFS(Offerings!$B$5:$B$145,A77,Offerings!$K$5:$K$145,"Yes")>0,"Yes","No") -> No | K77: https://docs.google.com/presentation/d/1XHyB5roxz6Fxi0gF1OoauaR6rN8ZaGCO_PqmorWkaP4/edit?usp=drivesdk | L77: https://drive.google.com/drive/folders/1_LvYC5COwUaXTMX7PeFWbg9OJGhFgFca
A78: MTC-080 | B78: Number Bracelets | C78: Generate number sequences from a simple rule, look for repeating cycles, and explore how starting values or rule changes affect the resulting bracelets. | D78: Number Theory | E78: Algebra | F78: sequences; recurrence; cycles; modular arithmetic | G78: 2017-06-15 to 2017-06-16 (institute window) 2023-05-02 | H78: MTC academic-year session; Summer Institute | I78: =COUNTIF(Offerings!$B$5:$B$145,A78) -> 2 | J78: =IF(COUNTIFS(Offerings!$B$5:$B$145,A78,Offerings!$K$5:$K$145,"Yes")>0,"Yes","No") -> Yes | K78: https://drive.google.com/file/d/1q1t0wTzFzhN1uokGX16E4pLExzL1M_H8/view?usp=drivesdk | L78: https://drive.google.com/drive/folders/1TBPAE_rso5xGRij7i3rFXQ8N4uywc2En
A79: MTC-081 | B79: Number Puzzles | C79: Explore Hidato, Kakuro, and Minesweeper to practice logical deduction and arithmetic and investigate the mathematics behind the puzzles. | D79: Logic & Proof | E79: Number Sense & Arithmetic | F79: Hidato; Kakuro; Minesweeper; puzzles | G79: 2021-09-07 (review) | H79: MTC academic-year session | I79: =COUNTIF(Offerings!$B$5:$B$145,A79) -> 1 | J79: =IF(COUNTIFS(Offerings!$B$5:$B$145,A79,Offerings!$K$5:$K$145,"Yes")>0,"Yes","No") -> Yes | K79: https://drive.google.com/file/d/1PMbt8CmnyXGG7W2A1aHCjmgh75UCVKt1/view?usp=drivesdk | L79: https://drive.google.com/drive/folders/1jz8btew6_1UD1nmxQPoX7_UuGH_9SrVg
A80: MTC-082 | B80: Number Sense and Number Talks | C80: Discuss number sense across grade levels and practice number-talk routines that make flexible mental strategies and mathematical reasoning visible. | D80: Number Sense & Arithmetic | E80: Teaching & Learning | F80: number sense; mental mathematics; number talks; discussion | G80: 2018-06-18 to 2018-06-21 (institute window) | H80: Summer Institute | I80: =COUNTIF(Offerings!$B$5:$B$145,A80) -> 1 | J80: =IF(COUNTIFS(Offerings!$B$5:$B$145,A80,Offerings!$K$5:$K$145,"Yes")>0,"Yes","No") -> Yes | K80: https://docs.google.com/presentation/d/1w6zbxZ-IP-d8JIvt92fKb847qBwcJWLG/edit?usp=drivesdk&ouid=109901495158487957834&rtpof=true&sd=true | L80: https://drive.google.com/drive/folders/11FfjTUKh-FPQhCcOhtIda6V1nSSo_Z9J
A81: MTC-083 | B81: Operating on Numbers | C81: Define new operations by combining familiar ones, then investigate their properties, associated formulas, and connections to symmetry and multivariable functions. | D81: Algebra | F81: binary operations; symmetry; functions | G81: 2021-03-02 | H81: MTC academic-year session | I81: =COUNTIF(Offerings!$B$5:$B$145,A81) -> 1 | J81: =IF(COUNTIFS(Offerings!$B$5:$B$145,A81,Offerings!$K$5:$K$145,"Yes")>0,"Yes","No") -> No | K81: https://drive.google.com/file/d/1Ztapvj-KkNmR0ws9aV3V3qc2xwvPFqKc/view?usp=drivesdk | L81: https://drive.google.com/drive/folders/1CVZF71C2s9mxmRG6_lKsCqljz3GnKqyy
A82: MTC-084 | B82: Pancake Sorting and Recursion | C82: Investigate how to sort a stack of pancakes by flipping portions of the stack, and connect strategies with sorting algorithms and recursion. | D82: Algorithms & Computing | E82: Combinatorics | F82: sorting; recursion; algorithms | G82: 2016-09-06 2023-11-07 | H82: MTC academic-year session | I82: =COUNTIF(Offerings!$B$5:$B$145,A82) -> 2 | J82: =IF(COUNTIFS(Offerings!$B$5:$B$145,A82,Offerings!$K$5:$K$145,"Yes")>0,"Yes","No") -> No | K82: https://drive.google.com/file/d/1vndeRMVvzkTjPX-nDoOGaCkcv4leGQcI/view?usp=drivesdk | L82: https://drive.google.com/drive/folders/1WTzMMoPReWPNCbL9NzWXSzbglOr2ulUi
A83: MTC-085 | B83: Partition Like Piet: Mondrian Puzzles | C83: Partition a square into rectangles and search for arrangements that minimize the difference between the largest and smallest areas. | D83: Geometry | E83: Combinatorics | F83: partitioning; area; optimization | G83: 2020-05-05 | H83: MTC academic-year session | I83: =COUNTIF(Offerings!$B$5:$B$145,A83) -> 1 | J83: =IF(COUNTIFS(Offerings!$B$5:$B$145,A83,Offerings!$K$5:$K$145,"Yes")>0,"Yes","No") -> No | K83: https://drive.google.com/file/d/1wUSXfacX_VeWYYM4Bg6VGQJT1F6qzVz8/view?usp=drivesdk | L83: https://drive.google.com/drive/folders/1QEX_uFoZOctsQRNl9iMQs8y_FnbIUd36
A84: MTC-086 | B84: Pick Connects the Dots | C84: Use lattice points and Pick’s theorem to investigate polygon areas without measuring every edge. | D84: Geometry | E84: Number Theory | F84: Pick’s theorem; lattice polygons; area | G84: 2018-02-06 | H84: MTC academic-year session | I84: =COUNTIF(Offerings!$B$5:$B$145,A84) -> 1 | J84: =IF(COUNTIFS(Offerings!$B$5:$B$145,A84,Offerings!$K$5:$K$145,"Yes")>0,"Yes","No") -> No | K84: https://drive.google.com/file/d/1R1gYmeYW9Lj7iffE529TqyvGBsKE07mJ/view?usp=drivesdk | L84: https://drive.google.com/drive/folders/1q_2vVslIW9JqR0NSnnPxMRve8Qwb7L4m
A85: MTC-087 | B85: Pirates, Prisoners, and Chicken: An Introduction to Game Theory | C85: Analyze pirate bargaining, prisoners’ choices, and Chicken to explore how game theory models decisions involving other people. | D85: Game Theory | E85: Mathematical Modeling | F85: decision making; prisoner’s dilemma; strategy | G85: 2016-12-06 | H85: MTC academic-year session | I85: =COUNTIF(Offerings!$B$5:$B$145,A85) -> 1 | J85: =IF(COUNTIFS(Offerings!$B$5:$B$145,A85,Offerings!$K$5:$K$145,"Yes")>0,"Yes","No") -> No | K85: https://drive.google.com/file/d/0B4cCTfJeL7_dZ0d4eFRvY0M2WFU/view?usp=drivesdk&resourcekey=0-BU-CIxJ-KiHzrpFxXsS3uA | L85: https://drive.google.com/drive/folders/0B4cCTfJeL7_dOFBFa3FZZ3p3X2s?resourcekey=0-3nvbz4Z7QcO8Jp0kPrED0Q
A86: MTC-089 | B86: Puzzling Pairs | C86: Arrange pairs of numbers with prescribed gaps, investigate which sizes permit solutions, and develop conjectures about Langford pairings. | D86: Combinatorics | E86: Number Theory | F86: Langford pairs; sequences; constraints; patterns | G86: 2025-06-13 | H86: Summer Institute | I86: =COUNTIF(Offerings!$B$5:$B$145,A86) -> 1 | J86: =IF(COUNTIFS(Offerings!$B$5:$B$145,A86,Offerings!$K$5:$K$145,"Yes")>0,"Yes","No") -> No | K86: https://docs.google.com/presentation/d/10l4IUqFNcsGDdI3EpPfWoRRLD8XacO6N/edit?usp=drivesdk&ouid=109901495158487957834&rtpof=true&sd=true | L86: https://drive.google.com/drive/folders/1jiWrWvgndwUoN-3kKi7cHTNb1bV9KyRS
A87: MTC-090 | B87: Rational Tangle Dance | C87: Create and undo rope tangles through a team activity that connects physical moves with the mathematics of rational tangles. | D87: Number Sense & Arithmetic | E87: Fractions | F87: rational tangles; fractions; collaboration | G87: 2016-10-04 2024-03-05 | H87: MTC academic-year session | I87: =COUNTIF(Offerings!$B$5:$B$145,A87) -> 2 | J87: =IF(COUNTIFS(Offerings!$B$5:$B$145,A87,Offerings!$K$5:$K$145,"Yes")>0,"Yes","No") -> No | K87: https://drive.google.com/file/d/1B7Q5yK1f3xX3sHWaqFA1_Bduwr6mzuEF/view?usp=drivesdk | L87: https://drive.google.com/drive/folders/1O2jKo-ETXHHkmhuLB0PkeiBkg4GUX2Eg
A88: MTC-091 | B88: Reading Apprenticeship: Cognitive Dimension | C88: Practice cognitive tools for reading mathematical texts, including metacognitive logs, chunking, visualization, and concise summaries. | D88: Teaching & Learning | F88: Reading Apprenticeship; reading logs; summarizing; visualizing | G88: 2024-06-21 | H88: Summer Institute | I88: =COUNTIF(Offerings!$B$5:$B$145,A88) -> 1 | J88: =IF(COUNTIFS(Offerings!$B$5:$B$145,A88,Offerings!$K$5:$K$145,"Yes")>0,"Yes","No") -> No | K88: https://drive.google.com/file/d/1t8tfTw2is6Du8xU7ARDOulPBDoLmJaJX/view?usp=drivesdk | L88: https://drive.google.com/drive/folders/1snYWtnWJn7o1t_f6MUW9IZgU42PPlM5Z
A89: MTC-092 | B89: Reading Apprenticeship: Knowledge-Building Dimension | C89: Practice routines that surface students’ existing knowledge and help them connect, revise, and extend that knowledge while reading mathematics. | D89: Teaching & Learning | F89: Reading Apprenticeship; prior knowledge; KWL; discussion routines | G89: 2024-06-20 | H89: Summer Institute | I89: =COUNTIF(Offerings!$B$5:$B$145,A89) -> 1 | J89: =IF(COUNTIFS(Offerings!$B$5:$B$145,A89,Offerings!$K$5:$K$145,"Yes")>0,"Yes","No") -> No | K89: https://drive.google.com/file/d/1IerOufU-I3O6lO8wLxykX9qwjmOlfubF/view?usp=drivesdk | L89: https://drive.google.com/drive/folders/1yFqMd8ssJpVqMg2bbU912bXb6yPDduyD
A90: MTC-093 | B90: Reading Apprenticeship: Overview and Metacognition | C90: Make reading processes visible and explore how Reading Apprenticeship helps students become more independent readers of mathematical texts. | D90: Teaching & Learning | F90: Reading Apprenticeship; metacognition; disciplinary literacy | G90: 2024-06-17 | H90: Summer Institute | I90: =COUNTIF(Offerings!$B$5:$B$145,A90) -> 1 | J90: =IF(COUNTIFS(Offerings!$B$5:$B$145,A90,Offerings!$K$5:$K$145,"Yes")>0,"Yes","No") -> No | K90: https://drive.google.com/file/d/1vR-zXRsqpuCQaAAcfScMMTknXXDhOLzQ/view?usp=drivesdk | L90: https://drive.google.com/drive/folders/1D5XL0CBZfHJZLZw1ZN2PGYYv5YIfHmNB
A91: MTC-094 | B91: Reading Apprenticeship: Personal and Social Dimensions | C91: Explore routines that build classroom community, support positive mathematical identities, and make participation and thinking more equitable. | D91: Teaching & Learning | F91: Reading Apprenticeship; math identity; equitable participation | G91: 2024-06-18 | H91: Summer Institute | I91: =COUNTIF(Offerings!$B$5:$B$145,A91) -> 1 | J91: =IF(COUNTIFS(Offerings!$B$5:$B$145,A91,Offerings!$K$5:$K$145,"Yes")>0,"Yes","No") -> No | K91: https://drive.google.com/file/d/1d8WszCKgr-I7gXzwDQAk6Fj3KtBgwMhv/view?usp=drivesdk | L91: https://drive.google.com/drive/folders/1w6xM2kGSSbD4PCZLHdr-unbOnhRxHtwo
A92: MTC-095 | B92: Risk in the Stock Market | C92: Use probability, statistics, and simulation to investigate investment risk and why diversification changes the behavior of a portfolio. | D92: Probability & Statistics | E92: Mathematical Modeling | F92: simulation; diversification; risk | G92: 2019-10-01 | H92: MTC academic-year session | I92: =COUNTIF(Offerings!$B$5:$B$145,A92) -> 1 | J92: =IF(COUNTIFS(Offerings!$B$5:$B$145,A92,Offerings!$K$5:$K$145,"Yes")>0,"Yes","No") -> No | K92: https://drive.google.com/file/d/1g_FJ_SokTuc1cmcJJya9SSHliXcz8aj_/view?usp=drivesdk | L92: https://drive.google.com/drive/folders/1C8zlEji75_NnIvC-ezPPXLj5nzOB8G7Q
A93: MTC-096 | B93: SET: The Mathematics Behind the Game | C93: Play SET and investigate counting questions, conditions that guarantee a set, and geometric interpretations of the cards. | D93: Combinatorics | E93: Geometry | F93: SET; card games; counting | G93: 2017-02-07 (review) | H93: MTC academic-year session | I93: =COUNTIF(Offerings!$B$5:$B$145,A93) -> 1 | J93: =IF(COUNTIFS(Offerings!$B$5:$B$145,A93,Offerings!$K$5:$K$145,"Yes")>0,"Yes","No") -> Yes | K93: https://drive.google.com/file/d/0B4cCTfJeL7_dQ2lLeDdMUDhwX28/view?usp=drivesdk&resourcekey=0-WVYtZLMYQXEHOqfrY_cTog | L93: https://drive.google.com/drive/folders/0B4cCTfJeL7_ddmlxWS1KMEhRUU0?resourcekey=0-OSSepIY-DO-yW5nAxaOcUg
A94: MTC-097 | B94: Seeing Math in Photos | C94: Find mathematical features in photographs and use Desmos points, functions, sliders, and regression to represent them. | D94: Geometry | E94: Algebra; Teaching & Learning | F94: photography; Desmos; functions; modeling | G94: 2022-06-22 | H94: Summer Institute | I94: =COUNTIF(Offerings!$B$5:$B$145,A94) -> 1 | J94: =IF(COUNTIFS(Offerings!$B$5:$B$145,A94,Offerings!$K$5:$K$145,"Yes")>0,"Yes","No") -> No | K94: https://docs.google.com/presentation/d/1VIKwg8XbFC1-lEdcFHW1O03cXamwbINDBOi2FuJ3CLA/edit?usp=drivesdk | L94: https://drive.google.com/drive/folders/1S4RXsHe-nlbaLXgBSSgAnb8zt7jYvF1e
A95: MTC-098 | B95: Setting the Stage for Professional Learning | C95: Explore the structure and recurring practices of the MPLP professional-learning modules and connect them with equitable mathematics teaching. | D95: Teaching & Learning | F95: MPLP; teacher leadership; professional learning | G95: 2026-06-15 | H95: Summer Institute | I95: =COUNTIF(Offerings!$B$5:$B$145,A95) -> 1 | J95: =IF(COUNTIFS(Offerings!$B$5:$B$145,A95,Offerings!$K$5:$K$145,"Yes")>0,"Yes","No") -> No | K95: https://docs.google.com/presentation/d/1jFtKXH-aLhBtDGbREnCUhanu9-3WelMf/edit?usp=drivesdk&ouid=109901495158487957834&rtpof=true&sd=true | L95: https://drive.google.com/drive/folders/1p_V_zMd7U5Usmmm_pc1ghlzTvB84LP-G
A96: MTC-099 | B96: Sharing Leadership and Lesson Plans | C96: Use a structured presentation and response protocol to share lesson, coaching, or leadership plans and refine them through peer feedback. | D96: Teaching & Learning | F96: peer feedback; lesson planning; teacher leadership | G96: 2026-06-18 | H96: Summer Institute | I96: =COUNTIF(Offerings!$B$5:$B$145,A96) -> 1 | J96: =IF(COUNTIFS(Offerings!$B$5:$B$145,A96,Offerings!$K$5:$K$145,"Yes")>0,"Yes","No") -> No | K96: https://docs.google.com/document/d/1cZ5to3LfAYUrqhdMgv8jv2XCtHTPxWmL/edit?usp=drivesdk&ouid=109901495158487957834&rtpof=true&sd=true | L96: https://drive.google.com/drive/folders/1_LvYC5COwUaXTMX7PeFWbg9OJGhFgFca
A97: MTC-100 | B97: Simon Says, Four Gallons | C97: Solve water-jug measuring puzzles and explore efficient strategies and connections with geometry and number theory. | D97: Number Theory | E97: Geometry | F97: water jugs; measurement; algorithms | G97: 2017-09-05 | H97: MTC academic-year session | I97: =COUNTIF(Offerings!$B$5:$B$145,A97) -> 1 | J97: =IF(COUNTIFS(Offerings!$B$5:$B$145,A97,Offerings!$K$5:$K$145,"Yes")>0,"Yes","No") -> No | K97: https://drive.google.com/file/d/0B4cCTfJeL7_deVFiWDRMT1VQYmc/view?usp=drivesdk&resourcekey=0-8EUWjRObcmI30hRFwB6oZg | L97: https://drive.google.com/drive/folders/0B4cCTfJeL7_dUFNwTFBrNUU4VzA?resourcekey=0-96gg3J2fV_f4hY50lKOCkg
A98: MTC-101 | B98: Skyscrapers, Flowers and JRMF | C98: Solve Skyscrapers and Magic Flowers puzzles, develop strategies, and generalize numerical patterns to new puzzle configurations. | D98: Logic & Proof | E98: Number Sense & Arithmetic | F98: JRMF; Skyscrapers; Magic Flowers; patterns | G98: 2023-03-07 | H98: MTC academic-year session | I98: =COUNTIF(Offerings!$B$5:$B$145,A98) -> 1 | J98: =IF(COUNTIFS(Offerings!$B$5:$B$145,A98,Offerings!$K$5:$K$145,"Yes")>0,"Yes","No") -> No | K98: https://drive.google.com/file/d/1l0rFahE46JC40HQmew09pmSGnKaD6Aqw/view?usp=drivesdk | L98: https://drive.google.com/drive/folders/1lkUmGq_Y7NtSZasPCqeDj-XrmE5_Bhr-
A99: MTC-103 | B99: Spaghetti Tower Challenge | C99: Build a freestanding tower from spaghetti, tape, and string that supports a marshmallow, working within shared material and time constraints. | D99: Teaching & Learning | E99: Geometry | F99: collaboration; design challenge; structures | G99: 2017-06-15 to 2017-06-16 (institute window) | H99: Summer Institute | I99: =COUNTIF(Offerings!$B$5:$B$145,A99) -> 1 | J99: =IF(COUNTIFS(Offerings!$B$5:$B$145,A99,Offerings!$K$5:$K$145,"Yes")>0,"Yes","No") -> Yes | K99: https://docs.google.com/presentation/d/0B4cCTfJeL7_dNkFpWHhUbkk5cmM/edit?usp=drivesdk&ouid=109901495158487957834&resourcekey=0-14wM74J9lM5YAVbPFV4nyA&rtpof=true&sd=true | L99: https://drive.google.com/drive/folders/0B4cCTfJeL7_dWTVUcFFkV2tlRkk?resourcekey=0-HN2srsoL-ck5T3_rtb41LA
A100: MTC-104 | B100: Spot It! | C100: Investigate how a Spot It! deck is constructed so that pairs of cards share a symbol, and explore the mathematical structure behind the game. | D100: Combinatorics | E100: Geometry | F100: card games; finite geometry; design | G100: 2017-05-02 (review) 2024-11-12 | H100: MTC academic-year session | I100: =COUNTIF(Offerings!$B$5:$B$145,A100) -> 2 | J100: =IF(COUNTIFS(Offerings!$B$5:$B$145,A100,Offerings!$K$5:$K$145,"Yes")>0,"Yes","No") -> Yes | K100: https://drive.google.com/file/d/1fyBYeYwxeATEWKWiYzFiSKURO8PobL2m/view?usp=drivesdk | L100: https://drive.google.com/drive/folders/1t8JHMXL6yAnZ5kv4Cu0yeTJkhD-57FPV
A101: MTC-105 | B101: Spread of Disease | C101: Use simulation and a logistic-curve model to investigate the spread of disease and discuss the assumptions involved in modeling it. | D101: Mathematical Modeling | E101: Probability & Statistics | F101: simulation; logistic growth; Desmos | G101: 2021-06-18 | H101: Summer Institute | I101: =COUNTIF(Offerings!$B$5:$B$145,A101) -> 1 | J101: =IF(COUNTIFS(Offerings!$B$5:$B$145,A101,Offerings!$K$5:$K$145,"Yes")>0,"Yes","No") -> No | K101: https://docs.google.com/document/d/1XgBPtwa7dVUiBdYAa1nvv7DqLhWe7ho8BS23HndmozU/edit?usp=drivesdk | L101: https://drive.google.com/drive/folders/1jMaUXv_moFqp4vPk7rMqgcL-NFSsSY0E
...

Sheet Offerings
A1: Documented offerings
A2: 148 offering records . 28 flagged for review . Start/end dates may be candidate dates or institute windows; read Date status
A4: Offering ID | B4: Session ID | C4: Session title | D4: Start date | E4: End date | F4: Date label | G4: Date status | H4: Program | I4: Archive context | J4: Facilitator / presenter | K4: Review needed | L4: Source notes / review details | M4: Source URL 1 | N4: Source URL 2 | O4: Resource folder URL
A5: OFR-001 | B5: MTC-084 | C5: Pancake Sorting and Recursion | D5: 42619 | E5: 42619 | F5: 2016-09-06 | G5: Exact date | H5: MTC academic-year session | I5: 2016-2017 Academic Year/9/6/16 Pancake Sorting | K5: No | M5: https://drive.google.com/file/d/0B4cCTfJeL7_deUdjclQ3NnFELVU/view?usp=drivesdk&resourcekey=0-zp3Cn9a3fXHo_C2g_YC3cw | O5: https://drive.google.com/drive/folders/0B4cCTfJeL7_dQ2RycmJVeTNETXM?resourcekey=0-4K6CIC7x0R0waYq99bkWGA
A6: OFR-002 | B6: MTC-090 | C6: Rational Tangle Dance | D6: 42647 | E6: 42647 | F6: 2016-10-04 | G6: Exact date | H6: MTC academic-year session | I6: 2016-2017 Academic Year/10/4/16 Rational Tangles | K6: No | M6: https://drive.google.com/file/d/0B4cCTfJeL7_dVUtKWVJXMnA5XzQ/view?usp=drivesdk&resourcekey=0-6BQhmPR9EvS9WJPbXzkZiA | O6: https://drive.google.com/drive/folders/0B4cCTfJeL7_dU1FKRzl0RldhR0U?resourcekey=0-Y0algVj--3lZVPKkuZKJiQ
A7: OFR-003 | B7: MTC-116 | C7: The Mad Veterinarian | D7: 42675 | E7: 42675 | F7: 2016-11-01 | G7: Exact date | H7: MTC academic-year session | I7: 2016-2017 Academic Year/11/1/16 Mad Vet | K7: No | M7: https://drive.google.com/file/d/0B4cCTfJeL7_dcUF3dHJHWjJiMEE/view?usp=drivesdk&resourcekey=0-81akf2SWjep3EUPUzYf7mg | O7: https://drive.google.com/drive/folders/0B4cCTfJeL7_dZ3YwX2JjODYxVVk?resourcekey=0-e5oGqFPne975XL1jVl2yRg
A8: OFR-004 | B8: MTC-087 | C8: Pirates, Prisoners, and Chicken: An Introduction to Game Theory | D8: 42710 | E8: 42710 | F8: 2016-12-06 | G8: Exact date | H8: MTC academic-year session | I8: 2016-2017 Academic Year/12/6/16 Game Theory | K8: No | M8: https://drive.google.com/file/d/0B4cCTfJeL7_dZ0d4eFRvY0M2WFU/view?usp=drivesdk&resourcekey=0-BU-CIxJ-KiHzrpFxXsS3uA | O8: https://drive.google.com/drive/folders/0B4cCTfJeL7_dOFBFa3FZZ3p3X2s?resourcekey=0-3nvbz4Z7QcO8Jp0kPrED0Q
A9: OFR-005 | B9: MTC-096 | C9: SET: The Mathematics Behind the Game | D9: 42773 | E9: 42773 | F9: 2017-02-07 (review) | G9: Date conflict | H9: MTC academic-year session | I9: 2016-2017 Academic Year/2/7/17 Set | K9: Yes | L9: Flyer says 2016-02-07; academic-year folder places the session in 2017. Date shown follows folder context; confirm before publication. | M9: https://drive.google.com/file/d/0B4cCTfJeL7_dQ2lLeDdMUDhwX28/view?usp=drivesdk&resourcekey=0-WVYtZLMYQXEHOqfrY_cTog | O9: https://drive.google.com/drive/folders/0B4cCTfJeL7_ddmlxWS1KMEhRUU0?resourcekey=0-OSSepIY-DO-yW5nAxaOcUg
A10: OFR-006 | B10: MTC-049 | C10: KenKen | D10: 42801 | E10: 42801 | F10: 2017-03-07 (review) | G10: Date conflict | H10: MTC academic-year session | I10: 2016-2017 Academic Year/3/7/17 KenKen | K10: Yes | L10: Flyer says 2016-03-07; academic-year folder places the session in 2017. Date shown follows folder context; confirm before publication. | M10: https://drive.google.com/file/d/0B4cCTfJeL7_dUlREbmJoWGpoRlU/view?usp=drivesdk&resourcekey=0-2KQz8LJ2bXF_iO3B4_-4tg | O10: https://drive.google.com/drive/folders/0B4cCTfJeL7_dNzh2OXc3WDN5Tjg?resourcekey=0-6YR3U00KQXCHW6GbAQ7Q7w
A11: OFR-007 | B11: MTC-055 | C11: Liar’s Bingo | D11: 42829 | E11: 42829 | F11: 2017-04-04 (review) | G11: Date conflict | H11: MTC academic-year session | I11: 2016-2017 Academic Year/4/4/17 Liar's Bingo | K11: Yes | L11: Flyer says 2016-04-04; academic-year folder places the session in 2017. Date shown follows folder context; confirm before publication. | M11: https://drive.google.com/file/d/0B4cCTfJeL7_dczlEMzB2eGQ5YVk/view?usp=drivesdk&resourcekey=0-GCGp3Qs2y9W6daypRLoWtA | O11: https://drive.google.com/drive/folders/0B4cCTfJeL7_dWWMzbGxOSjVGdWc?resourcekey=0-_FeKZxpz7-puqnxrmu6Z9A
A12: OFR-008 | B12: MTC-104 | C12: Spot It! | D12: 42857 | E12: 42857 | F12: 2017-05-02 (review) | G12: Date conflict | H12: MTC academic-year session | I12: 2016-2017 Academic Year/5/2/17 Spot It! | K12: Yes | L12: Flyer says 2016-05-02; academic-year folder places the session in 2017. Date shown follows folder context; confirm before publication. | M12: https://drive.google.com/file/d/0B4cCTfJeL7_dQUQ3eU5sOE5MWUU/view?usp=drivesdk&resourcekey=0-Cw1xQYQCqNsv5bN4o85e6w | O12: https://drive.google.com/drive/folders/0B4cCTfJeL7_dbUI1cU4yc3hVblU?resourcekey=0-54WnQLLZfcFpfgeyMwqqEw
A13: OFR-010 | B13: MTC-045 | C13: Instant Insanity | D13: 42901 | E13: 42902 | F13: 2017-06-15 to 2017-06-16 (institute window) | G13: Institute window | H13: Summer Institute | I13: 2017 Summer Institute | K13: Yes | L13: Individual session day is not established; slide author is Judith Covington, not verified as the local facilitator. | M13: https://docs.google.com/presentation/d/0B4cCTfJeL7_dZ084MGZNUjVBU1E/edit?usp=drivesdk&ouid=109901495158487957834&resourcekey=0-xqQaukkaqbnIwZhtqkr3HQ&rtpof=true&sd=true | N13: https://drive.google.com/file/d/0B4cCTfJeL7_dU3lfY2t4ckNZQ3M/view?usp=drivesdk&resourcekey=0-mgNytrTm-j1DMeP0R_Ki6w | O13: https://drive.google.com/drive/folders/0B4cCTfJeL7_dQTJaNFc5empWbUE?resourcekey=0-8hWfh9_udgJ8jFMROirwEg
A14: OFR-011 | B14: MTC-057 | C14: Logic: Knights and Knaves | D14: 42901 | E14: 42902 | F14: 2017-06-15 to 2017-06-16 (institute window) | G14: Institute window | H14: Summer Institute | I14: 2017 Summer Institute | K14: Yes | L14: Individual session day is not established. Slides credit Martha Rojas. | M14: https://docs.google.com/presentation/d/0B2XvpmARE9ZbMnZCM0ZOaHZXSVk/edit?usp=drivesdk&ouid=109901495158487957834&resourcekey=0-V7nKYNXuHYTwHhbaPrZV6w&rtpof=true&sd=true | N14: https://drive.google.com/file/d/0B4cCTfJeL7_dU3lfY2t4ckNZQ3M/view?usp=drivesdk&resourcekey=0-mgNytrTm-j1DMeP0R_Ki6w | O14: https://drive.google.com/drive/folders/0B4cCTfJeL7_dWWlYb3JRTVljWlU?resourcekey=0-NwX1MEHlBgX_Rxr44Y1iBQ
A15: OFR-012 | B15: MTC-062 | C15: Mastermind | D15: 42901 | E15: 42902 | F15: 2017-06-15 to 2017-06-16 (institute window) | G15: Institute window | H15: Summer Institute | I15: 2017 Summer Institute | K15: Yes | L15: Individual session day is not established. | M15: https://docs.google.com/presentation/d/0B4cCTfJeL7_dbkR1d0RQeHRMclU/edit?usp=drivesdk&ouid=109901495158487957834&resourcekey=0-qaLSVqn8XKSsNH4sKGV55g&rtpof=true&sd=true | N15: https://drive.google.com/file/d/0B4cCTfJeL7_dU3lfY2t4ckNZQ3M/view?usp=drivesdk&resourcekey=0-mgNytrTm-j1DMeP0R_Ki6w | O15: https://drive.google.com/drive/folders/0B4cCTfJeL7_dTHBkS1RrSkdGa1E?resourcekey=0-t_6NCUKHfrRprA1_i9yyhw
A16: OFR-013 | B16: MTC-080 | C16: Number Bracelets | D16: 42901 | E16: 42902 | F16: 2017-06-15 to 2017-06-16 (institute window) | G16: Institute window | H16: Summer Institute | I16: 2017 Summer Institute | K16: Yes | L16: Folder identifies a Number Bracelets mini-session; local PDF/PPT text was unavailable. Description uses the matching 2023 session flyer. Individual day is not established. | M16: https://drive.google.com/file/d/0B4cCTfJeL7_dZEszNWJvRHBDQkU/view?usp=drivesdk&resourcekey=0-JEkHg4pkfRvfDuTq1EmA7g | N16: https://drive.google.com/file/d/0B4cCTfJeL7_dU3lfY2t4ckNZQ3M/view?usp=drivesdk&resourcekey=0-mgNytrTm-j1DMeP0R_Ki6w | O16: https://drive.google.com/drive/folders/0B4cCTfJeL7_dU2JKWnFJcGtBY00?resourcekey=0-FP1TbLBlmig7a_ncKTRKmg
A17: OFR-014 | B17: MTC-103 | C17: Spaghetti Tower Challenge | D17: 42901 | E17: 42902 | F17: 2017-06-15 to 2017-06-16 (institute window) | G17: Institute window | H17: Summer Institute | I17: 2017 Summer Institute | K17: Yes | L17: Included as a named institute activity; individual day is not established. | M17: https://docs.google.com/presentation/d/0B4cCTfJeL7_dNkFpWHhUbkk5cmM/edit?usp=drivesdk&ouid=109901495158487957834&resourcekey=0-14wM74J9lM5YAVbPFV4nyA&rtpof=true&sd=true | N17: https://drive.google.com/file/d/0B4cCTfJeL7_dU3lfY2t4ckNZQ3M/view?usp=drivesdk&resourcekey=0-mgNytrTm-j1DMeP0R_Ki6w | O17: https://drive.google.com/drive/folders/0B4cCTfJeL7_dWTVUcFFkV2tlRkk?resourcekey=0-HN2srsoL-ck5T3_rtb41LA
A18: OFR-015 | B18: MTC-106 | C18: Sprouts | D18: 42901 | E18: 42902 | F18: 2017-06-15 to 2017-06-16 (institute window) | G18: Institute window | H18: Summer Institute | I18: 2017 Summer Institute | K18: Yes | L18: Individual session day is not established. | M18: https://docs.google.com/presentation/d/0B4cCTfJeL7_dUGgtc2hVRVZkZFU/edit?usp=drivesdk&ouid=109901495158487957834&resourcekey=0-xyg98UR1GYtUjh9gnA0xIg&rtpof=true&sd=true | N18: https://drive.google.com/file/d/0B4cCTfJeL7_dU3lfY2t4ckNZQ3M/view?usp=drivesdk&resourcekey=0-mgNytrTm-j1DMeP0R_Ki6w | O18: https://drive.google.com/drive/folders/0B4cCTfJeL7_dcFp4bFRZSFpnNDg?resourcekey=0-hSfkHFOkkiJTtdq-rI2V5Q
A19: OFR-016 | B19: MTC-100 | C19: Simon Says, Four Gallons | D19: 42983 | E19: 42983 | F19: 2017-09-05 | G19: Exact date | H19: MTC academic-year session | I19: 2017-2018 Academic Year/9/5/17 Simon Says, Four Gallons | K19: No | M19: https://drive.google.com/file/d/0B4cCTfJeL7_deVFiWDRMT1VQYmc/view?usp=drivesdk&resourcekey=0-8EUWjRObcmI30hRFwB6oZg | O19: https://drive.google.com/drive/folders/0B4cCTfJeL7_dUFNwTFBrNUU4VzA?resourcekey=0-96gg3J2fV_f4hY50lKOCkg
A20: OFR-017 | B20: MTC-027 | C20: Estimathon | D20: 43011 | E20: 43011 | F20: 2017-10-03 | G20: Exact date | H20: MTC academic-year session | I20: 2017-2018 Academic Year/10/3/17 Estimathon | K20: No | M20: https://drive.google.com/file/d/0B4cCTfJeL7_dV0lNaHRySThBV1k/view?usp=drivesdk&resourcekey=0-4tLGwO-rngRT5TqyiZh4jw | O20: https://drive.google.com/drive/folders/0B4cCTfJeL7_dYkh0eHhlc1o5dVE?resourcekey=0-mQ9ZVlb8YaF0fKERKMu7-w
A21: OFR-018 | B21: MTC-014 | C21: Candy Sharing | D21: 43046 | E21: 43046 | F21: 2017-11-07 | G21: Exact date | H21: MTC academic-year session | I21: 2017-2018 Academic Year/11/7/17 Candy Sharing | K21: No | M21: https://drive.google.com/file/d/0B4cCTfJeL7_dNG1SRGJIUWh4R2c/view?usp=drivesdk&resourcekey=0-jEyNsfAltNj9lA6QZChKPQ | O21: https://drive.google.com/drive/folders/0B4cCTfJeL7_demd3d3RFTkZKWnM?resourcekey=0-MzT-jVW9rtLCFP_7rXBvcw
A22: OFR-019 | B22: MTC-048 | C22: Is Santa Secretly Deranged? | D22: 43074 | E22: 43074 | F22: 2017-12-05 | G22: Exact date | H22: MTC academic-year session | I22: 2017-2018 Academic Year/12/5/17 Secret Santa | K22: No | M22: https://drive.google.com/file/d/0B4cCTfJeL7_dRGtKNnNWdTZYdDQ/view?usp=drivesdk&resourcekey=0-nGy0YI7Lwf594ydSovumNg | O22: https://drive.google.com/drive/folders/0B4cCTfJeL7_dMXY5aFFEVmV4WWM?resourcekey=0-kjwEUe_Jp8A26HRYrpu0_g
A23: OFR-020 | B23: MTC-086 | C23: Pick Connects the Dots | D23: 43137 | E23: 43137 | F23: 2018-02-06 | G23: Resolved source typo | H23: MTC academic-year session | I23: 2017-2018 Academic Year/2/6/18 Pick Connects the Dots | K23: No | L23: Flyer says 2017-02-06; academic-year folder places the session in 2018. Date shown is corroborated by the dated folder and the 2017–2018 annual meeting schedule. | M23: https://drive.google.com/file/d/1R1gYmeYW9Lj7iffE529TqyvGBsKE07mJ/view?usp=drivesdk | N23: https://drive.google.com/file/d/0B4cCTfJeL7_ddFdsUVdRLXlaTzQ/view?usp=drivesdk&resourcekey=0-JM9t5EGhZrOqAE-8IEEG4g | O23: https://drive.google.com/drive/folders/1q_2vVslIW9JqR0NSnnPxMRve8Qwb7L4m
A24: OFR-021 | B24: MTC-114 | C24: The Game of Hex | D24: 43165 | E24: 43165 | F24: 2018-03-06 | G24: Resolved source typo | H24: MTC academic-year session | I24: 2017-2018 Academic Year/3/6/18 Hex | K24: No | L24: Flyer says 2017-03-06; academic-year folder places the session in 2018. Date shown is corroborated by the dated folder and the 2017–2018 annual meeting schedule. | M24: https://drive.google.com/file/d/1bLa7gfa8xUVahh1Gr22CDvwwh9Pj1nge/view?usp=drivesdk | N24: https://drive.google.com/file/d/0B4cCTfJeL7_ddFdsUVdRLXlaTzQ/view?usp=drivesdk&resourcekey=0-JM9t5EGhZrOqAE-8IEEG4g | O24: https://drive.google.com/drive/folders/1TCrLedo3dh09m9uQ3HBEV1-k7I6qxZZf
A25: OFR-023 | B25: MTC-050 | C25: Knot Mosaics | D25: 43221 | E25: 43221 | F25: 2018-05-01 | G25: Exact date | H25: MTC academic-year session | I25: 2017-2018 Academic Year/5/1/18 Knot Mosaics | K25: No | M25: https://drive.google.com/file/d/11ZpvXPWejLT5th3HJ3hSWalPALNrBgMz/view?usp=drivesdk | O25: https://drive.google.com/drive/folders/1jnKOroAXawrv7jPNAbeqiP_dv2ScX-o2
A26: OFR-024 | B26: MTC-004 | C26: Alternate Algorithms | D26: 43269 | E26: 43272 | F26: 2018-06-18 to 2018-06-21 (institute window) | G26: Institute window | H26: Summer Institute | I26: 2018 Summer Institute | K26: Yes | L26: Individual session day is not established. Slides credit Part I to Martha Rojas and Part II to Dr. Jones. | M26: https://docs.google.com/presentation/d/1u6vBmLM7voR7AKzROirAZsQji_7M82HC/edit?usp=drivesdk&ouid=109901495158487957834&rtpof=true&sd=true | N26: https://docs.google.com/presentation/d/1w6zbxZ-IP-d8JIvt92fKb847qBwcJWLG/edit?usp=drivesdk&ouid=109901495158487957834&rtpof=true&sd=true | O26: https://drive.google.com/drive/folders/1SdYWc2admzVtcf9FW5D6I12sTV-2Ivi4
A27: OFR-026 | B27: MTC-029 | C27: Exploding Dots | D27: 43269 | E27: 43270 | F27: 2018-06-18 to 2018-06-19 | G27: Multi-day session | H27: Summer Institute | I27: 2018 Summer Institute | K27: No | L27: Part 1 slides specify June 18; Part 2 specifies June 19. Treated as one two-part offering. | M27: https://docs.google.com/presentation/d/1Xt1UGnUBeJ4dzoaQai64-gyIFavAC_P4/edit?usp=drivesdk&ouid=109901495158487957834&rtpof=true&sd=true | N27: https://docs.google.com/presentation/d/1t8J3ddja7Gsl0gzR603MUG_G9H8HWMHH/edit?usp=drivesdk&ouid=109901495158487957834&rtpof=true&sd=true | O27: https://drive.google.com/drive/folders/1fTD9nzVBBx-KwkD0_11w5IIrpzxiWWck
A28: OFR-027 | B28: MTC-082 | C28: Number Sense and Number Talks | D28: 43269 | E28: 43272 | F28: 2018-06-18 to 2018-06-21 (institute window) | G28: Institute window | H28: Summer Institute | I28: 2018 Summer Institute | K28: Yes | L28: Institute overview dates the event June 18–21; the individual session date is not explicit. | M28: https://docs.google.com/presentation/d/1w6zbxZ-IP-d8JIvt92fKb847qBwcJWLG/edit?usp=drivesdk&ouid=109901495158487957834&rtpof=true&sd=true | O28: https://drive.google.com/drive/folders/11FfjTUKh-FPQhCcOhtIda6V1nSSo_Z9J
A29: OFR-028 | B29: MTC-123 | C29: Tie Folding | D29: 43269 | E29: 43272 | F29: 2018-06-18 to 2018-06-21 (institute window) | G29: Institute window | H29: Summer Institute | I29: 2018 Summer Institute | K29: Yes | L29: Individual session day is not established. | M29: https://docs.google.com/presentation/d/1qex5opjxGqGC-i2oN65td994Ro2i69cr/edit?usp=drivesdk&ouid=109901495158487957834&rtpof=true&sd=true | N29: https://docs.google.com/presentation/d/1w6zbxZ-IP-d8JIvt92fKb847qBwcJWLG/edit?usp=drivesdk&ouid=109901495158487957834&rtpof=true&sd=true | O29: https://drive.google.com/drive/folders/1aNQ_FDnyCco1U3pa7SlDA983Xpvr33rR
A30: OFR-029 | B30: MTC-131 | C30: What I Learned About Sharing Long After Kindergarten | D30: 43347 | E30: 43347 | F30: 2018-09-04 | G30: Exact date | H30: MTC academic-year session | I30: 2018-2019 Academic Year/9/4 Fair Sharing | K30: No | M30: https://drive.google.com/file/d/1nsXDgel4Pb_3ipjtnjLBgSKMJJ-FfaQc/view?usp=drivesdk | O30: https://drive.google.com/drive/folders/1yOpm_cASa4HBAA6QgUjQdONtHIGUPE_n
A31: OFR-030 | B31: MTC-135 | C31: Winning the Lottery | D31: 43375 | E31: 43375 | F31: 2018-10-02 | G31: Exact date | H31: MTC academic-year session | I31: 2018-2019 Academic Year/10/2 Lottery | K31: No | M31: https://drive.google.com/file/d/18i5vhFOo7l9IdpyytXgObFTv-3tfjAKr/view?usp=drivesdk | O31: https://drive.google.com/drive/folders/1wXZbh9f63Wpej9tlYk4UVJ-kr04eYgtk
A32: OFR-031 | B32: MTC-010 | C32: Blokus and Polyominoes | D32: 43410 | E32: 43410 | F32: 2018-11-06 | G32: Year from academic-year folder | H32: MTC academic-year session | I32: 2018-2019 Academic Year/11/6 Blokus | K32: No | M32: https://drive.google.com/file/d/11LMWsczRyxmNkLaP_2Zb_5QISDRARhAM/view?usp=drivesdk | O32: https://drive.google.com/drive/folders/1i6fFH73dedn7uE3D5CrxC0mC5dTf-zL8
A33: OFR-032 | B33: MTC-032 | C33: Factoring in Time for Numeracy: Prime Climb | D33: 43438 | E33: 43438 | F33: 2018-12-04 | G33: Year from academic-year folder | H33: MTC academic-year session | I33: 2018-2019 Academic Year/12/4 Prime Climb | K33: No | M33: https://drive.google.com/file/d/16ak6R_4SaZE99Gsze3dcCRqK4fT_51pN/view?usp=drivesdk | O33: https://drive.google.com/drive/folders/1ffcjcyAm95Yy8nXxrdPMgVGMrNNJloao
A34: OFR-033 | B34: MTC-063 | C34: Match or No Match | D34: 43501 | E34: 43501 | F34: 2019-02-05 | G34: Year from academic-year folder | H34: MTC academic-year session | I34: 2018-2019 Academic Year/2/5 Match or No Match | K34: No | M34: https://drive.google.com/file/d/1uC4fIii10Gq-tSJ5Dwhw5_m51EwmJBEC/view?usp=drivesdk | O34: https://drive.google.com/drive/folders/1hAGkv8rqxLUASObqaWlFU_gVs-0zwUHv
A35: OFR-034 | B35: MTC-110 | C35: Symmetry and Algebra | D35: 43529 | E35: 43529 | F35: 2019-03-05 | G35: Year from academic-year folder | H35: MTC academic-year session | I35: 2018-2019 Academic Year/3/5 Symmetry and Algebra | K35: No | M35: https://drive.google.com/file/d/1xszrpVkaqbfBuJGGqZEcdB6l5hACiwzj/view?usp=drivesdk | O35: https://drive.google.com/drive/folders/1gkpHpNj4NZSQS1hdGddoKnZAOpmh2KUX
A36: OFR-035 | B36: MTC-037 | C36: Getting Nim-ble with Binary | D36: 43592 | E36: 43592 | F36: 2019-05-07 | G36: Year from academic-year folder | H36: MTC academic-year session | I36: 2018-2019 Academic Year/5/7 Nim | K36: No | M36: https://drive.google.com/file/d/1LmYLoppKA9ocXHlpg0I5khoTcvwL6DyI/view?usp=drivesdk | O36: https://drive.google.com/drive/folders/1oGJIHA5ZxR875CYuluh6RfpoRAxKMTrl
A37: OFR-037 | B37: MTC-018 | C37: Criss Cross | D37: 43636 | E37: 43637 | F37: 2019-06-20 to 2019-06-21 (review) | G37: Date conflict | H37: Summer Institute | I37: 2019 Summer Institute | K37: Yes | L37: Institute flyer gives June 20–21; session slides say June 19. Individual date needs confirmation. | M37: https://drive.google.com/file/d/1wZBu9JjpnZc-_lNGFN8W4n1F9bUGb0un/view?usp=drivesdk | N37: https://drive.google.com/file/d/18IAEnpI3zxkzzDaN-RwC1Odal0ARUM-i/view?usp=drivesdk | O37: https://drive.google.com/drive/folders/1NsrdraSpycoqCkhd5WqHbz2EyQAug4eW
A38: OFR-038 | B38: MTC-025 | C38: Eleusis | D38: 43636 | E38: 43637 | F38: 2019-06-20 to 2019-06-21 (institute window) | G38: Institute window | H38: Summer Institute | I38: 2019 Summer Institute | K38: Yes | L38: Individual session day is not established. Eleusis also appears within Duck Duck Deduce in 2024. | M38: https://docs.google.com/presentation/d/1eWTlS74T3knkqT6S_U0QG41FVvl8RVxy/edit?usp=drivesdk&ouid=109901495158487957834&rtpof=true&sd=true | N38: https://drive.google.com/file/d/18IAEnpI3zxkzzDaN-RwC1Odal0ARUM-i/view?usp=drivesdk | O38: https://drive.google.com/drive/folders/1nc7RfHAErgH-D9djo1jgGfxKw29-k9zM
A39: OFR-039 | B39: MTC-031 | C39: Facets of Proof | D39: 43636 | E39: 43637 | F39: 2019-06-20 to 2019-06-21 (institute window) | G39: Institute window | H39: Summer Institute | I39: 2019 Summer Institute | K39: Yes | L39: Individual session day is not established. | M39: https://docs.google.com/presentation/d/1pKYAhcrbgatmOoLS58fDMZghafRnEF7_/edit?usp=drivesdk&ouid=109901495158487957834&rtpof=true&sd=true | N39: https://drive.google.com/file/d/18IAEnpI3zxkzzDaN-RwC1Odal0ARUM-i/view?usp=drivesdk | O39: https://drive.google.com/drive/folders/1fjql2fMUsHiBMi1aVeM4pZcYt0NRT0OL
A40: OFR-040 | B40: MTC-044 | C40: Inductive Reasoning with Geoboards | D40: 43636 | E40: 43637 | F40: 2019-06-20 to 2019-06-21 (institute window) | G40: Institute window | H40: Summer Institute | I40: 2019 Summer Institute | K40: Yes | L40: Individual session day is not established. | M40: https://docs.google.com/presentation/d/1TMow9UBVdxIhyPxYmk4QKFf2aPfA39kd45XcXvdJ71w/edit?usp=drivesdk | N40: https://drive.google.com/file/d/18IAEnpI3zxkzzDaN-RwC1Odal0ARUM-i/view?usp=drivesdk | O40: https://drive.google.com/drive/folders/1rCzj4dRC4_nPVNUpFQC8srEsaJOrEUFN
A41: OFR-041 | B41: MTC-115 | C41: The Josephus Problem | D41: 43636 | E41: 43637 | F41: 2019-06-20 to 2019-06-21 (institute window) | G41: Institute window | H41: Summer Institute | I41: 2019 Summer Institute | K41: Yes | L41: Individual session day is not established. | M41: https://docs.google.com/presentation/d/1kYmasiSFiBZJEIJbKX32WN3SQg_o9oxJ/edit?usp=drivesdk&ouid=109901495158487957834&rtpof=true&sd=true | N41: https://drive.google.com/file/d/18IAEnpI3zxkzzDaN-RwC1Odal0ARUM-i/view?usp=drivesdk | O41: https://drive.google.com/drive/folders/1ptFLSF9Fq1c5uVTikawl8OslpUu3nYAX
A42: OFR-042 | B42: MTC-013 | C42: Bulgarian Solitaire | D42: 43711 | E42: 43711 | F42: 2019-09-03 | G42: Exact date | H42: MTC academic-year session | I42: 2019-2020 Academic Year/September Bulgarian Solitaire | K42: No | M42: https://drive.google.com/file/d/1gfAyb62Hqiwmjzht8VDSoYEYMegTx87L/view?usp=drivesdk | O42: https://drive.google.com/drive/folders/11SA0qc1_8-DXGqh_XV_yRZnR-bkzOPXu
A43: OFR-043 | B43: MTC-095 | C43: Risk in the Stock Market | D43: 43739 | E43: 43739 | F43: 2019-10-01 | G43: Exact date | H43: MTC academic-year session | I43: 2019-2020 Academic Year/October Stock Market Risk | K43: No | M43: https://drive.google.com/file/d/1g_FJ_SokTuc1cmcJJya9SSHliXcz8aj_/view?usp=drivesdk | O43: https://drive.google.com/drive/folders/1C8zlEji75_NnIvC-ezPPXLj5nzOB8G7Q
A44: OFR-044 | B44: MTC-077 | C44: Multiplication Madness | D44: 43774 | E44: 43774 | F44: 2019-11-05 | G44: Exact date | H44: MTC academic-year session | I44: 2019-2020 Academic Year/November Multiplication Madness | K44: No | M44: https://drive.google.com/file/d/1nTZAzrX50ic8-p_UeQd6j7uylgKOVBum/view?usp=drivesdk | O44: https://drive.google.com/drive/folders/1cMnUxgRQXWjD1UgjsQfvtw0kcOtXPWZ4
A45: OFR-045 | B45: MTC-040 | C45: Harmonic Numbers | D45: 43802 | E45: 43802 | F45: 2019-12-03 | G45: Exact date | H45: MTC academic-year session | I45: 2019-2020 Academic Year/December Harmonic Numbers | K45: No | M45: https://drive.google.com/file/d/14NMNxZXO05cJLv0l_H-OyJCi0VUlGaVL/view?usp=drivesdk | N45: https://drive.google.com/file/d/1PCT0LoEmg8BJLx7jhtRYK8f3Ixt-LqXC/view?usp=drivesdk | O45: https://drive.google.com/drive/folders/1QngmjBRVRDmBrUxQpDi4INur_f1rfZUq
A46: OFR-046 | B46: MTC-028 | C46: Euler and Hamilton: Two Travelers | D46: 43865 | E46: 43865 | F46: 2020-02-04 (review) | G46: Date conflict | H46: MTC academic-year session | I46: 2019-2020 Academic Year/February Graph Theory | K46: Yes | L46: Flyer says 2019-02-04; academic-year folder places the session in 2020. Date shown follows folder context; confirm before publication. | M46: https://drive.google.com/file/d/1NUoohDIE7En8mNXJFO17YY8SFLMBh-Aw/view?usp=drivesdk | O46: https://drive.google.com/drive/folders/14m4-qQdf7br8-tagTwB4Q7nAJD-OTZnQ
A47: OFR-047 | B47: MTC-078 | C47: Nearest Neighbor: Voronoi Diagrams | D47: 43893 | E47: 43893 | F47: 2020-03-03 | G47: Exact date | H47: MTC academic-year session | I47: 2019-2020 Academic Year/March Voronoi Diagrams | K47: No | M47: https://drive.google.com/file/d/1iYATNDZoGU69G_AkxC5O9cU4eo59Uq59/view?usp=drivesdk | O47: https://drive.google.com/drive/folders/1GYFrk5PJ894tCvq0mcp9561W-UjxSmZK
A48: OFR-049 | B48: MTC-085 | C48: Partition Like Piet: Mondrian Puzzles | D48: 43956 | E48: 43956 | F48: 2020-05-05 | G48: Exact date | H48: MTC academic-year session | I48: 2019-2020 Academic Year/May Mondrian Puzzles | K48: No | M48: https://drive.google.com/file/d/1wUSXfacX_VeWYYM4Bg6VGQJT1F6qzVz8/view?usp=drivesdk | O48: https://drive.google.com/drive/folders/1QEX_uFoZOctsQRNl9iMQs8y_FnbIUd36
A49: OFR-051 | B49: MTC-034 | C49: Flipping the Script: Reclaiming Mathematics for Our Students and Ourselves | D49: 44004 | E49: 44004 | F49: 2020-06-22 | G49: Exact date | H49: Summer Institute | I49: 2020 Summer Institute | J49: Cristina Runnalls | K49: Yes | L49: Session slides could not be read (access denied); description is limited to the agenda and linked activity context. | M49: https://docs.google.com/document/d/1MU72dj7yVBt8j7hlae9ghGnPc6Dz3vmIQFpOM_nm71k/edit?usp=drivesdk | O49: https://drive.google.com/drive/folders/1TR-rQ5baZ9czW3kQE8Y527uOZJ4PG-0s
A50: OFR-052 | B50: MTC-070 | C50: Mathematics Education Through the Lens of Social Justice | D50: 44005 | E50: 44005 | F50: 2020-06-23 | G50: Exact date | H50: Summer Institute | I50: 2020 Summer Institute | K50: No | L50: Agenda identifies pre-reading and reading discussion. | M50: https://docs.google.com/document/d/1MU72dj7yVBt8j7hlae9ghGnPc6Dz3vmIQFpOM_nm71k/edit?usp=drivesdk | O50: https://drive.google.com/drive/folders/1TR-rQ5baZ9czW3kQE8Y527uOZJ4PG-0s
A51: OFR-053 | B51: MTC-117 | C51: The Mathematics of Redistricting | D51: 44005 | E51: 44005 | F51: 2020-06-23 | G51: Exact date | H51: Summer Institute | I51: 2020 Summer Institute | J51: Matt Jones | K51: No | M51: https://docs.google.com/document/d/1MU72dj7yVBt8j7hlae9ghGnPc6Dz3vmIQFpOM_nm71k/edit?usp=drivesdk | O51: https://drive.google.com/drive/folders/1TR-rQ5baZ9czW3kQE8Y527uOZJ4PG-0s
A52: OFR-054 | B52: MTC-112 | C52: Teaching Is Political | D52: 44006 | E52: 44006 | F52: 2020-06-24 | G52: Exact date | H52: Summer Institute | I52: 2020 Summer Institute | J52: Brian Katz | K52: No | M52: https://docs.google.com/presentation/d/1rrA3JELjC-clcpPbOSfsYPCgCf33Jb3UhkPCU5M5r98/edit?usp=drivesdk | N52: https://docs.google.com/document/d/1MU72dj7yVBt8j7hlae9ghGnPc6Dz3vmIQFpOM_nm71k/edit?usp=drivesdk | O52: https://drive.google.com/drive/folders/1rxaKVcdkN3XGGMls0DtS7bHiYPB1Psek
A53: OFR-055 | B53: MTC-033 | C53: Fair Voting and Group-Ranking Methods | D53: 44007 | E53: 44007 | F53: 2020-06-25 | G53: Exact date | H53: Summer Institute | I53: 2020 Summer Institute | J53: Carolyn Yarnall | K53: No | M53: https://docs.google.com/presentation/d/16hOUbRO7_xJVUHgbLJz_zCbZ20M9xh9k/edit?usp=drivesdk&ouid=109901495158487957834&rtpof=true&sd=true | N53: https://docs.google.com/document/d/1MU72dj7yVBt8j7hlae9ghGnPc6Dz3vmIQFpOM_nm71k/edit?usp=drivesdk | O53: https://drive.google.com/drive/folders/18jJY1WsPIv8pmmwysbw2lKMdx4Olf16e
A54: OFR-056 | B54: MTC-021 | C54: Desmos: More than Graphing Curves | D54: 44008 | E54: 44008 | F54: 2020-06-26 | G54: Exact date | H54: Summer Institute | I54: 2020 Summer Institute | J54: Sarah DeMartino | K54: No | L54: Includes the Graphs, Equations, and Situations card-sort warmup. | M54: https://drive.google.com/file/d/1Sh_xE5MoDkGr3KBG0lJk_wxq0kbGjDNI/view?usp=drivesdk | N54: https://docs.google.com/document/d/1MU72dj7yVBt8j7hlae9ghGnPc6Dz3vmIQFpOM_nm71k/edit?usp=drivesdk | O54: https://drive.google.com/drive/folders/1M9dECAjNKbC9FGv_ypUoRPws0u6-LvNK
A55: OFR-057 | B55: MTC-072 | C55: Mathematics and Social Justice: Examining Stop and Frisk | D55: 44075 | E55: 44075 | F55: 2020-09-01 | G55: Exact date | H55: MTC academic-year session | I55: 2020-2021 Academic Year/September Stop and Frisk | K55: No | M55: https://drive.google.com/file/d/1FFLwOX1vcCpoJlVxhFeNMYQNg7-0nvL8/view?usp=drivesdk | O55: https://drive.google.com/drive/folders/1BgJfrLsCwVUImbaAqDDV_jJK8b4tjbZa
A56: OFR-058 | B56: MTC-124 | C56: Tools for Promoting Racial and Gender Equity in Mathematics Classrooms | D56: 44110 | E56: 44110 | F56: 2020-10-06 | G56: Exact date | H56: MTC academic-year session | I56: 2020-2021 Academic Year/October Promoting Classroom Equity | K56: No | M56: https://drive.google.com/file/d/1lTh4izb_yRBkeN_hBBBhulPhrgwC7s6o/view?usp=drivesdk | O56: https://drive.google.com/drive/folders/1N15-P0BkZ_2tSFV8RzmxN2ufOkgk0tlG
A57: OFR-059 | B57: MTC-019 | C57: Cryptography: Secure Data Transmission | D57: 44138 | E57: 44138 | F57: 2020-11-03 | G57: Exact date | H57: MTC academic-year session | I57: 2020-2021 Academic Year/November Cryptography | K57: No | M57: https://drive.google.com/file/d/1i6SpS6W-YZiPy7V_ZJSeutnvYwNI1D-H/view?usp=drivesdk | O57: https://drive.google.com/drive/folders/1yvy4uEkXQwZCq_GOJuB7fUcqEzkz9oh8
A58: OFR-062 | B58: MTC-083 | C58: Operating on Numbers | D58: 44257 | E58: 44257 | F58: 2021-03-02 | G58: Exact date | H58: MTC academic-year session | I58: 2020-2021 Academic Year/March Operating on Numbers | K58: No | M58: https://drive.google.com/file/d/1Ztapvj-KkNmR0ws9aV3V3qc2xwvPFqKc/view?usp=drivesdk | O58: https://drive.google.com/drive/folders/1CVZF71C2s9mxmRG6_lKsCqljz3GnKqyy
A59: OFR-063 | B59: MTC-107 | C59: Square Wars | D59: 44320 | E59: 44320 | F59: 2021-05-04 | G59: Exact date | H59: MTC academic-year session | I59: 2020-2021 Academic Year/May Square Wars | K59: No | M59: https://drive.google.com/file/d/1OM5t3A7GmkHSkuIrkyNMJqD2PHyuLncP/view?usp=drivesdk | O59: https://drive.google.com/drive/folders/1TXHhyQCyYqch7_I2snKLUFAvnDfex8D6
A60: OFR-064 | B60: MTC-001 | C60: 3-Act Math Tasks | D60: 44364 | E60: 44364 | F60: 2021-06-17 | G60: Exact date | H60: Summer Institute | I60: 2021 Summer Institute | J60: Sarah DeMartino | K60: No | M60: https://docs.google.com/presentation/d/1n_7f4sxYuztvXVN8gZ-NnK-xv4gQRV5r_x4P9LyLR2A/edit?usp=drivesdk | N60: https://docs.google.com/document/d/1XgBPtwa7dVUiBdYAa1nvv7DqLhWe7ho8BS23HndmozU/edit?usp=drivesdk | O60: https://drive.google.com/drive/folders/1e2q-g-xXdeIYu1vMIBuR4E2F1yCZiMxQ
A61: OFR-066 | B61: MTC-060 | C61: Make Your Own 3-Act Math Task | D61: 44364 | E61: 44364 | F61: 2021-06-17 | G61: Exact date | H61: Summer Institute | I61: 2021 Summer Institute | J61: Sharon Lanaghan | K61: No | M61: https://docs.google.com/document/d/1XgBPtwa7dVUiBdYAa1nvv7DqLhWe7ho8BS23HndmozU/edit?usp=drivesdk | O61: https://drive.google.com/drive/folders/1jMaUXv_moFqp4vPk7rMqgcL-NFSsSY0E
A62: OFR-067 | B62: MTC-121 | C62: Thinking Through a Lesson: High-Level Tasks | D62: 44364 | E62: 44364 | F62: 2021-06-17 | G62: Exact date | H62: Summer Institute | I62: 2021 Summer Institute | K62: No | L62: Agenda identifies the reading discussion. | M62: https://docs.google.com/document/d/1XgBPtwa7dVUiBdYAa1nvv7DqLhWe7ho8BS23HndmozU/edit?usp=drivesdk | O62: https://drive.google.com/drive/folders/1jMaUXv_moFqp4vPk7rMqgcL-NFSsSY0E
A63: OFR-068 | B63: MTC-133 | C63: What Is Mathematical Modeling? | D63: 44364 | E63: 44364 | F63: 2021-06-17 | G63: Exact date | H63: Summer Institute | I63: 2021 Summer Institute | J63: Matt Jones | K63: No | L63: Description based on agenda and linked activity title. | M63: https://docs.google.com/document/d/1XgBPtwa7dVUiBdYAa1nvv7DqLhWe7ho8BS23HndmozU/edit?usp=drivesdk | O63: https://drive.google.com/drive/folders/1jMaUXv_moFqp4vPk7rMqgcL-NFSsSY0E
A64: OFR-069 | B64: MTC-007 | C64: Assessing Mathematical Modeling | D64: 44365 | E64: 44365 | F64: 2021-06-18 | G64: Exact date | H64: Summer Institute | I64: 2021 Summer Institute | K64: No | M64: https://docs.google.com/document/d/1XgBPtwa7dVUiBdYAa1nvv7DqLhWe7ho8BS23HndmozU/edit?usp=drivesdk | O64: https://drive.google.com/drive/folders/1jMaUXv_moFqp4vPk7rMqgcL-NFSsSY0E
A65: OFR-070 | B65: MTC-105 | C65: Spread of Disease | D65: 44365 | E65: 44365 | F65: 2021-06-18 | G65: Exact date | H65: Summer Institute | I65: 2021 Summer Institute | J65: Matt Jones | K65: No | L65: Description based on the agenda’s named activity and linked modeling tools. | M65: https://docs.google.com/document/d/1XgBPtwa7dVUiBdYAa1nvv7DqLhWe7ho8BS23HndmozU/edit?usp=drivesdk | O65: https://drive.google.com/drive/folders/1jMaUXv_moFqp4vPk7rMqgcL-NFSsSY0E
A66: OFR-071 | B66: MTC-053 | C66: Learning Mathematics and Social Justice | D66: 44366 | E66: 44366 | F66: 2021-06-19 | G66: Exact date | H66: Summer Institute | I66: 2021 Summer Institute | J66: Matt Jones | K66: No | M66: https://docs.google.com/document/d/1XgBPtwa7dVUiBdYAa1nvv7DqLhWe7ho8BS23HndmozU/edit?usp=drivesdk | O66: https://drive.google.com/drive/folders/1jMaUXv_moFqp4vPk7rMqgcL-NFSsSY0E
A67: OFR-072 | B67: MTC-056 | C67: Linear Programming: Cookies and Inequalities | D67: 44366 | E67: 44366 | F67: 2021-06-19 | G67: Exact date | H67: Summer Institute | I67: 2021 Summer Institute | J67: Kristen Stagg | K67: No | L67: Description based on the agenda and named scenario materials. | M67: https://docs.google.com/document/d/1XgBPtwa7dVUiBdYAa1nvv7DqLhWe7ho8BS23HndmozU/edit?usp=drivesdk | O67: https://drive.google.com/drive/folders/1jMaUXv_moFqp4vPk7rMqgcL-NFSsSY0E
A68: OFR-073 | B68: MTC-075 | C68: Monte Carlo Simulations | D68: 44368 | E68: 44368 | F68: 2021-06-21 | G68: Exact date | H68: Summer Institute | I68: 2021 Summer Institute | J68: Carolyn Yarnall | K68: No | M68: https://docs.google.com/presentation/d/19cXuJB9iIDB86Fdlc5V7KbOxKqFGx-ij/edit?usp=drivesdk&ouid=109901495158487957834&rtpof=true&sd=true | N68: https://docs.google.com/document/d/1XgBPtwa7dVUiBdYAa1nvv7DqLhWe7ho8BS23HndmozU/edit?usp=drivesdk | O68: https://drive.google.com/drive/folders/1E7fYcRB-72i5hOTtaIDTIY5i8Ft41yv2
A69: OFR-074 | B69: MTC-081 | C69: Number Puzzles | D69: 44446 | E69: 44446 | F69: 2021-09-07 (review) | G69: Date conflict | H69: MTC academic-year session | I69: 2021-2022 Academic Year/September Number Puzzles | K69: Yes | L69: Flyer says 2022-09-07; academic-year folder places the session in 2021. Date shown follows folder context; confirm before publication. | M69: https://drive.google.com/file/d/1PMbt8CmnyXGG7W2A1aHCjmgh75UCVKt1/view?usp=drivesdk | O69: https://drive.google.com/drive/folders/1jz8btew6_1UD1nmxQPoX7_UuGH_9SrVg
A70: OFR-075 | B70: MTC-130 | C70: What Color Is My Hat? | D70: 44474 | E70: 44474 | F70: 2021-10-05 | G70: Exact date | H70: MTC academic-year session | I70: 2021-2022 Academic Year/October What Color is my Hat? | K70: No | M70: https://drive.google.com/file/d/10Qcd0YwWRqS93rKQnriOw9PhewDlv4V2/view?usp=drivesdk | O70: https://drive.google.com/drive/folders/1zDnJdjaZzIZKUXCBjU5Jso6HKNaQRtC8
A71: OFR-076 | B71: MTC-003 | C71: Addressing Unfinished Learning | D71: 44583 | E71: 44583 | F71: 2022-01-22 | G71: Exact date | H71: PLUS Math | I71: 2021-2022 Academic Year/PLUS-Math Unfinished Learning | K71: No | M71: https://drive.google.com/file/d/1bASee8-xo4xHQZQi3HM7F3FOFzsfH4TX/view?usp=drivesdk | O71: https://drive.google.com/drive/folders/1iaJ8EXGtfXLv8gjdcBmZKyAShomA-9JP
A72: OFR-077 | B72: MTC-042 | C72: I Walk the Line(s) | D72: 44593 | E72: 44593 | F72: 2022-02-01 | G72: Exact date | H72: MTC academic-year session | I72: 2021-2022 Academic Year/February I Walk the Line(s) | K72: No | M72: https://drive.google.com/file/d/13fyIOABz9uBbRndjzz5Ooo3U22jlO9jr/view?usp=drivesdk | O72: https://drive.google.com/drive/folders/10V2guKNARlg4mRUiutmHeFEH_h7p_D7x
A73: OFR-078 | B73: MTC-012 | C73: Bubbling Cauldrons | D73: 44621 | E73: 44621 | F73: 2022-03-01 | G73: Exact date | H73: MTC academic-year session | I73: 2021-2022 Academic Year/March Bubbling Cauldrons | K73: No | M73: https://drive.google.com/file/d/14bi8fihcIm4Args2WhVR4CV7iAsAnimL/view?usp=drivesdk | N73: https://docs.google.com/presentation/d/1v-idVEF2UhAxrQqAegkHJ3LTitKK9sT_/edit?usp=drivesdk&ouid=109901495158487957834&rtpof=true&sd=true | O73: https://drive.google.com/drive/folders/1S5El3eNXpjIllIZfOLvcKPqZt-7IHb44
A74: OFR-081 | B74: MTC-038 | C74: Graph Talks | D74: 44733 | E74: 44733 | F74: 2022-06-21 | G74: Exact date | H74: Summer Institute | I74: 2022 Summer Institute | K74: No | L74: Offered as an article discussion on graph talks and social justice. | M74: https://docs.google.com/presentation/d/1TQ--3SL3S2D03ZGUqqZ7g1oV0plPyN3RM_1DWxLmG8Y/edit?usp=drivesdk | N74: https://docs.google.com/document/d/1eRd5aZl7I91mn_7VhOIpsYI23-MfBOBtVABSROttK8c/edit?usp=drivesdk | O74: https://drive.google.com/drive/folders/12KdwrIwdgiabfHJPsYNGx-iNT777x6Yq
A75: OFR-082 | B75: MTC-064 | C75: Math and Environmental Justice | D75: 44733 | E75: 44733 | F75: 2022-06-21 | G75: Exact date | H75: Summer Institute | I75: 2022 Summer Institute | J75: Carolyn Yarnall | K75: No | M75: https://docs.google.com/presentation/d/1RTj1fMGz0wEOL9Ve-0AWctdb8txMNY_S/edit?usp=drivesdk&ouid=109901495158487957834&rtpof=true&sd=true | N75: https://docs.google.com/document/d/1eRd5aZl7I91mn_7VhOIpsYI23-MfBOBtVABSROttK8c/edit?usp=drivesdk | O75: https://drive.google.com/drive/folders/12KdwrIwdgiabfHJPsYNGx-iNT777x6Yq
A76: OFR-083 | B76: MTC-065 | C76: Math and Photography: Classroom Applications | D76: 44734 | E76: 44734 | F76: 2022-06-22 | G76: Exact date | H76: Summer Institute | I76: 2022 Summer Institute | K76: No | M76: https://docs.google.com/presentation/d/1tJ6ON4M2cMa8SB_FiNd8-PawVANjjAaUuDpJ8OUMimQ/edit?usp=drivesdk | N76: https://docs.google.com/document/d/1eRd5aZl7I91mn_7VhOIpsYI23-MfBOBtVABSROttK8c/edit?usp=drivesdk | O76: https://drive.google.com/drive/folders/1S4RXsHe-nlbaLXgBSSgAnb8zt7jYvF1e
A77: OFR-084 | B77: MTC-097 | C77: Seeing Math in Photos | D77: 44734 | E77: 44734 | F77: 2022-06-22 | G77: Exact date | H77: Summer Institute | I77: 2022 Summer Institute | K77: No | M77: https://docs.google.com/presentation/d/1VIKwg8XbFC1-lEdcFHW1O03cXamwbINDBOi2FuJ3CLA/edit?usp=drivesdk | N77: https://docs.google.com/document/d/1eRd5aZl7I91mn_7VhOIpsYI23-MfBOBtVABSROttK8c/edit?usp=drivesdk | O77: https://drive.google.com/drive/folders/1S4RXsHe-nlbaLXgBSSgAnb8zt7jYvF1e
A78: OFR-085 | B78: MTC-046 | C78: Introduction to Fractals | D78: 44735 | E78: 44735 | F78: 2022-06-23 (review) | G78: Date conflict | H78: Summer Institute | I78: 2022 Summer Institute | K78: Yes | L78: Slides and folder identify June 23; agenda says Thursday June 25, which does not match the 2022 calendar. | M78: https://docs.google.com/presentation/d/1bDNjxI9WN_Ivms1TvOklkV9Poh1zcHzR/edit?usp=drivesdk&ouid=109901495158487957834&rtpof=true&sd=true | O78: https://drive.google.com/drive/folders/16M3IuXYUFOAt1KMkN3Cm6F4lnMv7WKSX
A79: OFR-086 | B79: MTC-068 | C79: Mathematical Interactions for English Learners | D79: 44735 | E79: 44735 | F79: 2022-06-23 (review) | G79: Date conflict | H79: Summer Institute | I79: 2022 Summer Institute | K79: Yes | L79: Folder identifies June 23; agenda says Thursday June 25. Includes the describe-and-draw vocabulary activity. | M79: https://docs.google.com/presentation/d/1O2bEMT3iJ5PP8TmY8gR_Ja4-J-lzoZOwtzg_qizB_to/edit?usp=drivesdk | N79: https://docs.google.com/document/d/1eRd5aZl7I91mn_7VhOIpsYI23-MfBOBtVABSROttK8c/edit?usp=drivesdk | O79: https://drive.google.com/drive/folders/16M3IuXYUFOAt1KMkN3Cm6F4lnMv7WKSX
A80: OFR-087 | B80: MTC-066 | C80: Math in Toys and Games | D80: 44736 | E80: 44736 | F80: 2022-06-24 (review) | G80: Date conflict | H80: Summer Institute | I80: 2022 Summer Institute | K80: Yes | L80: Folder identifies June 24; agenda says Friday June 26, which does not match the 2022 calendar. Article discussion is included in the session deck. | M80: https://docs.google.com/presentation/d/1RWRtteAz3hCalu4sddo6U3kiJ-GO7XaN/edit?usp=drivesdk&ouid=109901495158487957834&rtpof=true&sd=true | N80: https://docs.google.com/document/d/1eRd5aZl7I91mn_7VhOIpsYI23-MfBOBtVABSROttK8c/edit?usp=drivesdk | O80: https://drive.google.com/drive/folders/1eGpbdA4Hp8lOeRdRuohJia-TGwjesrAN
A81: OFR-088 | B81: MTC-125 | C81: Tricolor Triangles | D81: 44810 | E81: 44810 | F81: 2022-09-06 | G81: Exact date | H81: MTC academic-year session | I81: 2022-2023 Academic Year/September Tri Color Triangle Puzzles | K81: No | M81: https://drive.google.com/file/d/1kw4bOlcnl5dq1kDX6XB0d2pWt1IRJv1O/view?usp=drivesdk | O81: https://drive.google.com/drive/folders/1dKCB8us6_ALzaR7bIrpQmTeIWTPqMJQG
A82: OFR-090 | B82: MTC-076 | C82: More Sprinkles | D82: 44866 | E82: 44866 | F82: 2022-11-01 | G82: Exact date | H82: MTC academic-year session | I82: 2022-2023 Academic Year/November More Sprinkles | K82: No | M82: https://drive.google.com/file/d/12tNUhCtvt8zln3LLOfIrqhu9fWiW-jgm/view?usp=drivesdk | O82: https://drive.google.com/drive/folders/17bNwEyyRjVcV1QoiEpohKhoXhgPMyynq
A83: OFR-091 | B83: MTC-074 | C83: Measuring Up: A Perfect Ruler | D83: 44964 | E83: 44964 | F83: 2023-02-07 | G83: Exact date | H83: MTC academic-year session | I83: 2022-2023 Academic Year/February A Perfect Ruler | K83: No | M83: https://drive.google.com/file/d/1G4zatwIw7aUlvSjwHvFqFcfNrTb5m_FU/view?usp=drivesdk | O83: https://drive.google.com/drive/folders/1mm9TLbXkEuHd67SSyDodgZgcaxF1JPF0
A84: OFR-092 | B84: MTC-101 | C84: Skyscrapers, Flowers and JRMF | D84: 44992 | E84: 44992 | F84: 2023-03-07 | G84: Exact date | H84: MTC academic-year session | I84: 2022-2023 Academic Year/March Skyscrapers, Flowers & JRMF | J84: Daniel Klein | K84: No | M84: https://drive.google.com/file/d/1l0rFahE46JC40HQmew09pmSGnKaD6Aqw/view?usp=drivesdk | O84: https://drive.google.com/drive/folders/1lkUmGq_Y7NtSZasPCqeDj-XrmE5_Bhr-
A85: OFR-093 | B85: MTC-111 | C85: Taxicab Geometry | D85: 45020 | E85: 45020 | F85: 2023-04-04 | G85: Exact date | H85: MTC academic-year session | I85: 2022-2023 Academic Year/April Taxicab Geometry | K85: No | M85: https://drive.google.com/file/d/1YEk67GB6F_d-cZnrJ48KQ0FETBdBtvR3/view?usp=drivesdk | O85: https://drive.google.com/drive/folders/1H3M33xsAEGa-Jm68SfX0wWgu_4eSTsqS
A86: OFR-094 | B86: MTC-080 | C86: Number Bracelets | D86: 45048 | E86: 45048 | F86: 2023-05-02 | G86: Exact date | H86: MTC academic-year session | I86: 2022-2023 Academic Year/May Number Bracelets | K86: No | M86: https://drive.google.com/file/d/1q1t0wTzFzhN1uokGX16E4pLExzL1M_H8/view?usp=drivesdk | O86: https://drive.google.com/drive/folders/1TBPAE_rso5xGRij7i3rFXQ8N4uywc2En
A87: OFR-095 | B87: MTC-009 | C87: Blind Stork: Collecting and Modeling Data | D87: 45097 | E87: 45097 | F87: 2023-06-20 | G87: Exact date | H87: Summer Institute | I87: 2023 Summer Institute | K87: No | M87: https://docs.google.com/presentation/d/1eBBhuPUH1Sk8yqbKnEZNtrYFpvk6s9e8/edit?usp=drivesdk&ouid=109901495158487957834&rtpof=true&sd=true | N87: https://docs.google.com/document/d/1oR0vP-6O-VQkMk_0MaUTya16f-a8jxPO/edit?usp=drivesdk&ouid=109901495158487957834&rtpof=true&sd=true | O87: https://drive.google.com/drive/folders/1NVpERNtguPK1wdF3QHYUFpueMv7iabZH
A88: OFR-097 | B88: MTC-038 | C88: Graph Talks | D88: 45097 | E88: 45097 | F88: 2023-06-20 | G88: Exact date | H88: Summer Institute | I88: 2023 Summer Institute | K88: No | M88: https://docs.google.com/presentation/d/1T1zOtCkQU_-Zb9bVvNtdICIVOv_v73ZS/edit?usp=drivesdk&ouid=109901495158487957834&rtpof=true&sd=true | N88: https://docs.google.com/document/d/1oR0vP-6O-VQkMk_0MaUTya16f-a8jxPO/edit?usp=drivesdk&ouid=109901495158487957834&rtpof=true&sd=true | O88: https://drive.google.com/drive/folders/1hDwdu80o8G_uXserSpBBqKXl4dJBQL1_
A89: OFR-098 | B89: MTC-132 | C89: What Is Data Science? | D89: 45097 | E89: 45097 | F89: 2023-06-20 | G89: Exact date | H89: Summer Institute | I89: 2023 Summer Institute | K89: No | M89: https://docs.google.com/presentation/d/1muGYzH6W6n52ehCFL1mlQC1ZLHZLaUQs/edit?usp=drivesdk&ouid=109901495158487957834&rtpof=true&sd=true | N89: https://docs.google.com/document/d/1oR0vP-6O-VQkMk_0MaUTya16f-a8jxPO/edit?usp=drivesdk&ouid=109901495158487957834&rtpof=true&sd=true | O89: https://drive.google.com/drive/folders/1t4B7HYNGHtPispn-fAHaUGF_QX4JGvY8
A90: OFR-099 | B90: MTC-017 | C90: Create Your Own Graph Talk | D90: 45098 | E90: 45098 | F90: 2023-06-21 | G90: Exact date | H90: Summer Institute | I90: 2023 Summer Institute | K90: No | M90: https://docs.google.com/presentation/d/1LWIWmJ3EBrNjSHOYKbrKgh5hV4SagZqu/edit?usp=drivesdk&ouid=109901495158487957834&rtpof=true&sd=true | N90: https://docs.google.com/document/d/1oR0vP-6O-VQkMk_0MaUTya16f-a8jxPO/edit?usp=drivesdk&ouid=109901495158487957834&rtpof=true&sd=true | O90: https://drive.google.com/drive/folders/1PT_C7BaoICdlpDmqhk9gb7LKcbGW-VWR
A91: OFR-100 | B91: MTC-038 | C91: Graph Talks | D91: 45098 | E91: 45098 | F91: 2023-06-21 | G91: Exact date | H91: Summer Institute | I91: 2023 Summer Institute | K91: No | L91: A second graph-talk block appears in the June 21 agenda. | M91: https://docs.google.com/presentation/d/1T1zOtCkQU_-Zb9bVvNtdICIVOv_v73ZS/edit?usp=drivesdk&ouid=109901495158487957834&rtpof=true&sd=true | N91: https://docs.google.com/document/d/1oR0vP-6O-VQkMk_0MaUTya16f-a8jxPO/edit?usp=drivesdk&ouid=109901495158487957834&rtpof=true&sd=true | O91: https://drive.google.com/drive/folders/1hDwdu80o8G_uXserSpBBqKXl4dJBQL1_
A92: OFR-101 | B92: MTC-127 | C92: Using CODAP to Investigate Sociopolitical Issues | D92: 45098 | E92: 45098 | F92: 2023-06-21 | G92: Exact date | H92: Summer Institute | I92: 2023 Summer Institute | J92: Ha Nguyen | K92: No | M92: https://docs.google.com/presentation/d/1VZt32dBGKlyiO9MwLofMlL4oLAqXVX-w/edit?usp=drivesdk&ouid=109901495158487957834&rtpof=true&sd=true | O92: https://drive.google.com/drive/folders/1PT_C7BaoICdlpDmqhk9gb7LKcbGW-VWR
A93: OFR-102 | B93: MTC-011 | C93: Bringing Data into Classrooms | D93: 45099 | E93: 45099 | F93: 2023-06-22 | G93: Exact date | H93: Summer Institute | I93: 2023 Summer Institute | J93: Matt Jones | K93: No | M93: https://docs.google.com/presentation/d/1K2tmaLErEVOhhciOyIDLkyqm0f5y_t4qHGoiHP-xoK8/edit?usp=drivesdk | N93: https://docs.google.com/document/d/1oR0vP-6O-VQkMk_0MaUTya16f-a8jxPO/edit?usp=drivesdk&ouid=109901495158487957834&rtpof=true&sd=true | O93: https://drive.google.com/drive/folders/1fbqt59z4P4_XYyOWhZAfhpE3u8oeSetz
A94: OFR-103 | B94: MTC-030 | C94: Exploring Traffic Stop Data | D94: 45099 | E94: 45099 | F94: 2023-06-22 | G94: Exact date | H94: Summer Institute | I94: 2023 Summer Institute | K94: No | M94: https://docs.google.com/presentation/d/1l0tgXLu1QdG2sz09KWIyXSdB9CKesD0v/edit?usp=drivesdk&ouid=109901495158487957834&rtpof=true&sd=true | N94: https://docs.google.com/document/d/1oR0vP-6O-VQkMk_0MaUTya16f-a8jxPO/edit?usp=drivesdk&ouid=109901495158487957834&rtpof=true&sd=true | O94: https://drive.google.com/drive/folders/1cfYEH3N18lQ0KgAeKUe3Yn0eQ2_KTM96
A95: OFR-104 | B95: MTC-120 | C95: The Titanic Shuffle | D95: 45100 | E95: 45100 | F95: 2023-06-23 | G95: Exact date | H95: Summer Institute | I95: 2023 Summer Institute | K95: No | M95: https://docs.google.com/presentation/d/1cZm86vqV1-YLVHo9RXZidF_bNR5OCHwV/edit?usp=drivesdk&ouid=109901495158487957834&rtpof=true&sd=true | N95: https://docs.google.com/document/d/1oR0vP-6O-VQkMk_0MaUTya16f-a8jxPO/edit?usp=drivesdk&ouid=109901495158487957834&rtpof=true&sd=true | O95: https://drive.google.com/drive/folders/1sAEt_Ov9eG578yHRMC_9r7kQAf9XlQdK
A96: OFR-105 | B96: MTC-134 | C96: What Is Random? | D96: 45174 | E96: 45174 | F96: 2023-09-05 | G96: Exact date | H96: MTC academic-year session | I96: 2023-2024 Academic Year/September Randomness | K96: No | M96: https://drive.google.com/file/d/1AFsfzbR9m_EWunQWAloe3-YTbVq7sebj/view?usp=drivesdk | O96: https://drive.google.com/drive/folders/1c7tz0PF-8WuiWeWRxdUkL1bJMWOiBlH_
A97: OFR-106 | B97: MTC-069 | C97: Mathematical Magic for Muggles | D97: 45202 | E97: 45202 | F97: 2023-10-03 | G97: Exact date | H97: MTC academic-year session | I97: 2023-2024 Academic Year/October - Math Magic | J97: Paul Zeitz | K97: No | M97: https://drive.google.com/file/d/1SC9cPIcEpCmbNPY2J1-ZyJ_wd-qsPtth/view?usp=drivesdk | O97: https://drive.google.com/drive/folders/17EyNurQXIQaadG6i9wXQsbpBWw_Ok9h8
A98: OFR-107 | B98: MTC-084 | C98: Pancake Sorting and Recursion | D98: 45237 | E98: 45237 | F98: 2023-11-07 | G98: Exact date | H98: MTC academic-year session | I98: 2023-2024 Academic Year/November - Pancake Flipping | K98: No | M98: https://drive.google.com/file/d/1vndeRMVvzkTjPX-nDoOGaCkcv4leGQcI/view?usp=drivesdk | O98: https://drive.google.com/drive/folders/1WTzMMoPReWPNCbL9NzWXSzbglOr2ulUi
A99: OFR-108 | B99: MTC-048 | C99: Is Santa Secretly Deranged? | D99: 45265 | E99: 45265 | F99: 2023-12-05 | G99: Exact date | H99: MTC academic-year session | I99: 2023-2024 Academic Year/December - Secret Santa | K99: No | M99: https://drive.google.com/file/d/1aFBtamtxp4JPdsOH_Yf003sqXUDzRTHT/view?usp=drivesdk | O99: https://drive.google.com/drive/folders/13-deZNzxTBUcDkHUwrj9rI4oee5VNdQn
A100: OFR-109 | B100: MTC-002 | C100: 4-Game Night | D100: 45328 | E100: 45328 | F100: 2024-02-06 | G100: Exact date | H100: MTC academic-year session | I100: 2023-2024 Academic Year/February - 4 Games | K100: No | M100: https://drive.google.com/file/d/1zL70vEoZ6Aae0qdb6JW5lnACC4mTBQaa/view?usp=drivesdk | O100: https://drive.google.com/drive/folders/1gUdo__wtMXb0xibi5HdtlAkjX3OzRTI1
A101: OFR-110 | B101: MTC-090 | C101: Rational Tangle Dance | D101: 45356 | E101: 45356 | F101: 2024-03-05 | G101: Exact date | H101: MTC academic-year session | I101: 2023-2024 Academic Year/March - Rational Tangle Dance | K101: No | M101: https://drive.google.com/file/d/1B7Q5yK1f3xX3sHWaqFA1_Bduwr6mzuEF/view?usp=drivesdk | O101: https://drive.google.com/drive/folders/1O2jKo-ETXHHkmhuLB0PkeiBkg4GUX2Eg
...

Sheet Resources
A1: Resource inventory
A2: 586 files . Full folder paths retained . Blank session/offering IDs indicate a resource not assigned to a specific session
A4: Resource title | B4: File type | C4: Resource role | D4: Archive path | E4: Session IDs | F4: Offering IDs | G4: Review coverage | H4: Resource URL | I4: Drive file ID
A5: MTC 10-4 Meeting Flyer.pdf | B5: PDF | C5: Agenda / announcement / institute support | D5: 2016-2017 Academic Year/10/4/16 Rational Tangles/MTC 10-4 Meeting Flyer.pdf | E5: MTC-090 | F5: OFR-002 | G5: Text reviewed | H5: https://drive.google.com/file/d/0B4cCTfJeL7_dVUtKWVJXMnA5XzQ/view?usp=drivesdk&resourcekey=0-6BQhmPR9EvS9WJPbXzkZiA | I5: 0B4cCTfJeL7_dVUtKWVJXMnA5XzQ
A6: Rational Tangle.pdf | B6: PDF | C6: Session or supporting resource | D6: 2016-2017 Academic Year/10/4/16 Rational Tangles/Rational Tangle.pdf | E6: MTC-090 | F6: OFR-002 | G6: Metadata inventoried | H6: https://drive.google.com/file/d/0B4cCTfJeL7_dZ1g5OHV2b0ppRE0/view?usp=drivesdk&resourcekey=0-gFEEHzqZZLUYISQVf2ElqQ | I6: 0B4cCTfJeL7_dZ1g5OHV2b0ppRE0
A7: Rational Tangles 10-4.pptx | B7: PowerPoint | C7: Session or supporting resource | D7: 2016-2017 Academic Year/10/4/16 Rational Tangles/Rational Tangles 10-4.pptx | E7: MTC-090 | F7: OFR-002 | G7: Metadata inventoried | H7: https://docs.google.com/presentation/d/0B4cCTfJeL7_daGlzTnJxTmJYNFE/edit?usp=drivesdk&ouid=109901495158487957834&resourcekey=0-PvNrNHCkTPRSyRcoVjP3rQ&rtpof=true&sd=true | I7: 0B4cCTfJeL7_daGlzTnJxTmJYNFE
A8: MadVet2.pptx | B8: PowerPoint | C8: Session or supporting resource | D8: 2016-2017 Academic Year/11/1/16 Mad Vet/MadVet2.pptx | E8: MTC-116 | F8: OFR-003 | G8: Metadata inventoried | H8: https://docs.google.com/presentation/d/0B4cCTfJeL7_dek16Y01ITGZZVWM/edit?usp=drivesdk&ouid=109901495158487957834&resourcekey=0-mgZwkory8HS2tN5UyBs3kg&rtpof=true&sd=true | I8: 0B4cCTfJeL7_dek16Y01ITGZZVWM
A9: MadVetProblems.pdf | B9: PDF | C9: Session or supporting resource | D9: 2016-2017 Academic Year/11/1/16 Mad Vet/MadVetProblems.pdf | E9: MTC-116 | F9: OFR-003 | G9: Metadata inventoried | H9: https://drive.google.com/file/d/0B4cCTfJeL7_dbGxYdlBhRWlITUU/view?usp=drivesdk&resourcekey=0-PLiXbNK72XjipdpkxxMFUw | I9: 0B4cCTfJeL7_dbGxYdlBhRWlITUU
A10: MTC Meeting 3 Flyer v2.pdf | B10: PDF | C10: Agenda / announcement / institute support | D10: 2016-2017 Academic Year/11/1/16 Mad Vet/MTC Meeting 3 Flyer v2.pdf | E10: MTC-116 | F10: OFR-003 | G10: Text reviewed | H10: https://drive.google.com/file/d/0B4cCTfJeL7_dcUF3dHJHWjJiMEE/view?usp=drivesdk&resourcekey=0-81akf2SWjep3EUPUzYf7mg | I10: 0B4cCTfJeL7_dcUF3dHJHWjJiMEE
A11: MTC Meeting 4 Flyer.pdf | B11: PDF | C11: Agenda / announcement / institute support | D11: 2016-2017 Academic Year/12/6/16 Game Theory/MTC Meeting 4 Flyer.pdf | E11: MTC-087 | F11: OFR-004 | G11: Text reviewed | H11: https://drive.google.com/file/d/0B4cCTfJeL7_dZ0d4eFRvY0M2WFU/view?usp=drivesdk&resourcekey=0-BU-CIxJ-KiHzrpFxXsS3uA | I11: 0B4cCTfJeL7_dZ0d4eFRvY0M2WFU
A12: Pirates-MTC-handout.docx | B12: Word | C12: Session or supporting resource | D12: 2016-2017 Academic Year/12/6/16 Game Theory/Pirates-MTC-handout.docx | E12: MTC-087 | F12: OFR-004 | G12: Metadata inventoried | H12: https://docs.google.com/document/d/0B4cCTfJeL7_dQnVVbTNaUXc1akk/edit?usp=drivesdk&ouid=109901495158487957834&resourcekey=0-Dw79X39kyi_xt6y8z3t1Mw&rtpof=true&sd=true | I12: 0B4cCTfJeL7_dQnVVbTNaUXc1akk
A13: Pirates, Prisoners, and Chicken.pdf | B13: PDF | C13: Session or supporting resource | D13: 2016-2017 Academic Year/12/6/16 Game Theory/Pirates, Prisoners, and Chicken.pdf | E13: MTC-087 | F13: OFR-004 | G13: Metadata inventoried | H13: https://drive.google.com/file/d/0B4cCTfJeL7_dcVVOZmwxX3RVdk0/view?usp=drivesdk&resourcekey=0-OMR_byjoY0v3RnYI1RRwcg | I13: 0B4cCTfJeL7_dcVVOZmwxX3RVdk0
A14: MTC Meeting 5 Flyer.pdf | B14: PDF | C14: Agenda / announcement / institute support | D14: 2016-2017 Academic Year/2/7/17 Set/MTC Meeting 5 Flyer.pdf | E14: MTC-096 | F14: OFR-005 | G14: Text reviewed | H14: https://drive.google.com/file/d/0B4cCTfJeL7_dQ2lLeDdMUDhwX28/view?usp=drivesdk&resourcekey=0-WVYtZLMYQXEHOqfrY_cTog | I14: 0B4cCTfJeL7_dQ2lLeDdMUDhwX28
A15: MTC SET.pdf | B15: PDF | C15: Session or supporting resource | D15: 2016-2017 Academic Year/2/7/17 Set/MTC SET.pdf | E15: MTC-096 | F15: OFR-005 | G15: Metadata inventoried | H15: https://drive.google.com/file/d/0B4cCTfJeL7_ddWtmMTdJdzg1c3M/view?usp=drivesdk&resourcekey=0-MODq2DeRNzOdnB4Q9bH_VQ | I15: 0B4cCTfJeL7_ddWtmMTdJdzg1c3M
... A31: Pancakes.pdf | B31: PDF | C31: Session or supporting resource | D31: 2016-2017 Academic Year/9/6/16 Pancake Sorting/Pancakes.pdf | E31: MTC-084 | F31: OFR-001 | G31: Metadata inventoried | H31: https://drive.google.com/file/d/0B4cCTfJeL7_dUzJ0UUF1SEJ2Y3c/view?usp=drivesdk&resourcekey=0-afpiECHbahHqSGhOkT6Dsg | I31: 0B4cCTfJeL7_dUzJ0UUF1SEJ2Y3c
A32: How Playing With Math Helps Teachers Better Empathize With Students _ MindShift _ KQED News.pdf | B32: PDF | C32: Session or supporting resource | D32: 2017 Summer Institute/Articles/How Playing With Math Helps Teachers Better Empathize With Students _ MindShift _ KQED News.pdf | G32: Metadata inventoried | H32: https://drive.google.com/file/d/0B4cCTfJeL7_dM0dNNTV5SUNSa0E/view?usp=drivesdk&resourcekey=0-qVJ9teLcNqd4G-DAPyGfGQ | I32: 0B4cCTfJeL7_dM0dNNTV5SUNSa0E
A33: MateasMTMS2016.pdf | B33: PDF | C33: Session or supporting resource | D33: 2017 Summer Institute/Articles/MateasMTMS2016.pdf | G33: Metadata inventoried | H33: https://drive.google.com/file/d/0BxzKPtfFAqkTcjBfZTFLU2ZVUzQ/view?usp=drivesdk&resourcekey=0-D8MmbxmYU4C5QaHzYYVXFA | I33: 0BxzKPtfFAqkTcjBfZTFLU2ZVUzQ
A34: MateasReadingGuide.docx | B34: Word | C34: Session or supporting resource | D34: 2017 Summer Institute/Articles/MateasReadingGuide.docx | G34: Metadata inventoried | H34: https://docs.google.com/document/d/0BxzKPtfFAqkTSGdZcWVuSFlvRDQ/edit?usp=drivesdk&ouid=109901495158487957834&resourcekey=0-A4zIBTvc5Ft40o1CQ2UeCA&rtpof=true&sd=true | I34: 0BxzKPtfFAqkTSGdZcWVuSFlvRDQ
A35: Pennant-ProblemSolvingTeachingNRICH.pdf | B35: PDF | C35: Session or supporting resource | D35: 2017 Summer Institute/Articles/Pennant-ProblemSolvingTeachingNRICH.pdf | G35: Metadata inventoried | H35: https://drive.google.com/file/d/0BxzKPtfFAqkTdmRMTUhIRFM2MWM/view?usp=drivesdk&resourcekey=0-ajxqv7B9Zha4jMsXMhW_wQ | I35: 0BxzKPtfFAqkTdmRMTUhIRFM2MWM
A36: Circle-Square | B36: Google Slides | C36: Session or supporting resource | D36: 2017 Summer Institute/Circle-Square | G36: Metadata inventoried | H36: https://docs.google.com/presentation/d/1PC8elmfASTVP3gvYVM2Yi7Tmpb9RifivsmP6JtTNX9U/edit?usp=drivesdk | I36: 1PC8elmfASTVP3gvYVM2Yi7Tmpb9RifivsmP6JtTNX9U
A37: CSUDH-Lesson-Template.docx | B37: Word | C37: Session or supporting resource | D37: 2017 Summer Institute/CSUDH-Lesson-Template.docx | G37: Metadata inventoried | H37: https://docs.google.com/document/d/0BxzKPtfFAqkTS3NHZzduTmFvMWM/edit?usp=drivesdk&ouid=109901495158487957834&resourcekey=0-3aW77TZlzn5QE0yS5e_f2w&rtpof=true&sd=true | I37: 0BxzKPtfFAqkTS3NHZzduTmFvMWM
A38: LessonSharingTemplate Algebra.pptx | B38: Google Slides | C38: Session or supporting resource | D38: 2017 Summer Institute/LessonSharingTemplate Algebra.pptx | G38: Metadata inventoried | H38: https://docs.google.com/presentation/d/1PuWmbuZBRx0iByro9qraotGEXtoXe9OfbBs0Zfw_eoY/edit?usp=drivesdk | I38: 1PuWmbuZBRx0iByro9qraotGEXtoXe9OfbBs0Zfw_eoY
A39: LessonSharingTemplate.pptx | B39: PowerPoint | C39: Session or supporting resource | D39: 2017 Summer Institute/LessonSharingTemplate.pptx | G39: Metadata inventoried | H39: https://docs.google.com/presentation/d/0BxzKPtfFAqkTUWNwUHNOeV9YSW8/edit?usp=drivesdk&ouid=109901495158487957834&resourcekey=0-G9UW94xH1FV7u83O01V_3g&rtpof=true&sd=true | I39: 0BxzKPtfFAqkTUWNwUHNOeV9YSW8
A40: irritating-things.pdf | B40: PDF | C40: Session or supporting resource | D40: 2017 Summer Institute/Math Mini-Session: Number Bracelets/irritating-things.pdf | G40: Metadata inventoried | H40: https://drive.google.com/file/d/0B4cCTfJeL7_dM2VFMEJha0pSMms/view?usp=drivesdk&resourcekey=0-1dXL1McgreOo5KRfk-lF9A | I40: 0B4cCTfJeL7_dM2VFMEJha0pSMms
A41: Number Bracelets final.ppt | B41: PowerPoint | C41: Session or supporting resource | D41: 2017 Summer Institute/Math Mini-Session: Number Bracelets/Number Bracelets final.ppt | G41: Text unavailable | H41: https://docs.google.com/presentation/d/0B4cCTfJeL7_ddnNuNFRmQ3JKVWs/edit?usp=drivesdk&ouid=109901495158487957834&resourcekey=0-Q9pnQJeCFP1ytdXA5NP0CA&rtpof=true&sd=true | I41: 0B4cCTfJeL7_ddnNuNFRmQ3JKVWs
A42: Number bracelets sheet.pdf | B42: PDF | C42: Session or supporting resource | D42: 2017 Summer Institute/Math Mini-Session: Number Bracelets/Number bracelets sheet.pdf | G42: Metadata inventoried | H42: https://drive.google.com/file/d/0B4cCTfJeL7_dZ1pEYTZoQWdRdUU/view?usp=drivesdk&resourcekey=0-anDVhWQRMIX9jy45xCuQOA | I42: 0B4cCTfJeL7_dZ1pEYTZoQWdRdUU
A43: Numberbracelets.pdf | B43: PDF | C43: Session or supporting resource | D43: 2017 Summer Institute/Math Mini-Session: Number Bracelets/Numberbracelets.pdf | E43: MTC-080 | F43: OFR-013 | G43: Text unavailable | H43: https://drive.google.com/file/d/0B4cCTfJeL7_dZEszNWJvRHBDQkU/view?usp=drivesdk&resourcekey=0-JEkHg4pkfRvfDuTq1EmA7g | I43: 0B4cCTfJeL7_dZEszNWJvRHBDQkU
A44: Mastermind-Blanks.docx | B44: Word | C44: Session or supporting resource | D44: 2017 Summer Institute/Math Session I: Mastermind/Mastermind-Blanks.docx | G44: Metadata inventoried | H44: https://docs.google.com/document/d/0B4cCTfJeL7_dQXFGbXduMVBMZ2c/edit?usp=drivesdk&ouid=109901495158487957834&resourcekey=0-G5jObCIs1D12QUC8M1rDuQ&rtpof=true&sd=true | I44: 0B4cCTfJeL7_dQXFGbXduMVBMZ2c
A45: Mastermind.pptx | B45: PowerPoint | C45: Session or supporting resource | D45: 2017 Summer Institute/Math Session I: Mastermind/Mastermind.pptx | E45: MTC-062 | F45: OFR-012 | G45: Text reviewed | H45: https://docs.google.com/presentation/d/0B4cCTfJeL7_dbkR1d0RQeHRMclU/edit?usp=drivesdk&ouid=109901495158487957834&resourcekey=0-qaLSVqn8XKSsNH4sKGV55g&rtpof=true&sd=true | I45: 0B4cCTfJeL7_dbkR1d0RQeHRMclU
A46: Logic Presentation.pptx | B46: PowerPoint | C46: Session or supporting resource | D46: 2017 Summer Institute/Math Session II: Knights and Knaves/Logic Presentation.pptx | E46: MTC-057 | F46: OFR-011 | G46: Text reviewed | H46: https://docs.google.com/presentation/d/0B2XvpmARE9ZbMnZCM0ZOaHZXSVk/edit?usp=drivesdk&ouid=109901495158487957834&resourcekey=0-V7nKYNXuHYTwHhbaPrZV6w&rtpof=true&sd=true | I46: 0B2XvpmARE9ZbMnZCM0ZOaHZXSVk
A47: Part 1 Knights and Knaves Updated.docx | B47: Word | C47: Session or supporting resource | D47: 2017 Summer Institute/Math Session II: Knights and Knaves/Part 1 Knights and Knaves Updated.docx | G47: Metadata inventoried | H47: https://docs.google.com/document/d/0B2XvpmARE9ZbTTItV19aQWZPd1k/edit?usp=drivesdk&ouid=109901495158487957834&resourcekey=0-ruEUP7nXAsZik6Pgpsw9Ig&rtpof=true&sd=true | I47: 0B2XvpmARE9ZbTTItV19aQWZPd1k
A48: Sprouts.pptx | B48: PowerPoint | C48: Session or supporting resource | D48: 2017 Summer Institute/Math Session III: Sprouts/Sprouts.pptx | E48: MTC-106 | F48: OFR-015 | G48: Text reviewed | H48: https://docs.google.com/presentation/d/0B4cCTfJeL7_dUGgtc2hVRVZkZFU/edit?usp=drivesdk&ouid=109901495158487957834&resourcekey=0-xyg98UR1GYtUjh9gnA0xIg&rtpof=true&sd=true | I48: 0B4cCTfJeL7_dUGgtc2hVRVZkZFU
A49: Instant Insanity.pptx | B49: PowerPoint | C49: Session or supporting resource | D49: 2017 Summer Institute/Math Session IV: Instant Insanity/Instant Insanity.pptx | E49: MTC-045 | F49: OFR-010 | G49: Text reviewed | H49: https://docs.google.com/presentation/d/0B4cCTfJeL7_dZ084MGZNUjVBU1E/edit?usp=drivesdk&ouid=109901495158487957834&resourcekey=0-xqQaukkaqbnIwZhtqkr3HQ&rtpof=true&sd=true | I49: 0B4cCTfJeL7_dZ084MGZNUjVBU1E
A50: Spaghetti Tower Challenge.pptx | B50: PowerPoint | C50: Session or supporting resource | D50: 2017 Summer Institute/Spaghetti Tower Challenge.pptx | E50: MTC-103 | F50: OFR-014 | G50: Text reviewed | H50: https://docs.google.com/presentation/d/0B4cCTfJeL7_dNkFpWHhUbkk5cmM/edit?usp=drivesdk&ouid=109901495158487957834&resourcekey=0-14wM74J9lM5YAVbPFV4nyA&rtpof=true&sd=true | I50: 0B4cCTfJeL7_dNkFpWHhUbkk5cmM
A51: Summer Institute Flyer 2017.pdf | B51: PDF | C51: Agenda / announcement / institute support | D51: 2017 Summer Institute/Summer Institute Flyer 2017.pdf | E51: MTC-045; MTC-057; MTC-062; MTC-080; MTC-103; MTC-106 | F51: OFR-010; OFR-011; OFR-012; OFR-013; OFR-014; OFR-015 | G51: Text reviewed | H51: https://drive.google.com/file/d/0B4cCTfJeL7_dU3lfY2t4ckNZQ3M/view?usp=drivesdk&resourcekey=0-mgNytrTm-j1DMeP0R_Ki6w | I51: 0B4cCTfJeL7_dU3lfY2t4ckNZQ3M
A52: 7th Grade 7NS.1 Alexandra Sluga, Odetta Moore, Richard Tejada (7th Grade) | B52: Google Doc | C52: Participant work / planning resources | D52: 2017 Summer Institute/Upload Lesson Plans Here/7th Grade 7NS.1 Alexandra Sluga, Odetta Moore, Richard Tejada (7th Grade) | G52: Metadata inventoried | H52: https://docs.google.com/document/d/1m4krlUlC_uusHyJKBIFLhBEaiayqUKHkxZ9GwjQb3-4/edit?usp=drivesdk | I52: 1m4krlUlC_uusHyJKBIFLhBEaiayqUKHkxZ9GwjQb3-4
A53: 7th Grade 7RP2A | B53: Google Slides | C53: Participant work / planning resources | D53: 2017 Summer Institute/Upload Lesson Plans Here/7th Grade 7RP2A | G53: Metadata inventoried | H53: https://docs.google.com/presentation/d/1f0rgfEbMdO6oRQP5jLvTyPII5lqajqFPd8BwDUdyE2A/edit?usp=drivesdk | I53: 1f0rgfEbMdO6oRQP5jLvTyPII5lqajqFPd8BwDUdyE2A
A54: 7th Grade 7RP2A | B54: Google Doc | C54: Participant work / planning resources | D54: 2017 Summer Institute/Upload Lesson Plans Here/7th Grade 7RP2A | G54: Metadata inventoried | H54: https://docs.google.com/document/d/1oZeAdy_7snloXGdyhvImQBRZn25TUADn2fSIFJBOlpo/edit?usp=drivesdk | I54: 1oZeAdy_7snloXGdyhvImQBRZn25TUADn2fSIFJBOlpo
A55: Alexandra Sluga, Odetta Moore, Richard Tejada | B55: Google Slides | C55: Participant work / planning resources | D55: 2017 Summer Institute/Upload Lesson Plans Here/Alexandra Sluga, Odetta Moore, Richard Tejada | G55: Metadata inventoried | H55: https://docs.google.com/presentation/d/1ys2u4Tp3JjyxG8-SE7Te3WsY9TuTsBJdGR6dWjVFJfU/edit?usp=drivesdk | I55: 1ys2u4Tp3JjyxG8-SE7Te3WsY9TuTsBJdGR6dWjVFJfU
A56: Completing the Square & Irrational Zeros Lesson | B56: Google Slides | C56: Participant work / planning resources | D56: 2017 Summer Institute/Upload Lesson Plans Here/Completing the Square & Irrational Zeros Lesson | G56: Metadata inventoried | H56: https://docs.google.com/presentation/d/1rc0XdtEq7oAg8nmKBEA9ZBOKihjMva20ZHid096WrTM/edit?usp=drivesdk | I56: 1rc0XdtEq7oAg8nmKBEA9ZBOKihjMva20ZHid096WrTM
A57: Copy of Algebra 2 CTS & Irrational Zeros Lesson | B57: Google Slides | C57: Participant work / planning resources | D57: 2017 Summer Institute/Upload Lesson Plans Here/Copy of Algebra 2 CTS & Irrational Zeros Lesson | G57: Metadata inventoried | H57: https://docs.google.com/presentation/d/14Ve7j4ih8cVcaXW5f4WYseDNVZhJZ1BPa0wwJHFot4w/edit?usp=drivesdk | I57: 14Ve7j4ih8cVcaXW5f4WYseDNVZhJZ1BPa0wwJHFot4w
A58: Copy of Circle-Square Lesson Plan | B58: Google Doc | C58: Participant work / planning resources | D58: 2017 Summer Institute/Upload Lesson Plans Here/Copy of Circle-Square Lesson Plan | G58: Metadata inventoried | H58: https://docs.google.com/document/d/1bPMaXBpLx_1qGPh2nPf50AEUl8ca0232ahgybgnAqc0/edit?usp=drivesdk | I58: 1bPMaXBpLx_1qGPh2nPf50AEUl8ca0232ahgybgnAqc0
A59: Copy of CSUDH Lesson Planning Algebra2 CTS 2018 | B59: Google Doc | C59: Participant work / planning resources | D59: 2017 Summer Institute/Upload Lesson Plans Here/Copy of CSUDH Lesson Planning Algebra2 CTS 2018 | G59: Metadata inventoried | H59: https://docs.google.com/document/d/14DNusMTW3u0SqRgICv8JLZQAJvUg9HqOHpxQ-zrhKJM/edit?usp=drivesdk | I59: 14DNusMTW3u0SqRgICv8JLZQAJvUg9HqOHpxQ-zrhKJM
A60: Copy of Designing A Dream House.pptx | B60: Google Slides | C60: Participant work / planning resources | D60: 2017 Summer Institute/Upload Lesson Plans Here/Copy of Designing A Dream House.pptx | G60: Metadata inventoried | H60: https://docs.google.com/presentation/d/1uyJfK-ZIOMFWjz0I0TaaVGNPF1GIJppE20rXRbKfIc4/edit?usp=drivesdk | I60: 1uyJfK-ZIOMFWjz0I0TaaVGNPF1GIJppE20rXRbKfIc4
A61: Copy of Middle School Math Grade 08-2.pptx | B61: PowerPoint | C61: Participant work / planning resources | D61: 2017 Summer Institute/Upload Lesson Plans Here/Copy of Middle School Math Grade 08-2.pptx | G61: Metadata inventoried | H61: https://docs.google.com/presentation/d/1Q3lRjmucRkguNWQDdTOjVBS3repGMjbQ/edit?usp=drivesdk&ouid=109901495158487957834&rtpof=true&sd=true | I61: 1Q3lRjmucRkguNWQDdTOjVBS3repGMjbQ
A62: Copy of Middle School Math Grade 08-2.pptx | B62: Google Slides | C62: Participant work / planning resources | D62: 2017 Summer Institute/Upload Lesson Plans Here/Copy of Middle School Math Grade 08-2.pptx | G62: Metadata inventoried | H62: https://docs.google.com/presentation/d/1o8aUhHp3NsU88A4GyaWNgWuc94UEOw9cqQ8OZNWBJL4/edit?usp=drivesdk | I62: 1o8aUhHp3NsU88A4GyaWNgWuc94UEOw9cqQ8OZNWBJL4
A63: Copy of Special Right Trialgles | B63: Google Slides | C63: Participant work / planning resources | D63: 2017 Summer Institute/Upload Lesson Plans Here/Copy of Special Right Trialgles | G63: Metadata inventoried | H63: https://docs.google.com/presentation/d/12iVvP0UrLCqso2BctybkPeB0QB8VJBQ1wyyQagGJuk8/edit?usp=drivesdk | I63: 12iVvP0UrLCqso2BctybkPeB0QB8VJBQ1wyyQagGJuk8
... A67: Special Right Trianlges | B67: Google Slides | C67: Participant work / planning resources | D67: 2017 Summer Institute/Upload Lesson Plans Here/Special Right Trianlges | G67: Metadata inventoried | H67: https://docs.google.com/presentation/d/1t8bBSVmztJpRFOvxDjTW80Z7hKWL0YuVNMdnaw1eov0/edit?usp=drivesdk | I67: 1t8bBSVmztJpRFOvxDjTW80Z7hKWL0YuVNMdnaw1eov0
A68: ESTIMATHON Flyer.pdf | B68: PDF | C68: Agenda / announcement / institute support | D68: 2017-2018 Academic Year/10/3/17 Estimathon/ESTIMATHON Flyer.pdf | E68: MTC-027 | F68: OFR-017 | G68: Text reviewed | H68: https://drive.google.com/file/d/0B4cCTfJeL7_dV0lNaHRySThBV1k/view?usp=drivesdk&resourcekey=0-4tLGwO-rngRT5TqyiZh4jw | I68: 0B4cCTfJeL7_dV0lNaHRySThBV1k
A69: Estimathon Spreadsheet.xlsx | B69: application/vnd.openxmlformats-officedocument.spreadsheetml.sheet | C69: Session or supporting resource | D69: 2017-2018 Academic Year/10/3/17 Estimathon/Estimathon Spreadsheet.xlsx | E69: MTC-027 | F69: OFR-017 | G69: Metadata inventoried | H69: https://docs.google.com/spreadsheets/d/0BxzKPtfFAqkTR0RLQ0M3bk12VlE/edit?usp=drivesdk&ouid=109901495158487957834&resourcekey=0-P7Kajjahh6fGF1MW774haQ&rtpof=true&sd=true | I69: 0BxzKPtfFAqkTR0RLQ0M3bk12VlE
A70: Estimathon-rulesandsetupOct2017.pptx | B70: PowerPoint | C70: Session or supporting resource | D70: 2017-2018 Academic Year/10/3/17 Estimathon/Estimathon-rulesandsetupOct2017.pptx | E70: MTC-027 | F70: OFR-017 | G70: Metadata inventoried | H70: https://docs.google.com/presentation/d/0BxzKPtfFAqkTMGxMWWxPTjZ4TEk/edit?usp=drivesdk&ouid=109901495158487957834&resourcekey=0-FAM4GxCMwFUlht-EDz8F5g&rtpof=true&sd=true | I70: 0BxzKPtfFAqkTMGxMWWxPTjZ4TEk
A71: Estimathon.docx | B71: Word | C71: Session or supporting resource | D71: 2017-2018 Academic Year/10/3/17 Estimathon/Estimathon.docx | E71: MTC-027 | F71: OFR-017 | G71: Metadata inventoried | H71: https://docs.google.com/document/d/0BxzKPtfFAqkTeW9vWjZLYU5LMjQ/edit?usp=drivesdk&ouid=109901495158487957834&resourcekey=0-CP8TgFUKScjZ0Jldok9XfQ&rtpof=true&sd=true | I71: 0BxzKPtfFAqkTeW9vWjZLYU5LMjQ
A72: EstimathonRd2.docx | B72: Word | C72: Session or supporting resource | D72: 2017-2018 Academic Year/10/3/17 Estimathon/EstimathonRd2.docx | E72: MTC-027 | F72: OFR-017 | G72: Metadata inventoried | H72: https://docs.google.com/document/d/0BxzKPtfFAqkTLXE3bGQ2cWNLY1E/edit?usp=drivesdk&ouid=109901495158487957834&resourcekey=0-eiuxytOakC3GmKTDeZkNwA&rtpof=true&sd=true | I72: 0BxzKPtfFAqkTLXE3bGQ2cWNLY1E
A73: Candy Game 2.xlsx | B73: Google Sheet | C73: Session or supporting resource | D73: 2017-2018 Academic Year/11/7/17 Candy Sharing/Candy Game 2.xlsx | E73: MTC-014 | F73: OFR-018 | G73: Metadata inventoried | H73: https://docs.google.com/spreadsheets/d/1r4lvNWD4QRZrTQV4p2EOC4zYWQNEkBk1zmKnrn0tceQ/edit?usp=drivesdk | I73: 1r4lvNWD4QRZrTQV4p2EOC4zYWQNEkBk1zmKnrn0tceQ
A74: Candy Game 2.xlsx | B74: application/vnd.openxmlformats-officedocument.spreadsheetml.sheet | C74: Session or supporting resource | D74: 2017-2018 Academic Year/11/7/17 Candy Sharing/Candy Game 2.xlsx | E74: MTC-014 | F74: OFR-018 | G74: Metadata inventoried | H74: https://docs.google.com/spreadsheets/d/1HvQbwqbcees_ruluJuMz_tBHZfciEB2A/edit?usp=drivesdk&ouid=109901495158487957834&rtpof=true&sd=true | I74: 1HvQbwqbcees_ruluJuMz_tBHZfciEB2A
A75: Candy Sharing | B75: Google Slides | C75: Session or supporting resource | D75: 2017-2018 Academic Year/11/7/17 Candy Sharing/Candy Sharing | E75: MTC-014 | F75: OFR-018 | G75: Metadata inventoried | H75: https://docs.google.com/presentation/d/1eCWrYzxXwSho46TB0Azc_apUlWiQMDRYmeZhu8ixmmw/edit?usp=drivesdk | I75: 1eCWrYzxXwSho46TB0Azc_apUlWiQMDRYmeZhu8ixmmw
A76: Candy Sharing Challenges | B76: Google Doc | C76: Session or supporting resource | D76: 2017-2018 Academic Year/11/7/17 Candy Sharing/Candy Sharing Challenges | E76: MTC-014 | F76: OFR-018 | G76: Metadata inventoried | H76: https://docs.google.com/document/d/1eqsi-hxCNA2SB9VE8VMBTrQ48AGNXHSshntmjnHh6_Y/edit?usp=drivesdk | I76: 1eqsi-hxCNA2SB9VE8VMBTrQ48AGNXHSshntmjnHh6_Y
A77: Candy Sharing Flyer.pdf | B77: PDF | C77: Agenda / announcement / institute support | D77: 2017-2018 Academic Year/11/7/17 Candy Sharing/Candy Sharing Flyer.pdf | E77: MTC-014 | F77: OFR-018 | G77: Text reviewed | H77: https://drive.google.com/file/d/0B4cCTfJeL7_dNG1SRGJIUWh4R2c/view?usp=drivesdk&resourcekey=0-jEyNsfAltNj9lA6QZChKPQ | I77: 0B4cCTfJeL7_dNG1SRGJIUWh4R2c
A78: Candy Sharing Outline | B78: Google Doc | C78: Session or supporting resource | D78: 2017-2018 Academic Year/11/7/17 Candy Sharing/Candy Sharing Outline | E78: MTC-014 | F78: OFR-018 | G78: Metadata inventoried | H78: https://docs.google.com/document/d/1Kff7YPynCRn9lfbFzmUwTRq4m7_iMVOLiq63VNJrGi0/edit?usp=drivesdk | I78: 1Kff7YPynCRn9lfbFzmUwTRq4m7_iMVOLiq63VNJrGi0
A79: CandyLong.pdf | B79: PDF | C79: Session or supporting resource | D79: 2017-2018 Academic Year/11/7/17 Candy Sharing/CandyLong.pdf | E79: MTC-014 | F79: OFR-018 | G79: Metadata inventoried | H79: https://drive.google.com/file/d/1kglWCD3Jiz9Iz-iOSMb_r87lZL97rpND/view?usp=drivesdk | I79: 1kglWCD3Jiz9Iz-iOSMb_r87lZL97rpND
... A106: MTC Meetings 2017-2018.pdf | B106: PDF | C106: Agenda / announcement / institute support | D106: 2017-2018 Academic Year/MTC Meetings 2017-2018.pdf | E106: MTC-086; MTC-114 | F106: OFR-020; OFR-021 | G106: Text reviewed | H106: https://drive.google.com/file/d/0B4cCTfJeL7_ddFdsUVdRLXlaTzQ/view?usp=drivesdk&resourcekey=0-JM9t5EGhZrOqAE-8IEEG4g | I106: 0B4cCTfJeL7_ddFdsUVdRLXlaTzQ
A107: MTC-1u-Syllabus.docx | B107: Word | C107: Agenda / announcement / institute support | D107: 2017-2018 Academic Year/MTC-1u-Syllabus.docx | G107: Metadata inventoried | H107: https://docs.google.com/document/d/0B4cCTfJeL7_dNVdXLTZYM21tamM/edit?usp=drivesdk&ouid=109901495158487957834&resourcekey=0-FUSrMrn5y651H8d73md6Iw&rtpof=true&sd=true | I107: 0B4cCTfJeL7_dNVdXLTZYM21tamM
A108: Alt-Algorithmsv2.pdf | B108: PDF | C108: Session or supporting resource | D108: 2018 Summer Institute/Alternate Algorithms/Alt-Algorithmsv2.pdf | G108: Metadata inventoried | H108: https://drive.google.com/file/d/1BB7cPzLWga1X9Pzpuwq_w4-5VuWwLN8h/view?usp=drivesdk | I108: 1BB7cPzLWga1X9Pzpuwq_w4-5VuWwLN8h
A109: Alternate Algorithms Handout.docx | B109: Word | C109: Session or supporting resource | D109: 2018 Summer Institute/Alternate Algorithms/Alternate Algorithms Handout.docx | G109: Metadata inventoried | H109: https://docs.google.com/document/d/1rLOrHkZ6LrNmCPpBkYepVtcc6CN0LnaZ/edit?usp=drivesdk&ouid=109901495158487957834&rtpof=true&sd=true | I109: 1rLOrHkZ6LrNmCPpBkYepVtcc6CN0LnaZ
A110: Alternate Algorithms Modified for pdf Presentation.pdf | B110: PDF | C110: Session or supporting resource | D110: 2018 Summer Institute/Alternate Algorithms/Alternate Algorithms Modified for pdf Presentation.pdf | G110: Metadata inventoried | H110: https://drive.google.com/file/d/1yCZ_HtrozLNlvn_c7Nn2wmAltnejq5A4/view?usp=drivesdk | I110: 1yCZ_HtrozLNlvn_c7Nn2wmAltnejq5A4
A111: Alternate Algorithms.pptx | B111: PowerPoint | C111: Session or supporting resource | D111: 2018 Summer Institute/Alternate Algorithms/Alternate Algorithms.pptx | E111: MTC-004 | F111: OFR-024 | G111: Text reviewed | H111: https://docs.google.com/presentation/d/1u6vBmLM7voR7AKzROirAZsQji_7M82HC/edit?usp=drivesdk&ouid=109901495158487957834&rtpof=true&sd=true | I111: 1u6vBmLM7voR7AKzROirAZsQji_7M82HC
A112: Copy of CSUDH-Lesson-Template.docx | B112: Word | C112: Session or supporting resource | D112: 2018 Summer Institute/Copy of CSUDH-Lesson-Template.docx | G112: Metadata inventoried | H112: https://docs.google.com/document/d/1AwQDYHPolqlIvVV6GsIIBJf5wy1aN2rN/edit?usp=drivesdk&ouid=109901495158487957834&rtpof=true&sd=true | I112: 1AwQDYHPolqlIvVV6GsIIBJf5wy1aN2rN
A113: CSUDH Math Teachers’ Circle Summer Institute.pptx | B113: PowerPoint | C113: Session or supporting resource | D113: 2018 Summer Institute/CSUDH Math Teachers’ Circle Summer Institute.pptx | E113: MTC-004; MTC-082; MTC-123 | F113: OFR-024; OFR-027; OFR-028 | G113: Text reviewed | H113: https://docs.google.com/presentation/d/1w6zbxZ-IP-d8JIvt92fKb847qBwcJWLG/edit?usp=drivesdk&ouid=109901495158487957834&rtpof=true&sd=true | I113: 1w6zbxZ-IP-d8JIvt92fKb847qBwcJWLG
A114: Exploding Dots P1.pptx | B114: PowerPoint | C114: Session or supporting resource | D114: 2018 Summer Institute/Exploding Dots/Exploding Dots P1.pptx | E114: MTC-029 | F114: OFR-026 | G114: Text reviewed | H114: https://docs.google.com/presentation/d/1Xt1UGnUBeJ4dzoaQai64-gyIFavAC_P4/edit?usp=drivesdk&ouid=109901495158487957834&rtpof=true&sd=true | I114: 1Xt1UGnUBeJ4dzoaQai64-gyIFavAC_P4
A115: Exploding Dots Part 2.pptx | B115: PowerPoint | C115: Session or supporting resource | D115: 2018 Summer Institute/Exploding Dots/Exploding Dots Part 2.pptx | E115: MTC-029 | F115: OFR-026 | G115: Text reviewed | H115: https://docs.google.com/presentation/d/1t8J3ddja7Gsl0gzR603MUG_G9H8HWMHH/edit?usp=drivesdk&ouid=109901495158487957834&rtpof=true&sd=true | I115: 1t8J3ddja7Gsl0gzR603MUG_G9H8HWMHH
A116: ExplodingDotsBoxes2.pdf | B116: PDF | C116: Session or supporting resource | D116: 2018 Summer Institute/Exploding Dots/ExplodingDotsBoxes2.pdf | G116: Metadata inventoried | H116: https://drive.google.com/file/d/1eS3-YPpccUgU1uQHkALgx65l1YrZA5IP/view?usp=drivesdk | I116: 1eS3-YPpccUgU1uQHkALgx65l1YrZA5IP
A117: ExplodingDotsWorksheetDay2.pdf | B117: PDF | C117: Session or supporting resource | D117: 2018 Summer Institute/Exploding Dots/ExplodingDotsWorksheetDay2.pdf | G117: Metadata inventoried | H117: https://drive.google.com/file/d/13OshyY3Rvf-6q4WjLr6oM-KN6pTFIWPk/view?usp=drivesdk | I117: 13OshyY3Rvf-6q4WjLr6oM-KN6pTFIWPk
A118: Lesson Planning2018.pptx | B118: Google Slides | C118: Session or supporting resource | D118: 2018 Summer Institute/Lesson Planning2018.pptx | G118: Text reviewed | H118: https://docs.google.com/presentation/d/1pSVrDxmnyRJL8AzIJNSwXKzPW1GUqD5ednEtp6qJZug/edit?usp=drivesdk | I118: 1pSVrDxmnyRJL8AzIJNSwXKzPW1GUqD5ednEtp6qJZug
A119: Lesson Planning2018.pptx | B119: PowerPoint | C119: Session or supporting resource | D119: 2018 Summer Institute/Lesson Planning2018.pptx | G119: Metadata inventoried | H119: https://docs.google.com/presentation/d/1swBIEtI8XLMePIJ4vlAf4QHbBkr1dhff/edit?usp=drivesdk&ouid=109901495158487957834&rtpof=true&sd=true | I119: 1swBIEtI8XLMePIJ4vlAf4QHbBkr1dhff
A120: LessonSharingTemplate.pptx | B120: Google Slides | C120: Session or supporting resource | D120: 2018 Summer Institute/LessonSharingTemplate.pptx | G120: Metadata inventoried | H120: https://docs.google.com/presentation/d/17KXdV3PEd3SS9Sv-3l6gEYbqrICUibbeImt-56rdBcE/edit?usp=drivesdk | I120: 17KXdV3PEd3SS9Sv-3l6gEYbqrICUibbeImt-56rdBcE
A121: LessonSharingTemplate.pptx | B121: PowerPoint | C121: Session or supporting resource | D121: 2018 Summer Institute/LessonSharingTemplate.pptx | G121: Metadata inventoried | H121: https://docs.google.com/presentation/d/1QAPRjSQlQ3nLoAnaYS307mO1rc4-73uC/edit?usp=drivesdk&ouid=109901495158487957834&rtpof=true&sd=true | I121: 1QAPRjSQlQ3nLoAnaYS307mO1rc4-73uC
A122: 1994-PromoteNumberSense-MTMS.pdf | B122: PDF | C122: Session or supporting resource | D122: 2018 Summer Institute/Number Sense Reading/1994-PromoteNumberSense-MTMS.pdf | G122: Metadata inventoried | H122: https://drive.google.com/file/d/1gMCsNQCOGJ1d1EJxmGwe7x0vlVMn_lQG/view?usp=drivesdk | I122: 1gMCsNQCOGJ1d1EJxmGwe7x0vlVMn_lQG
A123: MentalMathBeyond-RubinsteinMT.pdf | B123: PDF | C123: Session or supporting resource | D123: 2018 Summer Institute/Number Sense Reading/MentalMathBeyond-RubinsteinMT.pdf | G123: Metadata inventoried | H123: https://drive.google.com/file/d/16MSYWlWt2jOxVnOJVQMM5fc5U2XZjm-S/view?usp=drivesdk | I123: 16MSYWlWt2jOxVnOJVQMM5fc5U2XZjm-S
A124: questions for article review.docx | B124: Word | C124: Session or supporting resource | D124: 2018 Summer Institute/Number Sense Reading/questions for article review.docx | G124: Metadata inventoried | H124: https://docs.google.com/document/d/10yuWlhBovpeORe-3mTzheF4r1FK99X0b/edit?usp=drivesdk&ouid=109901495158487957834&rtpof=true&sd=true | I124: 10yuWlhBovpeORe-3mTzheF4r1FK99X0b
A125: Tie Folding.pptx | B125: PowerPoint | C125: Session or supporting resource | D125: 2018 Summer Institute/Tie Folding/Tie Folding.pptx | E125: MTC-123 | F125: OFR-028 | G125: Text reviewed | H125: https://docs.google.com/presentation/d/1qex5opjxGqGC-i2oN65td994Ro2i69cr/edit?usp=drivesdk&ouid=109901495158487957834&rtpof=true&sd=true | I125: 1qex5opjxGqGC-i2oN65td994Ro2i69cr
A126: Beating the Lottery Sim Recording Sheet.docx | B126: Word | C126: Session or supporting resource | D126: 2018-2019 Academic Year/10/2 Lottery/Beating the Lottery Sim Recording Sheet.docx | E126: MTC-135 | F126: OFR-030 | G126: Metadata inventoried | H126: https://docs.google.com/document/d/1D74Ub2nCFxkYjMZy7A7WGrdRd26m-E5W/edit?usp=drivesdk&ouid=109901495158487957834&rtpof=true&sd=true | I126: 1D74Ub2nCFxkYjMZy7A7WGrdRd26m-E5W
A127: Beating the Lottery Sim Recording Sheet.pdf | B127: PDF | C127: Session or supporting resource | D127: 2018-2019 Academic Year/10/2 Lottery/Beating the Lottery Sim Recording Sheet.pdf | E127: MTC-135 | F127: OFR-030 | G127: Metadata inventoried | H127: https://drive.google.com/file/d/1fDGE8rNJBEZUW6nVMYRbzWFRZF5MEjr1/view?usp=drivesdk | I127: 1fDGE8rNJBEZUW6nVMYRbzWFRZF5MEjr1
A128: How a Group of MIT Students Gamed the Massachusetts State Lottery - The Atlantic.pdf | B128: PDF | C128: Session or supporting resource | D128: 2018-2019 Academic Year/10/2 Lottery/How a Group of MIT Students Gamed the Massachusetts State Lottery - The Atlantic.pdf | E128: MTC-135 | F128: OFR-030 | G128: Metadata inventoried | H128: https://drive.google.com/file/d/13BPlB_mFuUn3Wd-X_EVCBRDTbKOlYhic/view?usp=drivesdk | I128: 13BPlB_mFuUn3Wd-X_EVCBRDTbKOlYhic
A129: Lottery.pdf | B129: PDF | C129: Session or supporting resource | D129: 2018-2019 Academic Year/10/2 Lottery/Lottery.pdf | E129: MTC-135 | F129: OFR-030 | G129: Metadata inventoried | H129: https://drive.google.com/file/d/1-Ebb9gzoUswNhYoMz41PROvlgHn4fV8n/view?usp=drivesdk | I129: 1-Ebb9gzoUswNhYoMz41PROvlgHn4fV8n
A130: Oct Lottery.pdf | B130: PDF | C130: Session or supporting resource | D130: 2018-2019 Academic Year/10/2 Lottery/Oct Lottery.pdf | E130: MTC-135 | F130: OFR-030 | G130: Text reviewed | H130: https://drive.google.com/file/d/18i5vhFOo7l9IdpyytXgObFTv-3tfjAKr/view?usp=drivesdk | I130: 18i5vhFOo7l9IdpyytXgObFTv-3tfjAKr
A131: Winning the Lottery.pptx | B131: PowerPoint | C131: Session or supporting resource | D131: 2018-2019 Academic Year/10/2 Lottery/Winning the Lottery.pptx | E131: MTC-135 | F131: OFR-030 | G131: Metadata inventoried | H131: https://docs.google.com/presentation/d/1EM3vWm-VAyzWRvb_95RuLML1RwNbcT9R/edit?usp=drivesdk&ouid=109901495158487957834&rtpof=true&sd=true | I131: 1EM3vWm-VAyzWRvb_95RuLML1RwNbcT9R
A132: Blokus and Polyominoes.pptx | B132: PowerPoint | C132: Session or supporting resource | D132: 2018-2019 Academic Year/11/6 Blokus/Blokus and Polyominoes.pptx | E132: MTC-010 | F132: OFR-031 | G132: Metadata inventoried | H132: https://docs.google.com/presentation/d/1yBpdBpnear8YpXzPJlpcm1UWD_5FcwSi/edit?usp=drivesdk&ouid=109901495158487957834&rtpof=true&sd=true | I132: 1yBpdBpnear8YpXzPJlpcm1UWD_5FcwSi
A133: Nov Blokus.pdf | B133: PDF | C133: Session or supporting resource | D133: 2018-2019 Academic Year/11/6 Blokus/Nov Blokus.pdf | E133: MTC-010 | F133: OFR-031 | G133: Text reviewed | H133: https://drive.google.com/file/d/11LMWsczRyxmNkLaP_2Zb_5QISDRARhAM/view?usp=drivesdk | I133: 11LMWsczRyxmNkLaP_2Zb_5QISDRARhAM
A134: Dec Prime Climb.pdf | B134: PDF | C134: Session or supporting resource | D134: 2018-2019 Academic Year/12/4 Prime Climb/Dec Prime Climb.pdf | E134: MTC-032 | F134: OFR-032 | G134: Text reviewed | H134: https://drive.google.com/file/d/16ak6R_4SaZE99Gsze3dcCRqK4fT_51pN/view?usp=drivesdk | I134: 16ak6R_4SaZE99Gsze3dcCRqK4fT_51pN
A135: Prime Climb Updated.pptx | B135: PowerPoint | C135: Session or supporting resource | D135: 2018-2019 Academic Year/12/4 Prime Climb/Prime Climb Updated.pptx | E135: MTC-032 | F135: OFR-032 | G135: Metadata inventoried | H135: https://docs.google.com/presentation/d/1NJG33WYWWG3WsiEKPm4JczaOHFU84sk2/edit?usp=drivesdk&ouid=109901495158487957834&rtpof=true&sd=true | I135: 1NJG33WYWWG3WsiEKPm4JczaOHFU84sk2
A136: Feb Match No Match.pdf | B136: PDF | C136: Session or supporting resource | D136: 2018-2019 Academic Year/2/5 Match or No Match/Feb Match No Match.pdf | E136: MTC-063 | F136: OFR-033 | G136: Text reviewed | H136: https://drive.google.com/file/d/1uC4fIii10Gq-tSJ5Dwhw5_m51EwmJBEC/view?usp=drivesdk | I136: 1uC4fIii10Gq-tSJ5Dwhw5_m51EwmJBEC
... A146: MTC9-2018Sharing.pdf | B146: PDF | C146: Session or supporting resource | D146: 2018-2019 Academic Year/9/4 Fair Sharing/MTC9-2018Sharing.pdf | E146: MTC-131 | F146: OFR-029 | G146: Metadata inventoried | H146: https://drive.google.com/file/d/14wcy7SQk_ryIMEPBab12zeMNfone6-rx/view?usp=drivesdk | I146: 14wcy7SQk_ryIMEPBab12zeMNfone6-rx
A147: CSUDH-Lesson-Template.docx | B147: Word | C147: Session or supporting resource | D147: 2019 Summer Institute/2019 Lesson Planning/CSUDH-Lesson-Template.docx | G147: Metadata inventoried | H147: https://docs.google.com/document/d/1cNlVgApdlDy_cr91oIe1jGgx8w0jAn95/edit?usp=drivesdk&ouid=109901495158487957834&rtpof=true&sd=true | I147: 1cNlVgApdlDy_cr91oIe1jGgx8w0jAn95
A148: Criss Cross.pdf | B148: PDF | C148: Session or supporting resource | D148: 2019 Summer Institute/Criss Cross/Criss Cross.pdf | G148: Metadata inventoried | H148: https://drive.google.com/file/d/17sogJ10SR1pVOrq723-RDdu3_72QKSpI/view?usp=drivesdk | I148: 17sogJ10SR1pVOrq723-RDdu3_72QKSpI
A149: CrissCross.pdf | B149: PDF | C149: Session or supporting resource | D149: 2019 Summer Institute/Criss Cross/CrissCross.pdf | E149: MTC-018 | F149: OFR-037 | G149: Text reviewed | H149: https://drive.google.com/file/d/1wZBu9JjpnZc-_lNGFN8W4n1F9bUGb0un/view?usp=drivesdk | I149: 1wZBu9JjpnZc-_lNGFN8W4n1F9bUGb0un
A150: CrissCrossBoards.pdf | B150: PDF | C150: Session or supporting resource | D150: 2019 Summer Institute/Criss Cross/CrissCrossBoards.pdf | G150: Metadata inventoried | H150: https://drive.google.com/file/d/1cUdfep7SMYNxLNZiHG8PIuadGAjWRHc_/view?usp=drivesdk | I150: 1cUdfep7SMYNxLNZiHG8PIuadGAjWRHc_
A151: Eleusis - Drive.pptx | B151: PowerPoint | C151: Session or supporting resource | D151: 2019 Summer Institute/Eleusis/Eleusis - Drive.pptx | E151: MTC-025 | F151: OFR-038 | G151: Text reviewed | H151: https://docs.google.com/presentation/d/1eWTlS74T3knkqT6S_U0QG41FVvl8RVxy/edit?usp=drivesdk&ouid=109901495158487957834&rtpof=true&sd=true | I151: 1eWTlS74T3knkqT6S_U0QG41FVvl8RVxy
A152: Eleusis Express.pdf | B152: PDF | C152: Session or supporting resource | D152: 2019 Summer Institute/Eleusis/Eleusis Express.pdf | G152: Metadata inventoried | H152: https://drive.google.com/file/d/1vRPQYSwkhtIRvUvy0Ff8U9bmRC2vIlIe/view?usp=drivesdk | I152: 1vRPQYSwkhtIRvUvy0Ff8U9bmRC2vIlIe
A153: Eleusis Sample Rules.docx | B153: Word | C153: Session or supporting resource | D153: 2019 Summer Institute/Eleusis/Eleusis Sample Rules.docx | G153: Metadata inventoried | H153: https://docs.google.com/document/d/1cEyv6EpzYRnSIUzdQZuSBIt-4M5pcVXL/edit?usp=drivesdk&ouid=109901495158487957834&rtpof=true&sd=true | I153: 1cEyv6EpzYRnSIUzdQZuSBIt-4M5pcVXL
A154: Activities.docx | B154: Word | C154: Session or supporting resource | D154: 2019 Summer Institute/Facets of Proof/Activities.docx | G154: Metadata inventoried | H154: https://docs.google.com/document/d/1_NwDyt-uWQHEpoQsZu_ZQZOWyNdgpZ8E/edit?usp=drivesdk&ouid=109901495158487957834&rtpof=true&sd=true | I154: 1_NwDyt-uWQHEpoQsZu_ZQZOWyNdgpZ8E
...

Sheet Read Me
A1: CSUDH Math Teachers’ Circle
A2: Session database. Archive snapshot as of October 1, 2026
A4: Start here | B4: Use Sessions to browse topics. Use Offerings to see each documented date, facilitator, evidence, and review note. Use Resources to locate all files in the shared archive.
A5: Archive source | B5: https://drive.google.com/drive/folders/0B4cCTfJeL7_deW5yOXlJTFZ0MzA?resourcekey=0-JJtNRz7hE4MPx68ceG6DLg
A6: Coverage | B6: 134 session records; 148 documented offerings; 586 files. All 77 academic-year session folders and selected named Summer Institute sessions or activities are represented.
A7: What counts as a session | B7: Routine breaks, meals, check-ins, unnamed warmups, and collaborative lesson planning/sharing are excluded from the session catalog. Participant-created lessons remain in Resources. Named mathematics, pedagogy, and data science activities are included.
A8: Descriptions and tags | B8: Short descriptions and controlled topic tags are editorial summaries of source materials, not original supplied metadata. Agenda-only or inferred descriptions are identified in offering notes.
A9: Repeated sessions | B9: Matching sessions are consolidated across years. Combined sessions remain intact (for example, 4-Game Night); their individual activities are searchable as tags. Exploding Dots Parts 1–2 are one two-part offering.
A10: Date evidence | B10: Dates come from flyers, agendas, slide title pages, or dated folder names, never file creation or modification timestamps. Flyers establish advertised dates, not proof that a meeting took place. Institute windows do not identify an individual session day. Conflicts and partial dates are flagged.
A11: Date precision | B11: Exact date = a specific documented day. Institute window = a range during which the session was offered; it does not establish the session day. Month only = no day is known. Candidate dates remain flagged when sources conflict.
A12: Review flags | B12: 28 offerings need review. Filter Offerings → Review needed = Yes, then read the source notes. Flags include partial dates, conflicts, broad institute windows, and inferred or incomplete session details.
A13: Facilitators | B13: Names appear only where a source explicitly identifies a facilitator or presenter. An author’s name on a borrowed handout does not establish who facilitated the local session.
A14: Resource coverage | B14: All 586 files are inventoried. Text was reviewed for selected flyers, agendas, presentations, and handouts, not every file. Resource-to-session links are assigned when supported; unassigned resources retain full archive paths.
A15: Source access | B15: URLs point to the original Google Drive files and folders, preserving resource keys when available. Access depends on the source owner’s sharing permissions.
... A35: Topology | B35: Connectedness and properties preserved by continuous deformation.
